Workbook

Sheet Июнь
A1: Имя сотрудника | B1: зарплата за март | C1: аванс 1 | D1: аванс 2 | E1: аванс 3 | F1: аванс 4 | G1: аванс 5 | H1: премия | I1: остаток зп на март | J1: ИП | K1: перевод
A2: Ерболат Аружан | B2: 600000 | H2: 0 | I2: =B2-C2-D2-E2-F2-G2 -> 600000
A3: Тұрсынхан Нұртілеу | B3: 600000 | H3: 0 | I3: =B3-C3-D3-E3-F3-G3 -> 600000
A4: Байғазы Салтанат | B4: 700000 | C4: 200000 | H4: 0 | I4: =B4-C4-D4-E4-F4-G4 -> 500000
A5: Расиль Асхат | B5: 700000 | H5: 0 | I5: =B5-C5-D5-E5-F5-G5 -> 700000 | J5: 700000
A6: Эльвира (уборщица) | B6: 120000 | H6: 0 | I6: =B6-C6-D6-E6-F6-G6 -> 120000
A7: Құндызай юрист | B7: 100000 | C7: 50000 | H7: 0 | I7: =B7-C7-D7-E7-F7-G7 -> 50000
A8: Али | B8: 50000 | H8: 0 | I8: =B8-C8-D8-E8-F8-G8 -> 50000
A9: Нурым | B9: 150000 | H9: 0 | I9: =B9-C9-D9-E9-F9-G9 -> 150000 | J9: 150000
A10: Мадияр | B10: 85000 | C10: 150000 | H10: 281677 | I10: =B10-C10-D10-E10-F10-G10+H10 -> 216677
A11: Бейбит | B11: 150000 | C11: 50000 | H11: 0 | I11: =B11-C11-D11-E11-F11-G11 -> 100000
A12: Мадина | B12: 40800 | H12: 122377 | I12: =B12-C12-D12-E12-F12-G12+H12 -> 163177
A13: Анель | B13: 40800 | H13: 113931 | I13: =B13-C13-D13-E13-F13-G13+H13 -> 154731
A14: Малика | B14: 54000 | C14: 50000 | H14: 0 | I14: =B14-C14-D14-E14-F14-G14 -> 4000
A15: Алена Гугл | B15: 200000 | I15: =B15-C15-D15-E15-F15-G15 -> 200000 | J15: 200000
A16: Султан 16 видео | B16: 24000 | I16: =B16-C16-D16-E16-F16-G16 -> 24000
A17: Общ | I17: =I2+I3+I4+I5+I6+I7+I8+I9+I10+I11+I12+I13+I14+I15+I16 -> 3632585 | J17: =J2+J3+J4+J5+J6+J7+J8+J9+J10+J11+J12+J13+J14 -> 850000 | K17: =I17-J17 -> 2782585 | L17: =K17-1000000+J15+J9 -> 2132585
J18: Зп Нурым с аленей | L18: 350000
B23: рабочие дни за март | C23: отработано
A24: Ерболат Аружан | B24: 25 | C24: 25
A25: Тұрсынхан Нұртілеу | B25: 25 | C25: 25 | I25: 1615908
A26: Байғазы Салтанат | B26: 25 | C26: 25 | I26: 2016677
A27: Расиль Асхат | B27: 25 | C27: 25
A28: Эльвира (уборщица) | B28: 25 | C28: 25
A29: Құндызай юрист | B29: 25 | C29: 25
A30: Али | B30: 25 | C30: 15 | D30: с 13 июня
A31: Нурым | B31: 25 | C31: 25
A32: Мадияр | B32: 25 | C32: 25 | E32: с 17 по 20
A33: Бейбит | B33: 25 | C33: 25
A34: Мадина | B34: 25 | C34: 12 | D34: с 17
A35: Анель | B35: 25 | C35: 11 | D35: с 17
A36: Малика | B36: 25 | C36: 9 | D36: с 20
A37: Султан | B37: 25

Sheet Июль
A1: Имя сотрудника | B1: зарплата за июль | C1: аванс 1 | D1: аванс 2 | E1: аванс 3 | F1: аванс 4 | G1: аванс 5 | H1: премия | I1: остаток зп на март
A2: Ерболат Аружан | B2: 1027138 | C2: 700000 | H2: 0 | I2: =B2-C2-D2-E2-F2-G2+H2 -> 327138
A3: Тұрсынхан Нұртілеу | B3: 1027138 | C3: 700000 | H3: 0 | I3: =B3-C3-D3-E3-F3-G3+H3 -> 327138
A4: Байғазы Салтанат | B4: 700000 | C4: 400000 | H4: 0 | I4: =B4-C4-D4-E4-F4-G4+H4 -> 300000
A5: Расиль Асхат | B5: 700000 | H5: 0 | I5: =B5-C5-D5-E5-F5-G5+H5 -> 700000
A6: Эльвира (уборщица) | B6: 120000 | H6: 0 | I6: =B6-C6-D6-E6-F6-G6+H6 -> 120000
A7: Құндызай юрист | B7: 80000 | H7: 0 | I7: =B7-C7-D7-E7-F7-G7+H7 -> 80000
A8: Аружан Дизайнер | B8: 233000 | H8: 0 | I8: =B8-C8-D8-E8-F8-G8+H8 -> 233000
A9: Нурым | B9: 400000 | H9: 0 | I9: =B9-C9-D9-E9-F9-G9+H9 -> 400000
A10: Бейбут | B10: 180000 | C10: 100000 | H10: 0 | I10: =B10-C10-D10-E10-F10-G10+H10 -> 80000
A11: Мадияр | B11: 42240 | H11: 222339 | I11: =B11-C11-D11-E11-F11-G11+H11 -> 264579
A12: Мадина | B12: 63466 | H12: 283278 | I12: =B12-C12-D12-E12-F12-G12+H12 -> 346744
A13: Анель | B13: 81600 | C13: 81600 | H13: 203383 | I13: =B13-C13-D13-E13-F13-G13+H13 -> 203383
A14: Арайлым СММ | B14: 132000 | C14: 85000 | H14: 0 | I14: =B14-C14-D14-E14-F14-G14+H14 -> 47000
A15: Маргулан Видеограф | B15: 200000 | H15: 0 | I15: =B15-C15-D15-E15-F15-G15+H15 -> 200000
A16: Бухгалтер | B16: 150000 | C16: 150000 | H16: 0 | I16: =B16-C16-D16-E16-F16-G16+H16 -> 0
A17: Алена | B17: 200000 | H17: 0 | I17: =B17-C17-D17-E17-F17-G17+H17 -> 200000
A18: Общ | I18: =I2+I3+I4+I5+I6+I7+I8+I9+I11+I10+I12+I13+I14+I15+I16+I17 -> 3828982
H23: =1700000-I23-I24-I4 -> 258294 | I23: =I13+I12+I11 -> 814706 | J23: менеджера
B24: рабочие дни за март | C24: отработано | I24: =I14+I10+I7+I6 -> 327000
A25: Ерболат Аружан | B25: 25 | C25: 25
A26: Тұрсынхан Нұртілеу | B26: 25 | C26: 25
A27: Байғазы Салтанат | B27: 25 | C27: 25 | H27: ПО ИП | I27: =I5+I9+I17+I15+I8 -> 1733000
A28: Расиль Асхат | B28: 25 | C28: 25
A29: Эльвира (уборщица) | B29: 25 | C29: 25
A30: Құндызай юрист | B30: 25 | C30: 25
A31: Аружан Дизайнер | B31: 25 | C31: 21 | D31: с 8 июля
A32: Нурым | B32: 25 | C32: 25
A33: Мадияр | B33: 25 | C33: 25
A34: Бейбут | B34: 25 | C34: 25
A35: Мадина | B35: 25 | C35: 12
A36: Анель | B36: 25 | C36: 11
A37: Арайлым | B37: 25 | C37: 21 | D37: с 8 июля
A38: Маргулан Видеограф | B38: 25 | C38: 21 | D38: с 8 июля
A39: Бухгалтер | B39: 25 | C39: 25
A40: Алена | B40: 25 | C40: 25
A41: Улан актер | B41: 25 | C41: 25
A42: Асель | B42: 25 | C42: 25

Sheet Август
A1: Имя сотрудника | B1: зарплата за март | C1: аванс 1 | D1: аванс 2 | E1: аванс 3 | F1: аванс 4 | G1: не выход на работу | H1: премия | I1: остаток зп на март
A2: Ерболат Аружан | B2: 1000000 | C2: 1000000 | H2: 0 | I2: =B2-C2-D2-E2-F2-G2+H2 -> 0
A3: Тұрсынхан Нұртілеу | B3: 1000000 | C3: 1000000 | H3: 0 | I3: =B3-C3-D3-E3-F3-G3+H3 -> 0
A4: Байғазы Салтанат | B4: 700000 | C4: 285000 | H4: 0 | I4: =B4-C4-D4-E4-F4-G4+H4 -> 415000
A5: Расиль Асхат | B5: 700000 | H5: 0 | I5: =B5-C5-D5-E5-F5-G5+H5 -> 700000
A6: Дархан | B6: 500000 | C6: 200000 | G6: 118181 | H6: 0 | I6: =B6-C6-D6-E6-F6-G6+H6 -> 181819
A7: Эльвира (уборщица) | B7: 120000 | H7: 0 | I7: =B7-C7-D7-E7-F7-G7+H7 -> 120000
A8: Құндызай юрист | B8: 80000 | H8: 0 | I8: =B8-C8-D8-E8-F8-G8+H8 -> 80000
A9: Аружан Дизайнер | B9: 300000 | H9: 0 | I9: =B9-C9-D9-E9-F9-G9+H9 -> 300000
A10: Нурым | B10: 400000 | H10: 0 | I10: =B10-C10-D10-E10-F10-G10+H10 -> 400000
A11: Бейбут | B11: 200000 | H11: 0 | I11: =B11-C11-D11-E11-F11-G11+H11 -> 200000
A12: Мадияр | B12: 81600 | H12: 0 | I12: =B12-C12-D12-E12-F12-G12+H12 -> 81600
A13: Мадина | B13: 81600 | C13: 81600 | H13: 0 | I13: 0
A14: Анель | B14: 81600 | C14: 81600 | H14: 0 | I14: =B14-C14-D14-E14-F14-G14+H14 -> 0
A15: Арайлым СММ | B15: 120000 | C15: 40000 | H15: 0 | I15: =B15-C15-D15-E15-F15-G15+H15 -> 80000
A16: Малика СММ | B16: 120000 | C16: 25000 | H16: 0 | I16: =B16-C16-D16-E16-F16-G16+H16 -> 95000
A17: Маргулан Видеограф | B17: 250000 | H17: 0 | I17: =B17-C17-D17-E17-F17-G17+H17 -> 250000
A18: Бухгалтер | B18: 150000 | F18: 150000 | H18: 0 | I18: =B18-C18-D18-E18-F18-G18+H18 -> 0
A19: Алена | B19: 200000 | H19: 0 | I19: =B19-C19-D19-E19-F19-G19+H19 -> 200000
A20: Улан актер | B20: 170000 | C20: 60000 | H20: 30909 | I20: =B20-C20-D20-E20-F20-G20+H20 -> 140909
A21: Асель | B21: 200000 | H21: 32000 | I21: =B21-C21-D21-E21-F21-G21+H21 -> 232000
A22: Меруерт ом | B22: 300000 | G22: 40909 | H22: 0 | I22: =B22-C22-D22-E22-F22-G22+H22 -> 259091
A23: Бекмухамед | B23: 250000 | G23: 113636 | H23: 0 | I23: =B23-C23-D23-E23-F23-G23+H23 -> 136364
A24: Аруна (ПУ) | B24: 150000 | G24: 150000 | H24: 35714 | I24: =B24-C24-D24-E24-F24-G24+H24 -> 35714
A25: Алмат РОП | B25: 250000 | C25: 56819 | G25: 193181 | I25: =B25-C25-D25-E25-F25-G25+H25 -> 0
A27: Общ | I27: =SUM(I2:I25) -> 3907497
B33: рабочие дни за март | C33: отработано
A34: Ерболат Аружан | B34: 22 | C34: 22
A35: Тұрсынхан Нұртілеу | B35: 22 | C35: 22
A36: Байғазы Салтанат | B36: 22 | C36: 22
A37: Расиль Асхат | B37: 22 | C37: 22
A38: Эльвира (уборщица) | B38: 22 | C38: 22
A39: Құндызай юрист | B39: 22 | C39: 22
A40: Аружан Дизайнер | B40: 22 | C40: 22
A41: Нурым | B41: 22 | C41: 22
A42: Мадияр | B42: 22 | C42: 22
A43: Бейбут | B43: 22 | C43: 22
A44: Мадина | B44: 22 | C44: 22 | D44: с 5 нет
A45: Анель | B45: 22 | C45: 22
A46: Арайлым | B46: 22 | C46: 22
A47: Маргулан Видеограф | B47: 22 | C47: 22
A48: Бухгалтер | B48: 22 | C48: 22
A49: Алена | B49: 22 | C49: 22
A50: Улан актер | B50: 22 | C50: 22 | D50: 4 дня за июль
A51: Асель | B51: 21 | C51: 22 | D51: 4 дня за июль
A52: Дархан | B52: 22 | C52: 22 | D52: с 6 Авг | E52: -8дней
A53: Меруерт | B53: 22 | C53: 22 | D53: с 6 Авг
A54: Бекмухамед | B54: 22 | C54: 22 | D54: с 15 Авг
A55: Аруна (ПУ) | B55: 21 | C55: 22 | D55: с 23 авг

Sheet Сентябрь
A1: Имя сотрудника | B1: зарплата за март | C1: аванс 1 | D1: аванс 2 | E1: аванс 3 | F1: аванс 4 | G1: На ДР | H1: Штрафы | I1: не выход на работу | J1: премия и % | K1: остаток зп на Сентябрь | L1: за 1 день
A2: Ерболат Аружан | B2: 1000000 | C2: 1000000 | I2: =L2*D36 -> 0 | K2: =B2-C2-D2-E2-F2-I2+J2-G2-H2 -> 0 | L2: 40000
A3: Тұрсынхан Нұртілеу | B3: 1000000 | C3: 1000000 | I3: =L3*D37 -> 0 | K3: =B3-C3-D3-E3-F3-I3+J3-G3-H3 -> 0 | L3: 40000
A4: Байғазы Салтанат | B4: 700000 | C4: 300000 | I4: =L4*D38 -> 50001 | K4: =B4-C4-D4-E4-F4-I4+J4-G4-H4 -> 349999 | L4: 33334
A5: Расиль Асхат | B5: 700000 | I5: =L5*D39 -> 50001 | K5: =B5-C5-D5-E5-F5-I5+J5-G5-H5 -> 649999 | L5: 33334
A6: Дархан | B6: 600000 | C6: 450000 | I6: =L6*D40 -> 23809.5 | K6: =B6-C6-D6-E6-F6-I6+J6-G6-H6 -> 126190.5 | L6: 23809.5
A7: Эльвира (уборщица) | B7: 120000 | I7: =L7*D41 -> 0 | K7: =B7-C7-D7-E7-F7-I7+J7-G7-H7 -> 120000 | L7: 4800
A8: Амина Дизайнер | B8: 300000 | I8: =L8*D42 -> 0 | K8: =B8-C8-D8-E8-F8-I8+J8-G8-H8 -> 300000 | L8: 10000
A9: Нурым | B9: 400000 | C9: 33000 | I9: =L9*D43 -> 0 | K9: =B9-C9-D9-E9-F9-I9+J9-G9-H9 -> 367000 | L9: 16000
A10: Бейбут | B10: 200000 | C10: 100000 | I10: =L10*D44 -> 0 | K10: =B10-C10-D10-E10-F10-I10+J10-G10-H10 -> 100000 | L10: 8000
A11: Алмат РОП | B11: 250000 | C11: 150000 | I11: =L11*D45 -> 10000 | J11: =IFERROR(__xludf.DUMMYFUNCTION("IMPORTRANGE(""https://docs.google.com/spreadsheets/d/1JJd44_6b1hsmD6e8liei_zzkkh-GYab6gE4K23IJPVI/edit?gid=0#gid=0&range=J95"",""'Лист1'!J93"")"),450416.17500000075) -> 450416.17 | K11: =B11-C11-D11-E11-F11-I11+J11-G11-H11 -> 540416.18 | L11: 10000
A12: Мадияр | B12: 81600 | C12: 205000 | H12: 10000 | I12: =L12*D46 -> 3264 | J12: =IFERROR(__xludf.DUMMYFUNCTION("IMPORTRANGE(""https://docs.google.com/spreadsheets/d/1JJd44_6b1hsmD6e8liei_zzkkh-GYab6gE4K23IJPVI/edit?gid=0#gid=0&range=L58"",""'Лист1'!K87"")"),451912.5) -> 451912.5 | K12: =B12-C12-D12-E12-F12-I12+J12-G12-H12 -> 315248.5 | L12: 3264
A13: Мадина | B13: 81600 | C13: 205000 | H13: 25000 | I13: =L13*D47 -> 3264 | J13: =IFERROR(__xludf.DUMMYFUNCTION("IMPORTRANGE(""https://docs.google.com/spreadsheets/d/1JJd44_6b1hsmD6e8liei_zzkkh-GYab6gE4K23IJPVI/edit?gid=0#gid=0&range=L58"",""'Лист1'!W87"")"),378242.775) -> 378242.78 | K13: =B13-C13-D13-E13-F13-I13+J13-G13-H13 -> 226578.77 | L13: 3264
A14: Анель | B14: 81600 | C14: 320000 | G14: 30000 | H14: 15000 | I14: =L14*D48 -> 0 | J14: =IFERROR(__xludf.DUMMYFUNCTION("IMPORTRANGE(""https://docs.google.com/spreadsheets/d/1JJd44_6b1hsmD6e8liei_zzkkh-GYab6gE4K23IJPVI/edit?gid=0#gid=0&range=L58"",""'Лист1'!AI87"") "),521093.25) -> 521093.25 | K14: =B14-C14-D14-E14-F14-I14+J14-G14-H14 -> 237693.25 | L14: 3264
A15: Руслан колл центр | B15: 100000 | I15: =L15*D49 -> 52000 | J15: =35000+40000 -> 75000 | K15: =B15-C15-D15-E15-F15-I15+J15-G15-H15 -> 123000 | L15: 4000
A16: Динара Колл центр | B16: 100000 | I16: =L16*D50 -> 84000 | J16: 3000 | K16: =B16-C16-D16-E16-F16-I16+J16-G16-H16 -> 19000 | L16: 4000
A17: Бахадыр Юрист | B17: 50000 | I17: =L17*D51 -> 0 | K17: =B17-C17-D17-E17-F17-I17+J17-G17-H17 -> 50000 | L17: 0
A18: Маргулан Видеограф | B18: 250000 | I18: =L18*D52 -> 0 | K18: =B18-C18-D18-E18-F18-I18+J18-G18-H18 -> 250000 | L18: 10000
A19: Гульжахан Бухгалтер | B19: 150000 | C19: 150000 | I19: =L19*D53 -> 0 | K19: =B19-C19-D19-E19-F19-I19+J19-G19-H19 -> 0 | L19: 6000
A20: Алена | B20: 200000 | I20: =L20*D54 -> 0 | K20: =B20-C20-D20-E20-F20-I20+J20-G20-H20 -> 200000 | L20: 8000
A21: Алуа Ментор Айлтс | B21: 250000 | C21: 5000 | D21: 100000 | I21: =L21*D55 -> 83333.333 | K21: =B21-C21-D21-E21-F21-I21+J21-G21-H21 -> 61666.667 | L21: 11904.762
A22: Гулмира ом | B22: 250000 | C22: 3000 | I22: =L22*D56 -> 10000 | K22: =B22-C22-D22-E22-F22-I22+J22-G22-H22 -> 237000 | L22: 10000
A23: Бекмухамед | B23: 250000 | I23: =L23*D57 -> 47619.048 | K23: =B23-C23-D23-E23-F23-I23+J23-G23-H23 -> 202380.95 | L23: 11904.762
A24: Аруна (ПУ) | B24: 150000 | I24: =L24*D58 -> 0 | K24: =B24-C24-D24-E24-F24-I24+J24-G24-H24 -> 150000 | L24: 7142.8571
A25: Аманжол | B25: 150000 | C25: 75000 | H25: 2000 | I25: =L25*D59 -> 21428.571 | K25: =B25-C25-D25-E25-F25-I25+J25-G25-H25 -> 51571.429 | L25: 7142.8571
A26: Алима | B26: 150000 | K26: =B26-C26-D26-E26-F26-I26+J26-G26-H26 -> 150000 | L26: 7142.8571
A27: Улан | B27: 170000 | K27: =B27-C27-D27-E27-F27-I27+J27-G27-H27 -> 170000
A29: Общ | K29: =SUM(K2:K27) -> 4997744.2 | L29: =SUM(L2:L27) -> 316307.6
K33: 525138
K34: нал | L34: общ
A35: ФИО | B35: рабочие дни за март | C35: отработано | D35: Дни отсутствия | E35: график работы | K35: =K6+K7+K10+K24 -> 496190.5 | L35: =K33-K35 -> 28947.5
A36: Ерболат Аружан | B36: 25 | C36: =B36-D36 -> 25 | E36: 45297
A37: Тұрсынхан Нұртілеу | B37: 25 | C37: =B37-D37 -> 25 | E37: 45297
A38: Байғазы Салтанат | B38: 21 | C38: =B38-D38 -> 19.5 | D38: 1.5 | E38: 45327
A39: Расиль Асхат | B39: 21 | C39: =B39-D39 -> 19.5 | D39: 1.5 | E39: 45327
A40: Дархан | B40: 21 | C40: =B40-D40 -> 20 | D40: 1 | E40: 45327
A41: Эльвира (уборщица) | B41: 25 | C41: =B41-D41 -> 25 | E41: 45297
A42: Амина Дизайнер | B42: 25 | C42: =B42-D42 -> 25 | E42: 45297
A43: Нурым | B43: 25 | C43: =B43-D43 -> 25 | E43: 45297
A44: Бейбут | B44: 25 | C44: =B44-D44 -> 25 | E44: 45297
A45: Алмат РОП | B45: 25 | C45: =B45-D45 -> 24 | D45: 1 | E45: 45297
A46: Мадияр | B46: 25 | C46: =B46-D46 -> 24 | D46: 1 | E46: 45297
A47: Мадина | B47: 25 | C47: =B47-D47 -> 24 | D47: 1 | E47: 45297
A48: Анель | B48: 25 | C48: =B48-D48 -> 25 | E48: 45297
A49: Руслан колл центр | B49: 25 | C49: =B49-D49 -> 12 | D49: 13 | E49: 45297 | F49: с 16 сент
A50: Динара Колл центр | B50: 25 | C50: =B50-D50 -> 4 | D50: 21 | E50: 45297
A51: Бахадыр Юрист | B51: 21 | C51: =B51-D51 -> 21 | E51: -
A52: Маргулан Видеограф | B52: 21 | C52: =B52-D52 -> 21 | E52: 20-25 видео в мес
A53: Гульжахан Бухгалтер | B53: 25 | C53: =B53-D53 -> 25 | E53: 45297
A54: Алена | B54: 25 | C54: 25 | E54: Онлайн
A55: Алуа | B55: 21 | C55: =B55-D55 -> 14 | D55: 7 | E55: 45327 | F55: с 9сент
A56: Гулмира | B56: 25 | C56: =B56-D56 -> 24 | D56: 1 | E56: 45297
A57: Бекмухамед | B57: 21 | C57: =B57-D57 -> 17 | D57: 4 | E57: 45327
A58: Аруна (ПУ) | B58: 21 | C58: =B58-D58 -> 21 | E58: 45327
A59: Аманжол | B59: 21 | C59: =B59-D59 -> 18 | D59: 3 | E59: 45327
A60: Алима | B60: 8 | C60: =B60-D60 -> 3 | D60: 5 | E60: 2 раза в нед
A61: Улан | B61: 21 | C61: =B61-D61 -> 21 | E61: 20-25 видео в мес

Sheet Октябрь
A1: Имя сотрудника | B1: зарплата за март | C1: аванс 1 | D1: аванс 2 | E1: аванс 3 | F1: аванс 4 | G1: На ДР | H1: Штрафы | I1: не выход на работу | J1: премия и % | K1: остаток зп на Сентябрь | L1: за 1 день
A2: Ерболат Аружан | B2: 1250000 | C2: 700000 | D2: 150000 | E2: 200000 | F2: 200000 | I2: =L2*D40 -> 0 | K2: =B2-C2-D2-E2-F2-I2+J2-G2 -> 0 | L2: =B2/B40 -> 48076.923
A3: Тұрсынхан Нұртілеу | B3: 1250000 | C3: 700000 | D3: 140000 | E3: 100000 | F3: 150000 | G3: 10000 | I3: =L3*D41 -> 0 | K3: =B3-C3-D3-E3-F3-I3+J3-G3 -> 150000 | L3: =B3/B41 -> 48076.923
A4: Байғазы Салтанат | B4: 908695 | C4: 350000 | G4: 3000 | I4: =L4*D42 -> 0 | K4: =B4-C4-D4-E4-F4-I4+J4-G4+22227 -> 577922 | L4: =B4/B42 -> 39508.478
A5: Расиль Асхат | B5: 908695 | I5: =L5*D43 -> 0 | K5: =B5-C5-D5-E5-F5-I5+J5-G5 -> 908695 | L5: =B5/B43 -> 302898.33
A6: Дархан | B6: 700000 | C6: 300000 | D6: 400000 | K6: =B6-C6-D6-E6-F6-I6+J6-G6 -> 0 | L6: 23809.5
A7: Эльвира (уборщица) | B7: 150000 | I7: =L7*D45 -> 0 | J7: 30000 | K7: =B7-C7-D7-E7-F7-I7+J7-G7 -> 180000 | L7: =B7/B45 -> 5769.2308
A8: Амина Дизайнер | B8: 300000 | I8: =L8*D46 -> 0 | K8: =B8-C8-D8-E8-F8-I8+J8-G8*4% -> 300000 | L8: =B8/B46 -> 11538.462
A9: Нурым | B9: 250000 | C9: 20000 | I9: =L9*D47 -> 0 | J9: =IFERROR(__xludf.DUMMYFUNCTION("IMPORTRANGE(""https://docs.google.com/spreadsheets/d/1JJd44_6b1hsmD6e8liei_zzkkh-GYab6gE4K23IJPVI/edit?gid=0#gid=0&range=J95"",""'Лист1'!J128"")"),302419.6150000021) -> 302419.61 | K9: =B9-C9-D9-E9-F9-I9+J9-G9 -> 532419.61 | L9: =B9/B47 -> 9615.3846
A10: Бейбут | B10: 200000 | C10: 100000 | I10: =L10*D48 -> 0 | K10: =B10-C10-D10-E10-F10-I10+J10-G10 -> 100000 | L10: =B10/B48 -> 7692.3077
A11: Алмат РОП | B11: 250000 | C11: 310000 | D11: 100000 | G11: 3000 | I11: =L11*D49 -> 9615.3846 | J11: =IFERROR(__xludf.DUMMYFUNCTION("IMPORTRANGE(""https://docs.google.com/spreadsheets/d/1JJd44_6b1hsmD6e8liei_zzkkh-GYab6gE4K23IJPVI/edit?gid=0#gid=0&range=J95"",""'Лист1'!J120"")"),453629.4224999994) -> 453629.42 | K11: =B11-C11-D11-E11-F11-I11+J11-G11 -> 281014.04 | L11: =B11/B49 -> 9615.3846
A12: Камиля Колл центр | B12: 31350 | I12: =L12*D50 -> 0 | J12: 10350 | K12: =B12-C12-D12-E12-F12-I12+J12-G12 -> 41700 | L12: 4000
A13: Мадияр | B13: 81600 | C13: 280000 | G13: 3000 | H13: 6000 | I13: =L13*D50 -> 0 | J13: =IFERROR(__xludf.DUMMYFUNCTION("IMPORTRANGE(""https://docs.google.com/spreadsheets/d/1JJd44_6b1hsmD6e8liei_zzkkh-GYab6gE4K23IJPVI/edit?gid=0#gid=0&range=L58"",""'Лист1'!L114"")"),855647.1) -> 855647.1 | K13: =B13-C13-D13-E13-F13-I13+J13-G13 -> 654247.1 | L13: =B13/B50 -> 3138.4615
A14: Мадина | B14: 81600 | C14: 81600 | K14: =B14-C14-D14-E14-F14-I14+J14-G14 -> 0 | L14: =B14/B51 -> 3138.4615
A15: Анель | B15: 81600 | C15: 310000 | D15: 81600 | E15: 10000 | G15: 3000 | H15: 35000 | I15: =L15*D52 -> 0 | J15: =IFERROR(__xludf.DUMMYFUNCTION("IMPORTRANGE(""https://docs.google.com/spreadsheets/d/1JJd44_6b1hsmD6e8liei_zzkkh-GYab6gE4K23IJPVI/edit?gid=0#gid=0&range=L58"",""'Лист1'!AI114"") "),511784.2125) -> 511784.21 | K15: =B15-C15-D15-E15-F15-I15+J15-G15 -> 188784.21 | L15: =B15/B52 -> 3138.4615
A16: Динара колл центр | B16: 100000 | G16: 2000 | I16: =L16*D53 -> 0 | J16: =IFERROR(__xludf.DUMMYFUNCTION("IMPORTRANGE(""https://docs.google.com/spreadsheets/d/1JJd44_6b1hsmD6e8liei_zzkkh-GYab6gE4K23IJPVI/edit?gid=0#gid=0&range=L58"",""'Лист1'!BG114"")+21600"),117858.375) -> 117858.38 | K16: =B16-C16-D16-E16-F16-I16+J16-G16 -> 215858.38 | L16: =B16/B53 -> 3846.1538
A17: СММ Абылай | B17: 200000 | I17: =L17*D54 -> 0 | K17: =B17-C17-D17-E17-F17-I17+J17-G17 -> 200000 | L17: =B17/B54 -> 7692.3077
A18: СММ Еркежан | B18: 100000 | C18: 100000 | I18: =L18*D55 -> 0 | K18: =B18-C18-D18-E18-F18-I18+J18-G18 -> 0 | L18: =B18/B55 -> 3846.1538
A19: Маргулан Видеограф | B19: 250000 | I19: =L19*D56 -> 0 | K19: =B19-C19-D19-E19-F19-I19+J19-G19 -> 250000 | L19: =B19/B56 -> 10869.565
A20: Гульжахан Бухгалтер | B20: 150000 | C20: 150000 | I20: =L20*D57 -> 0 | K20: =B20-C20-D20-E20-F20-I20+J20-G20 -> 0 | L20: =B20/B57 -> 5769.2308
A21: Алена | B21: 200000 | I21: =L21*D58 -> 0 | K21: =B21-C21-D21-E21-F21-I21+J21-G21 -> 200000 | L21: =B21/B58 -> 7692.3077
A22: Алуа Ментор Айлтс | B22: 250000 | C22: 125000 | G22: 2000 | I22: =L22*D59 -> 0 | K22: =B22-C22-D22-E22-F22-I22+J22-G22 -> 123000 | L22: =B22/B59 -> 11363.636
A23: Гулмира ом | B23: 250000 | C23: 20000 | G23: 3000 | I23: =L23*D60 -> 4807.6923 | K23: =B23-C23-D23-E23-F23-I23+J23-G23 -> 222192.31 | L23: =B23/B60 -> 9615.3846
A24: Бекмухамед | B24: 250000 | I24: =L24*D61 -> 0 | K24: =B24-C24-D24-E24-F24-I24+J24-G24 -> 250000 | L24: =B24/B61 -> 11363.636
A25: Аруна (ПУ) | B25: 200000 | G25: 3000 | I25: =L25*D62 -> 0 | K25: =B25-C25-D25-E25-F25-I25+J25-G25 -> 197000 | L25: =B25/B62 -> 9090.9091
A26: Аманжол | B26: 250000 | C26: 150000 | G26: 2000 | I26: =L26*D63 -> 11363.636 | J26: 13364 | K26: =B26-C26-D26-E26-F26-I26+J26-G26 -> 100000.36 | L26: =B26/B63 -> 11363.636
A27: Алима | B27: 150000 | I27: =L27*D64 -> 0 | K27: =B27-C27-D27-E27-F27-I27+J27-G27 -> 150000 | L27: =B27/B64 -> 18750
A28: Асель колл центр | I28: =L28*D65 -> 0 | K28: =B28-C28-D28-E28-F28-I28+J28-G28 -> 0 | L28: =B28/B65 -> 0
A29: Бахадыр Юрист | B29: 70000 | C29: 40000 | I29: =L29*D67 -> 0 | K29: =B29-C29-D29-E29-F29-I29+J29-G29 -> 30000 | L29: =B29/B67 -> 3181.8182
A30: Улан | B30: 170000 | K30: =B30-C30-D30-E30-F30-I30+J30-G30 -> 170000 | L30: =B30/B66 -> 6538.4615
A31: Асель SAT | B31: 250000 | I31: =L31*D68 -> 90909.091 | K31: =B31-C31-D31-E31-F31-I31+J31-G31 -> 159090.91 | L31: =B31/B68 -> 11363.636
A33: Общ | K33: =SUM(K2:K31) -> 6181923.9 | L33: =SUM(L2:L28) -> 631279.23
A39: ФИО | B39: рабочие дни за март | C39: отработано | D39: Дни отсутствия | E39: график работы
A40: Ерболат Аружан | B40: 26 | C40: =B40-D40 -> 26 | E40: 45297
A41: Тұрсынхан Нұртілеу | B41: 26 | C41: =B41-D41 -> 26 | E41: 45297
A42: Байғазы Салтанат | B42: 23 | C42: =B42-D42 -> 23 | E42: 45327
A43: Расиль Асхат | B43: 3 | C43: =B43-D43 -> 3 | E43: 45327
A44: Дархан | B44: 22 | C44: =B44-D44 -> 21 | D44: 1 | E44: 45327
A45: Эльвира (уборщица) | B45: 26 | C45: =B45-D45 -> 26 | E45: 45297
A46: Амина Дизайнер | B46: 26 | C46: =B46-D46 -> 26 | E46: 45297
A47: Нурым | B47: 26 | C47: =B47-D47 -> 26 | E47: 45297
A48: Бейбут | B48: 26 | C48: =B48-D48 -> 26 | E48: 45297
A49: Алмат РОП | B49: 26 | C49: =B49-D49 -> 25 | D49: 1 | E49: 45297
A50: Мадияр | B50: 26 | C50: =B50-D50 -> 26 | E50: 45297
A51: Мадина | B51: 26 | C51: =B51-D51 -> 8 | D51: 18 | E51: 45297
A52: Анель | B52: 26 | C52: =B52-D52 -> 26 | E52: 45297
A53: Динара колл центр | B53: 26 | C53: =B53-D53 -> 26 | E53: 45297 | F53: с 16 сент
A54: SMM Абылай | B54: 26 | C54: =B54-D54 -> 26 | E54: 45297
A55: SMM Еркежан | B55: 26 | C55: =B55-D55 -> 26 | E55: 45297
A56: Маргулан Видеограф | B56: 23 | C56: =B56-D56 -> 23 | E56: 20-25 видео в мес
A57: Гульжахан Бухгалтер | B57: 26 | C57: =B57-D57 -> 26 | E57: 45297
A58: Алена | B58: 26 | C58: 25 | E58: Онлайн
A59: Алуа | B59: 22 | C59: =B59-D59 -> 22 | E59: 45327 | F59: с 9сент
A60: Гулмира | B60: 26 | C60: =B60-D60 -> 25.5 | D60: 0.5 | E60: 45297
A61: Бекмухамед | B61: 22 | C61: =B61-D61 -> 22 | E61: 45327
A62: Аруна (ПУ) | B62: 22 | C62: =B62-D62 -> 22 | E62: 45327
A63: Аманжол | B63: 22 | C63: =B63-D63 -> 21 | D63: 1 | E63: 45327
A64: Алима | B64: 8 | C64: =B64-D64 -> 8 | E64: 2 раза в нед
A65: Асель колл центр | B65: 26 | C65: =B65-D65 -> 8 | D65: 18 | E65: 45297
A66: Улан | B66: 26 | C66: =B66-D66 -> 26 | E66: 45297
A67: Бахадыр | B67: 22 | C67: =B67-D67 -> 22 | E67: 45327
A68: Асель SAT | B68: 22 | C68: =B68-D68 -> 14 | D68: 8 | E68: 45327

Sheet Ноябрь
A1: Имя сотрудника | B1: зарплата за март | C1: аванс 1 | D1: аванс 2 | E1: аванс 3 | F1: аванс 4 | G1: На ДР | H1: Штрафы | I1: не выход на работу | J1: премия и % | K1: остаток зп на Сентябрь | L1: за 1 день
A2: Ерболат Аружан | B2: 1250000 | C2: 300000 | D2: 100000 | E2: 150000 | F2: 300000 | I2: =L2*D39 -> 0 | K2: =B2-C2-D2-E2-F2-I2+J2-G2 -> 400000 | L2: =B2/B39 -> 48076.923
A3: Тұрсынхан Нұртілеу | B3: 1250000 | C3: 50000 | D3: 150000 | E3: 200000 | F3: 450000 | I3: =L3*D40 -> 0 | K3: =B3-C3-D3-E3-F3-I3+J3-G3 -> 400000 | L3: =B3/B40 -> 48076.923
A4: Байғазы Салтанат | B4: 1000000 | G4: 10000 | I4: =L4*D41 -> 0 | K4: =B4-C4-D4-E4-F4-I4+J4-G4 -> 990000 | L4: =B4/B41 -> 47619.048
A5: Расиль Асхат | B5: 1000000 | G5: 10000 | I5: =L5*D42 -> 0 | K5: =B5-C5-D5-E5-F5-I5+J5-G5 -> 990000 | L5: =B5/B42 -> 47619.048
A6: Аруна (ПУ) | B6: 200000 | G6: 3000 | I6: =L6*D43 -> 9523.8095 | K6: =B6-C6-D6-E6-F6-I6+J6-G6 -> 187476.19 | L6: =B6/B43 -> 9523.8095
A7: Алуа Ментор Айлтс | B7: 250000 | G7: 3000 | I7: =L7*D44 -> 0 | J7: 85000 | K7: =B7-C7-D7-E7-F7-I7+J7-G7 -> 332000 | L7: =B7/B44 -> 11904.762
A8: Бекмухамед | B8: 250000 | I8: =L8*D45 -> 0 | K8: =B8-C8-D8-E8-F8-I8+J8-G8 -> 250000 | L8: =B8/B45 -> 11904.762
A9: Асель SAT | B9: 215000 | G9: 3000 | I9: =L9*D46 -> 0 | K9: =B9-C9-D9-E9-F9-I9+J9-G9 -> 212000 | L9: =B9/B46 -> 10238.095 | N9: =K4+K5+K21+K26 -> 2599159.9
A10: Алима | B10: 150000 | I10: =L10*D47 -> 0 | K10: =B10-C10-D10-E10-F10-I10+J10-G10 -> 150000 | L10: =B10/B47 -> 18750
A11: Аманжол Математика | B11: 250000 | C11: 150000 | D11: 88095 | I11: =L11*D48 -> 11904.762 | K11: =B11-C11-D11-E11-F11-I11+J11-G11 -> 0.23809524 | L11: =B11/B48 -> 11904.762
A12: Асем Психолог | B12: 150000 | I12: 0 | K12: =B12-C12-D12-E12-F12-I12+J12-G12 -> 150000 | L12: =B12/B49 -> 7142.8571
A13: Бейбут | B13: 200000 | C13: 100000 | I13: =L13*D50 -> 0 | K13: =B13-C13-D13-E13-F13-I13+J13-G13 -> 100000 | L13: =B13/B50 -> 9523.8095
A14: Алмат Ком дир | B14: 590000 | C14: 250000 | D14: 120000 | E14: 100000 | F14: 60000 | G14: 5000 | I14: =L14*D51 -> 0 | J14: 15000 | K14: =B14-C14-D14-E14-F14-I14+J14-G14 -> 70000 | L14: =B14/B51 -> 22692.308 | P14: =284659-187476 -> 97183
A15: Гульнара РОП | B15: 200000 | I15: =L15*D52 -> 100000 | J15: =IFERROR(__xludf.DUMMYFUNCTION("IMPORTRANGE(""https://docs.google.com/spreadsheets/d/1JJd44_6b1hsmD6e8liei_zzkkh-GYab6gE4K23IJPVI/edit?gid=0#gid=0&range=J95"",""'Лист1'!K149"")+39015"),147934.75499999934) -> 147934.76 | K15: =B15-C15-D15-E15-F15-I15+J15-G15 -> 247934.76 | L15: =B15/B52 -> 7692.3077
A16: Мадияр | B16: 81600 | G16: 3000 | I16: =L16*D53 -> 18830.769 | J16: =IFERROR(__xludf.DUMMYFUNCTION("IMPORTRANGE(""https://docs.google.com/spreadsheets/d/1JJd44_6b1hsmD6e8liei_zzkkh-GYab6gE4K23IJPVI/edit?gid=0#gid=0&range=J95"",""'Лист1'!K141"")"),307962.9) -> 307962.9 | K16: =B16-C16-D16-E16-F16-I16+J16-G16 -> 367732.13 | L16: =B16/B53 -> 3138.4615
A17: Мадина колл центр | I17: =L17*D54 -> 0 | J17: =IFERROR(__xludf.DUMMYFUNCTION("IMPORTRANGE(""https://docs.google.com/spreadsheets/d/1JJd44_6b1hsmD6e8liei_zzkkh-GYab6gE4K23IJPVI/edit?gid=0#gid=0&range=J95"",""'Лист1'!W141"")"),65025.0) -> 65025 | K17: 0 | L17: =B17/B54 -> 0
A18: Анель | B18: 81600 | C18: 310000 | G18: 3500 | I18: =L18*D55 -> 0 | J18: =IFERROR(__xludf.DUMMYFUNCTION("IMPORTRANGE(""https://docs.google.com/spreadsheets/d/1JJd44_6b1hsmD6e8liei_zzkkh-GYab6gE4K23IJPVI/edit?gid=0#gid=0&range=J95"",""'Лист1'!AI141"")"),227892.375) -> 227892.38 | K18: =B18-C18-D18-E18-F18-I18+J18-G18 -> -4007.625 | L18: =B18/B55 -> 3138.4615
A19: Динара колл центр | B19: 100000 | G19: 3000 | I19: =L19*D56 -> 0 | J19: =IFERROR(__xludf.DUMMYFUNCTION("IMPORTRANGE(""https://docs.google.com/spreadsheets/d/1JJd44_6b1hsmD6e8liei_zzkkh-GYab6gE4K23IJPVI/edit?gid=0#gid=0&range=J95"",""'Лист1'!BG141"")"),139071.24000000008) -> 139071.24 | K19: =B19-C19-D19-E19-F19-I19+J19-G19 -> 236071.24 | L19: =B19/B56 -> 3846.1538
A20: Айгерим колл центр | B20: 43076 | C20: 43076 | J20: =IFERROR(__xludf.DUMMYFUNCTION("IMPORTRANGE(""https://docs.google.com/spreadsheets/d/1JJd44_6b1hsmD6e8liei_zzkkh-GYab6gE4K23IJPVI/edit?gid=0#gid=0&range=J95"",""'Лист1'!BS141"")"),0.0) -> 0 | K20: =B20-C20-D20-E20-F20-I20+J20-G20 -> 0 | L20: =B20/B57 -> 1656.7692
A21: Нурым | B21: 250000 | G21: 3000 | I21: =L21*D58 -> 0 | J21: =IFERROR(__xludf.DUMMYFUNCTION("IMPORTRANGE(""https://docs.google.com/spreadsheets/d/1JJd44_6b1hsmD6e8liei_zzkkh-GYab6gE4K23IJPVI/edit?gid=0#gid=0&range=J95"",""'Лист1'!I147"")"),172159.8500000015) -> 172159.85 | K21: =B21-C21-D21-E21-F21-I21+J21-G21 -> 419159.85 | L21: =B21/B58 -> 9615.3846
A22: СММ Абылай | B22: 200000 | G22: 3000 | I22: =L22*D59 -> 0 | K22: =B22-C22-D22-E22-F22-I22+J22-G22 -> 197000 | L22: =B22/B59 -> 7692.3077 | Q22: =K14+K15+K23+K24+K25+K30+K28+15000+K9 -> 1504934.8
A23: Маргулан Видеограф | B23: 250000 | I23: =L23*D60 -> 0 | K23: =B23-C23-D23-E23-F23-I23+J23-G23 -> 250000 | L23: =B23/B60 -> 10000
A24: Амина Дизайнер | B24: 300000 | I24: =L24*D61 -> 0 | K24: =B24-C24-D24-E24-F24-I24+J24-G24 -> 300000 | L24: =B24/B61 -> 11538.462
A25: Улан | B25: 170000 | I25: =L25*D62 -> 0 | K25: =B25-C25-D25-E25-F25-I25+J25-G25 -> 170000 | L25: =B25/B62 -> 11333.333
A26: Алена | B26: 200000 | I26: =L26*D63 -> 0 | K26: =B26-C26-D26-E26-F26-I26+J26-G26 -> 200000 | L26: =B26/B63 -> 7692.3077
A27: Гулмира ом | B27: 300000 | G27: 3000 | I27: =L27*D64 -> 11538.462 | K27: =B27-C27-D27-E27-F27-I27+J27-G27 -> 285461.54 | L27: =B27/B64 -> 11538.462
A28: Гульжахан Бухгалтер | B28: 150000 | C28: 150000 | I28: =L28*D65 -> 0 | K28: =B28-C28-D28-E28-F28-I28+J28-G28 -> 0 | L28: =B28/B65 -> 7142.8571
A29: Бахадыр Юрист | B29: 70000 | I29: =L29*D66 -> 0 | K29: =B29-C29-D29-E29-F29-I29+J29-G29 -> 70000 | L29: =B29/B66 -> 3333.3333
A30: Эльвира (уборщица) | B30: 240000 | I30: =L30*D67 -> 0 | K30: =B30-C30-D30-E30-F30-I30+J30-G30 -> 240000 | L30: =B30/B67 -> 11428.571
A31: Ханаби | B31: 150000 | I31: =L31*D68 -> 121428.57 | J31: 1429 | K31: =B31-C31-D31-E31-F31-I31+J31-G31 -> 30000.429 | L31: =B31/B68 -> 7142.8571
A32: Общ | K32: =SUM(K2:K31) -> 7240828.7
A38: ФИО | B38: рабочие дни за март | C38: отработано | D38: Дни отсутствия | E38: график работы
A39: Ерболат Аружан | B39: 26 | C39: =B39-D39 -> 26 | D39: 0 | E39: 45297
A40: Тұрсынхан Нұртілеу | B40: 26 | C40: =B40-D40 -> 26 | D40: 0 | E40: 45297
A41: Байғазы Салтанат | B41: 21 | C41: =B41-D41 -> 21 | D41: 0 | E41: 45327
A42: Расиль Асхат | B42: 21 | C42: =B42-D42 -> 21 | D42: 0 | E42: 45327
A43: Аруна (ПУ) | B43: 21 | C43: =B43-D43 -> 20 | D43: 1 | E43: 45327 | H43: 260
A44: Алуа Ментор Айлтс | B44: 21 | C44: =B44-D44 -> 21 | D44: 0 | E44: 45327
A45: Бекмухамед | B45: 21 | C45: =B45-D45 -> 21 | D45: 0 | E45: 45327
A46: Асель SAT | B46: 21 | C46: =B46-D46 -> 21 | D46: 0 | E46: 45327 | F46: с 21 125000 зп | G46: 35700 | H46: 178500
A47: Алима | B47: 8 | C47: =B47-D47 -> 8 | D47: 0 | E47: 45297
A48: Аманжол Математика | B48: 21 | C48: =B48-D48 -> 20 | D48: 1 | E48: 45327
A49: Асем психолог | B49: 21 | C49: =B49-D49 -> 21 | D49: 0 | E49: 45327
A50: Бейбут | B50: 21 | C50: =B50-D50 -> 21 | D50: 0 | E50: 45327
A51: Алмат РОП | B51: 26 | C51: =B51-D51 -> 26 | D51: 0 | E51: 45297
A52: Гульнара РОП | B52: 26 | C52: =B52-D52 -> 13 | D52: 13 | E52: 45297 | F52: с13ого
A53: Мадияр | B53: 26 | C53: =B53-D53 -> 20 | D53: 6 | E53: 45297 | H53: 590
A54: Мадина колл центр | B54: 26 | C54: 9 | D54: 0 | E54: 45297
A55: Анель | B55: 26 | C55: =B55-D55 -> 26 | D55: 0 | E55: 45297 | F55: до 28го
A56: Динара колл центр | B56: 26 | C56: =B56-D56 -> 26 | D56: 0 | E56: 45297
A57: Айгерим колл центр | B57: 26 | C57: =B57-D57 -> 14 | D57: 12 | E57: 45297
A58: Нурым | B58: 26 | C58: =B58-D58 -> 26 | D58: 0 | E58: 45297
A59: СММ Абылай | B59: 26 | C59: =B59-D59 -> 26 | D59: 0 | E59: 45297
A60: Маргулан Видеограф | B60: 25 | C60: =B60-D60 -> 25 | D60: 0 | E60: 45297
A61: Амина Дизайнер | B61: 26 | C61: =B61-D61 -> 26 | D61: 0 | E61: 45297
A62: Улан | B62: 15 | C62: =B62-D62 -> 15 | D62: 0 | E62: 45327
A63: Алена | B63: 26 | C63: =B63-D63 -> 26 | D63: 0 | E63: 45297
A64: Гулмира ом | B64: 26 | C64: =B64-D64 -> 25 | D64: 1 | E64: 45297
A65: Гульжахан Бухгалтер | B65: 21 | C65: =B65-D65 -> 21 | D65: 0 | E65: 45327
A66: Бахадыр Юрист | B66: 21 | C66: =B66-D66 -> 21 | D66: 0 | E66: 45327
A67: Эльвира (уборщица) | B67: 21 | C67: =B67-D67 -> 21 | D67: 0 | E67: 45327
A68: Ханаби | B68: 21 | C68: =B68-D68 -> 4 | D68: 17 | E68: 45327

Sheet Декабрь
A1: Имя сотрудника | B1: зарплата за март | C1: аванс 1 | D1: аванс 2 | E1: аванс 3 | F1: аванс 4 | G1: На ДР | H1: Штрафы | I1: не выход на работу | J1: премия и % | K1: остаток зп на Сентябрь | L1: за 1 день
A2: Ерболат Аружан | B2: 550000 | D2: 200000 | E2: 170000 | F2: 100000 | I2: =L2*D37 -> 0 | K2: =B2-C2-D2-E2-F2-I2+J2-G2 -> 80000 | L2: =B2/B37 -> 27500
A3: Тұрсынхан Нұртілеу | B3: 550000 | C3: 24770 | D3: 200000 | E3: 150000 | F3: 150000 | I3: =L3*D38 -> 0 | K3: =B3-C3-D3-E3-F3-I3+J3-G3 -> 25230 | L3: =B3/B38 -> 27500
A4: Байғазы Салтанат | B4: 1000000 | C4: 24770 | D4: 200000 | I4: =L4*D39 -> 95238.095 | K4: =B4-C4-D4-E4-F4-I4+J4-G4 -> 679991.9 | L4: =B4/B39 -> 47619.048 | O4: =K4+K5+K6+K15+16500 -> 1372491.9
A5: Расиль Асхат | B5: 450000 | I5: =L5*D40 -> 0 | K5: =B5-C5-D5-E5-F5-I5+J5-G5 -> 450000 | L5: =B5/B40 -> 21428.571
A6: Алуа Ментор Айлтс | B6: 85000 | I6: =L6*D41 -> 0 | K6: =B6-C6-D6-E6-F6-I6+J6-G6 -> 85000 | L6: =B6/B41 -> 4047.619
A7: Бекмухамед | B7: 250000 | C7: 24770 | I7: =L7*D42 -> 59523.81 | K7: =B7-C7-D7-E7-F7-I7+J7-G7 -> 165706.19 | L7: =B7/B42 -> 11904.762
A8: Алима | B8: 150000 | I8: =L8*D43 -> 0 | K8: =B8-C8-D8-E8-F8-I8+J8-G8 -> 150000 | L8: =B8/B43 -> 18750
A9: Ханабиль | B9: 150000 | C9: 24770 | I9: =L9*D44 -> 28571.429 | J9: 25000 | K9: =B9-C9-D9-E9-F9-I9+J9-G9 -> 121658.57 | L9: =B9/B44 -> 7142.8571
A10: Асем Психолог | B10: 230000 | C10: 24770 | I10: =L10*D45 -> 32857.143 | J10: 90000 | K10: =B10-C10-D10-E10-F10-I10+J10-G10 -> 262372.86 | L10: =B10/B45 -> 10952.381 | P10: 1000000
A11: Асель | B11: 168000 | C11: =24770-16000 -> 8770 | I11: =L11*D46 -> 0 | K11: =B11-C11-D11-E11-F11-I11+J11-G11 -> 159230 | L11: =B11/B46 -> 8000 | P11: =K10+K11+K14+K27+K28+K9+Q11 -> 912461.43 | Q11: 79200
A12: Диас международн отд | B12: 350000 | I12: =L12*D47 -> 0 | J12: 50000 | K12: =B12-C12-D12-E12-F12-I12+J12-G12 -> 400000 | L12: =B12/B47 -> 16666.667 | M12: =L12*3 -> 50000 | P12: =P10-P11 -> 87538.571
A13: Султан | B13: 76500 | C13: 76500 | I13: =L13*D48 -> 0 | K13: =B13-C13-D13-E13-F13-I13+J13-G13 -> 0 | L13: =B13/B48 -> 3642.8571
A14: Бейбут | B14: 200000 | C14: 100000 | I14: =L14*D49 -> 0 | K14: =B14-C14-D14-E14-F14-I14+J14-G14 -> 100000 | L14: =B14/B49 -> 9523.8095
A15: Алмат Ком дир | B15: 641000 | C15: 100000 | D15: 150000 | E15: 150000 | F15: 100000 | I15: =L15*D50 -> 0 | K15: =B15-C15-D15-E15-F15-I15+J15-G15 -> 141000 | L15: =B15/B50 -> 30523.81
A16: Мадияр РОП | B16: 200000 | C16: 49540 | I16: =L16*D51 -> 0 | J16: =IFERROR(__xludf.DUMMYFUNCTION("IMPORTRANGE(""https://docs.google.com/spreadsheets/d/1JJd44_6b1hsmD6e8liei_zzkkh-GYab6gE4K23IJPVI/edit?gid=0#gid=0&range=J95"",""'Лист1'!K178"")"),183950.4824999998) -> 183950.48 | K16: =B16-C16-D16-E16-F16-I16+J16-G16 -> 334410.48 | L16: =B16/B51 -> 8000
A17: Темирлан РОП | B17: 200000 | C17: 40000 | D17: 30000 | E17: 50000 | I17: =L17*D52 -> 24000 | K17: =B17-C17-D17-E17-F17-I17+J17-G17 -> 56000 | L17: =B17/B52 -> 8000 | N17: =K16+K18+K19+K22+K23 -> 839735.41
A18: Ольга Атырау | B18: 200000 | I18: =L18*D53 -> 96000 | K18: =B18-C18-D18-E18-F18-I18+J18-G18 -> 104000 | L18: =B18/B53 -> 8000
A19: Динара колл центр | B19: 100000 | C19: 24770 | D19: 100000 | I19: =L19*D54 -> 0 | J19: =IFERROR(__xludf.DUMMYFUNCTION("IMPORTRANGE(""https://docs.google.com/spreadsheets/d/1JJd44_6b1hsmD6e8liei_zzkkh-GYab6gE4K23IJPVI/edit?gid=0#gid=0&range=J95"",""'Лист1'!V168"")"),126094.9275000005) -> 126094.93 | K19: =B19-C19-D19-E19-F19-I19+J19-G19 -> 101324.93 | L19: =B19/B54 -> 4000
A20: Нурым | B20: 250000 | I20: =L20*D55 -> 0 | J20: =IFERROR(__xludf.DUMMYFUNCTION("IMPORTRANGE(""https://docs.google.com/spreadsheets/d/1JJd44_6b1hsmD6e8liei_zzkkh-GYab6gE4K23IJPVI/edit?gid=0#gid=0&range=J95"",""'Лист1'!I174"")"),86123.72499999963) -> 86123.725 | K20: =B20-C20-D20-E20-F20-I20+J20-G20 -> 336123.72 | L20: =B20/B55 -> 12500 | N20: =K16+K18+K19+K22+K23+K2+200000 -> 1119735.4
A21: СММ Диана | B21: 200000 | I21: =L21*D56 -> 90000 | K21: =B21-C21-D21-E21-F21-I21+J21-G21 -> 110000 | L21: =B21/B56 -> 10000
A22: Маргулан Видеограф | B22: 250000 | I22: =L22*D57 -> 0 | K22: 250000 | L22: =B22/B57 -> 12500
A23: Амина Дизайнер | B23: 350000 | F23: 300000 | I23: =L23*D58 -> 0 | K23: =B23-D23-E23-F23-I23+J23-G23 -> 50000 | L23: =B23/B58 -> 17500
A24: Алена | B24: 200000 | I24: =L24*D59 -> 0 | K24: =B24-C23-D24-E24-F24-I24+J24-G24 -> 200000 | L24: =B24/B59 -> 10000
A25: Гулмира ом | B25: =300000-36364 -> 263636 | D25: 100000 | I25: =L25*D60 -> 158181.6 | K25: 0 | L25: =B25/B60 -> 13181.8
A26: Гульжахан Бухгалтер | B26: 150000 | F26: 150000 | I26: =L26*D61 -> 0 | K26: =B26-C26-D26-E26-F26-I26+J26-G26 -> 0 | L26: =B26/B61 -> 7142.8571
A27: Бахадыр Юрист | B27: 70000 | I27: =L27*D62 -> 0 | K27: =B27-C27-D27-E27-F27-I27+J27-G27 -> 70000 | L27: =B27/B62 -> 3333.3333
A28: Эльвира (уборщица) | B28: 120000 | I28: =L28*D63 -> 0 | K28: =B28-C28-D28-E28-F28-I28+J28-G28 -> 120000 | L28: =B28/B63 -> 5714.2857 | N28: 157506
A30: Общ | K30: =SUM(K2:K28) -> 4552048.7
A36: ФИО | B36: рабочие дни за март | C36: отработано | D36: Дни отсутствия | E36: график работы
A37: Ерболат Аружан | B37: 20 | C37: =B37-D37 -> 20 | D37: 0 | E37: 45297
A38: Тұрсынхан Нұртілеу | B38: 20 | C38: =B38-D38 -> 20 | D38: 0 | E38: 45297
A39: Байғазы Салтанат | B39: 21 | C39: =B39-D39 -> 19 | D39: 2 | E39: 45327 | I39: =K7+K8+K9+K10+K11+K12+K14+K28 -> 1478967.6 | J39: 2356000 | K39: =I39+J39+J40 -> 4834967.6 | P39: =K23+K22+K21 -> 410000
A40: Расиль Асхат | B40: 21 | C40: =B40-D40 -> 21 | D40: 0 | E40: 45327 | I40: 243600 | J40: 1000000
A41: Алуа Ментор Айлтс | B41: 21 | C41: =B41-D41 -> 21 | D41: 0 | E41: 45327
A42: Бекмухамед | B42: 21 | C42: =B42-D42 -> 16 | D42: 5 | E42: 45327
A43: Алима | B43: 8 | C43: =B43-D43 -> 8 | D43: 0 | E43: 45297
A44: Ханаби | B44: 21 | C44: =B44-D44 -> 17 | D44: 4 | E44: 45327
A45: Асем психолог | B45: 21 | C45: =B45-D45 -> 18 | D45: 3 | E45: 45327
A46: Асель | B46: 21 | C46: =B46-D46 -> 21 | D46: 0 | E46: 45327
A47: Диас международн отд | B47: 21 | C47: =B47-D47 -> 21 | D47: 0 | E47: 45327
A48: Султан | B48: 21 | C48: =B48-D48 -> 21 | D48: 0 | E48: 45327
A49: Бейбут | B49: 21 | C49: =B49-D49 -> 21 | D49: 0 | E49: 45327
A50: Алмат РОП | B50: 21 | C50: =B50-D50 -> 21 | D50: 0 | E50: 45297
A51: Мадияр РОП | B51: 25 | C51: =B51-D51 -> 25 | D51: 0 | E51: 45297 | I51: по факту если не работала
A52: Темирлан РОП | B52: 25 | C52: =B52-D52 -> 22 | D52: 3 | E52: 45297 | I52: фактические рабочие дни
A53: Ольга Атырау | B53: 25 | C53: =B53-D53 -> 13 | D53: 12 | E53: 45297
A54: Динара колл центр | B54: 25 | C54: =B54-D54 -> 25 | D54: 0 | E54: 45297
A55: Нурым | B55: 20 | C55: =B55-D55 -> 20 | D55: 0 | E55: 45297 | I55: 21
A56: СММ Диана | B56: 20 | C56: =B56-D56 -> 11 | D56: 9 | E56: 45297
A57: Маргулан Видеограф | B57: 20 | C57: =B57-D57 -> 20 | D57: 0 | E57: 45297 | I57: отпуск без сохра зара плата
A58: Амина Дизайнер | B58: 20 | C58: =B58-D58 -> 20 | D58: 0 | E58: 45297
A59: Алена | B59: 20 | C59: =B59-D59 -> 20 | D59: 0 | E59: 45297
A60: Гулмира ом | B60: 20 | C60: =B60-D60 -> 8 | D60: 12 | E60: 45297 | I60: не раб офиц
A61: Гульжахан Бухгалтер | B61: 21 | C61: =B61-D61 -> 21 | D61: 0 | E61: 45327 | I61: не работали
A62: Бахадыр Юрист | B62: 21 | C62: =B62-D62 -> 21 | D62: 0 | E62: 45327 | I62: офиц
A63: Эльвира (уборщица) | B63: 21 | C63: =B63-D63 -> 21 | D63: 0 | E63: 45327 | I63: не оплачивается
I64: 30 31

Sheet Январь
A1: Имя сотрудника | B1: зарплата за март | C1: аванс 1 | D1: аванс 2 | E1: аванс 3 | F1: аванс 4 | G1: На ДР | H1: Штрафы | I1: не выход на работу | J1: премия и % | K1: остаток зп на Сентябрь | L1: за 1 день
A2: Аружан | B2: 200000 | I2: =L2*D38 -> 0 | K2: =B2-C2-D2-E2-F2-I2+J2-G2 -> 200000 | L2: =B2/B38 -> 10000
A3: Нуртилеу | B3: 200000 | C3: 27353 | I3: =L3*D39 -> 0 | K3: =B3-C3-D3-E3-F3-I3+J3-G3 -> 172647 | L3: =B3/B39 -> 10000
A4: Салтанат | B4: 1000000 | I4: =L4*D40 -> 150000 | J4: 49000 | K4: =B4-C4-D4-E4-F4-I4+J4-G4 -> 899000 | L4: =B4/B40 -> 50000
A5: Расиль Асхат(Онлайн) | B5: 200000 | H5: 200000 | I5: =L5*D41 -> 0 | K5: 0 | L5: =B5/B41 -> 10000 | M5: онлайн
A6: Алуа (Онлайн) | B6: 45000 | I6: =L6*D42 -> 0 | K6: =B6-C6-D6-E6-F6-I6+J6-G6 -> 45000 | L6: =B6/B42 -> 2250 | M6: онлайн
A7: Алима | B7: 150000 | I7: =L7*D43 -> 0 | K7: =B7-C7-D7-E7-F7-I7+J7-G7 -> 150000 | L7: =B7/B43 -> 18750 | M7: онлайн
A8: Асем Психолог | B8: 230000 | F8: 227500 | I8: =L8*D44 -> 34500 | J8: 32000 | K8: =B8-C8-D8-E8-F8-I8+J8-G8-H8 -> 0 | L8: =B8/B44 -> 11500
A9: Асель | B9: 224000 | G9: 1000 | I9: =L9*D52 -> 0 | K9: =B9-C9-D9-E9-F9-I9+J9-G9-H9 -> 223000 | L9: =B9/B45 -> 11200
A10: Диас международн отд (Онлайн) | B10: 350000 | I10: =L10*D52 -> 0 | K10: =B10-C10-D10-E10-F10-I10+J10-G10-H10 -> 350000 | L10: =B10/B46 -> 17500
A11: Султан | B11: 63000 | H11: 63000 | K11: 0 | L11: =B11/B47 -> 3150 | M11: чт 12 | N11: пт12к | O11: сб2часа 6000 | P11: пн12к | Q11: ср12 | R11: пт12 | S11: по часам
A12: Мерей Сат с 11.01 | B12: 264000 | H12: 264000 | K12: 0 | L12: =B12/B48 -> 14666.667 | M12: по часам | N12: 4 часа в день | O12: по 4 к
A13: Miracle с 14.01 | B13: 300000 | I13: =L13*D49 -> 115384.62 | K13: =B13-C13-D13-E13-F13-I13+J13-G13-H13 -> 184615.38 | L13: =B13/B49 -> 23076.923
A14: Адип SAT | B14: 56000 | G14: 5000 | K14: =B14-C14-D14-E14-F14-I14+J14-G14-H14 -> 51000 | L14: 0
A15: Бейбут | B15: 200000 | F15: 150000 | I15: =L15*D52 -> 0 | K15: =B15-C15-D15-E15-F15-I15+J15-G15-H15 -> 50000 | L15: =B15/B52 -> 10000
A16: Алмат Ком дир | B16: 400000 | I16: =L16*D53 -> 116666.67 | K16: 0 | L16: =B16/B53 -> 16666.667
A17: Мадияр РОП | B17: 200000 | I17: =L17*D54 -> 8333.3333 | J17: =IFERROR(__xludf.DUMMYFUNCTION("IMPORTRANGE(""https://docs.google.com/spreadsheets/d/1JJd44_6b1hsmD6e8liei_zzkkh-GYab6gE4K23IJPVI/edit?gid=0#gid=0&range=J95"",""'Лист1'!K205"")"),119018.60999999971) -> 119018.61 | K17: =B17-C17-D17-E17-F17-I17+J17-G17-H17 -> 310685.28 | L17: =B17/B54 -> 8333.3333
A18: Темирлан РОП | B18: 200000 | C18: 30000 | D18: 50000 | E18: 40000 | I18: =L18*D56 -> 0 | K18: 0 | L18: =B18/B55 -> 8333.3333
A19: Динара колл центр | B19: 100000 | G19: 3000 | I19: =L19*D56 -> 0 | J19: =IFERROR(__xludf.DUMMYFUNCTION("IMPORTRANGE(""https://docs.google.com/spreadsheets/d/1JJd44_6b1hsmD6e8liei_zzkkh-GYab6gE4K23IJPVI/edit?gid=0#gid=0&range=J95"",""'Лист1'!V195"")+100000"),234593.65) -> 234593.65 | K19: =B19-C19-D19-E19-F19-I19+J19-G19-H19 -> 331593.65 | L19: =B19/B56 -> 4166.6667
A20: Мадина ОП | B20: 120000 | F20: 55000 | I20: =L20*D57 -> 65000 | K20: =B20-C20-D20-E20-F20-I20+J20-G20-H20 -> 0 | L20: =B20/B58 -> 5000
A21: Нурым | B21: 250000 | I21: =L21*D59 -> 0 | J21: =IFERROR(__xludf.DUMMYFUNCTION("IMPORTRANGE(""https://docs.google.com/spreadsheets/d/1JJd44_6b1hsmD6e8liei_zzkkh-GYab6gE4K23IJPVI/edit?gid=0#gid=0&range=J95"",""'Лист1'!I201"")"),70447.84999999963) -> 70447.85 | K21: =B21-C21-D21-E21-F21-I21+J21-G21 -> 320447.85 | L21: =B21/B58 -> 10416.667
A22: СММ Диана | B22: 200000 | I22: =L22*D59 -> 0 | K22: =B22-C22-D22-E22-F22-I22+J22-G22-H22 -> 200000 | L22: =B22/B59 -> 8333.3333
A23: Маргулан Видеограф | B23: 250000 | G23: 4000 | I23: =L23*D60 -> 0 | K23: =B23-C23-D23-E23-F23-I23+J23-G23-H23 -> 246000 | L23: =B23/B60 -> 10416.667
A24: Амина Дизайнер | B24: 300000 | I24: =L24*D61 -> 0 | K24: =B24-C24-D24-E24-F24-I24+J24-G24-H24 -> 300000 | L24: =B24/B61 -> 12500
A25: Алена | B25: 200000 | I25: =L25*D62 -> 0 | K25: =B25-C24-D25-E25-F25-I25+J25-G25 -> 200000 | L25: =B25/B62 -> 8333.3333
A26: Гулим ОМ | B26: 250000 | F26: 156250 | I26: =L26*D63 -> 72916.667 | K26: =B26-C26-D26-E26-F26-I26+J26-G26-H26 -> 20833.333 | L26: =B26/B63 -> 10416.667
A27: Гульжахан Бухгалтер | B27: 200000 | I27: =L27*D64 -> 0 | K27: =B27-C27-D27-E27-F27-I27+J27-G27 -> 200000 | L27: =B27/B64 -> 10000
A28: Бахадыр Юрист | B28: 100000 | F28: 100000 | I28: =L28*D65 -> 0 | K28: =B28-C28-D28-E28-F28-I28+J28-G28-H28 -> 0 | L28: =B28/B65 -> 5000
A29: Эльвира (уборщица) | B29: 120000 | I29: =L29*D66 -> 0 | K29: =B29-C29-D29-E29-F29-I29+J29-G29-H29 -> 120000 | L29: =B29/B66 -> 6000
A31: Общ | K31: =SUM(K2:K29) -> 4574822.5
A37: ФИО | B37: рабочие дни за март | C37: отработано | D37: Дни отсутствия | E37: график работы
A38: Аружан | B38: 20 | C38: =B38-D38 -> 20 | D38: 0 | E38: 45327
A39: Нуртилеу | B39: 20 | C39: =B39-D39 -> 20 | D39: 0 | E39: 45327 | I39: 2ого вышла до11
A40: Салтанат | B40: 20 | C40: =B40-D40 -> 17 | D40: 3 | E40: 45693
A41: Расиль Асхат | B41: 20 | C41: =B41-D41 -> 20 | D41: 0 | E41: 45327
A42: Алуа | B42: 20 | C42: =B42-D42 -> 20 | D42: 0 | E42: 45327
A43: Алима | B43: 8 | C43: =B43-D43 -> 8 | D43: 0 | E43: 45297
A44: Асем психолог | B44: 20 | C44: =B44-D44 -> 17 | D44: 3 | E44: 45327 | F44: 41556
A45: Асель | B45: 20 | C45: =B45-D45 -> 20 | D45: 0 | E45: 45327
A46: Диас международн отд | B46: 20 | C46: =B46-D46 -> 20 | D46: 0 | E46: 45327
A47: Султан | B47: 20 | C47: =B47-D47 -> 20 | D47: 0 | E47: 45327
A48: Мерей | B48: 18 | C48: =B48-D48 -> 18 | D48: 0 | E48: 45297 | F48: с 11
A49: Miracle | B49: 13 | C49: =B49-D49 -> 8 | D49: 5 | E49: 45327 | F49: с14 | G49: вт чт суб
A50: Адип | B50: ? | C50: =B50-D50 -> #VALUE! | D50: 0 | E50: 45327
A51: Учи | B51: 20 | C51: =B51-D51 -> 10 | D51: 10 | E51: 45327 | F51: с20
A52: Бейбут | B52: 20 | C52: =B52-D52 -> 20 | D52: 0 | E52: 45327
A53: Алмат РОП | B53: 24 | C53: =B53-D53 -> 17 | D53: 7 | E53: 45297
A54: Мадияр РОП | B54: 24 | C54: =B54-D54 -> 23 | D54: 1 | E54: 45297
A55: Темирлан РОП | B55: 24 | C55: =B55-D55 -> 24 | D55: 0 | E55: 45297
A56: Динара колл центр | B56: 24 | C56: =B56-D56 -> 24 | D56: 0 | E56: 45297
A57: Мадина ОП | B57: 24 | C57: =B57-D57 -> 11 | D57: 13 | E57: 45297
A58: Нурым | B58: 24 | C58: =B58-D58 -> 24 | D58: 0 | E58: 45297
A59: СММ Диана | B59: 24 | C59: =B59-D59 -> 24 | D59: 0 | E59: 45297
A60: Маргулан Видеограф | B60: 24 | C60: =B60-D60 -> 24 | D60: 0 | E60: 45297
A61: Амина Дизайнер | B61: 24 | C61: =B61-D61 -> 24 | D61: 0 | E61: 45297
A62: Алена | B62: 24 | C62: =B62-D62 -> 24 | D62: 0 | E62: 45297
A63: Гулим ОМ | B63: 24 | C63: =B63-D63 -> 17 | D63: 7 | E63: 45297
... A66: Эльвира (уборщица) | B66: 20 | C66: =B66-D66 -> 20 | D66: 0 | E66: 45327

Sheet Февраль
A1: Имя сотрудника | B1: зарплата за февраль | C1: аванс 1 | D1: аванс 2 | E1: аванс 3 | F1: аванс 4 | G1: На ДР | H1: 8 март | I1: не выход на работу | J1: премия и % | K1: остаток зп на Сентябрь | L1: за 1 день
A2: Аружан | B2: 319000 | C2: 20000 | D2: 50000 | E2: 100000 | F2: 139000 | G2: 10000 | I2: =L2*D41 -> 0 | K2: =B2-C2-D2-E2-F2-I2+J2-G2-H2 -> 0 | L2: =B2/B41 -> 15950
A3: Нуртилеу | B3: 315000 | C3: 100000 | D3: 100000 | E3: 100000 | H3: 15000 | I3: =L3*D42 -> 0 | K3: =B3-C3-D3-E3-F3-I3+J3-G3-H3 -> 0 | L3: =B3/B42 -> 15750
A4: Салтанат | B4: 1000000 | C4: 150000 | D4: 100000 | E4: 120000 | F4: 532000 | G4: 98000 | I4: =L4*D43 -> 0 | K4: =B4-C4-D4-E4-F4-I4+J4-G4-H4 -> 0 | L4: =B4/B43 -> 50000
A5: Алуа (Онлайн) | B5: 49500 | I5: 49500 | K5: =B5-C5-D5-E5-F5-I5+J5-G5-H5 -> 0 | L5: =B5/B44 -> 2475 | M5: онлайн
A6: Алима | B6: 150000 | C6: 150000 | I6: =L6*D46 -> 0 | K6: =B6-C6-D6-E6-F6-I6+J6-G6-H6 -> 0 | L6: =B6/B46 -> 18750 | M6: онлайн | Q6: =K4+K5+K7+K8+K10+K11+K12+K13+K28-850000+150000+200000+15000 -> -485000
A7: Асем Психолог | B7: 230000 | G7: 2000 | I7: 228000 | K7: =B7-C7-D7-E7-F7-I7+J7-G7-H7 -> 0 | L7: =B7/B47 -> 11500
A8: Асель | B8: 157500 | I8: 157500 | K8: =B8-C8-D8-E8-F8-I8+J8-G8-H8 -> 0 | L8: =B8/B48 -> 7875
A9: Диас международн отд (Онлайн) | B9: 450000 | C9: 435000 | H9: 15000 | I9: =L9*D55 -> 0 | K9: =B9-C9-D9-E9-F9-I9+J9-G9-H9 -> 0 | L9: =B9/B49 -> 22500
A10: Мерей Сат с 11.01 | B10: 318000 | C10: 180000 | H10: 5000 | I10: 133000 | K10: =B10-C10-D10-E10-F10-I10+J10-G10-H10 -> 0 | L10: =B10/B50 -> 17666.667 | M10: по часам | N10: 4 часа в день | O10: по 4 к
A11: Miracle с 14.01 | B11: 300000 | I11: 300000 | K11: =B11-C11-D11-E11-F11-I11+J11-G11-H11 -> 0 | L11: =B11/B51 -> 27272.727
A12: Адиб SAT | B12: 222000 | G12: 5000 | H12: 10000 | I12: 207000 | K12: =B12-C12-D12-E12-F12-I12+J12-G12-H12 -> 0 | L12: =B12/B52 -> #VALUE!
A13: Дамир SAT | B13: 90000 | H13: 10000 | I13: 80000 | K13: =B13-C13-D13-E13-F13-I13+J13-G13-H13 -> 0 | L13: =B13/B53 -> #VALUE!
A14: Шолпан | B14: 300000 | C14: 100000 | D14: 200000 | K14: =B14-C14-D14-E14-F14-I14+J14-G14-H14 -> 0 | L14: =B14/B54 -> 15000
A15: Бейбут | B15: 200000 | C15: 200000 | I15: =L15*D55 -> 0 | K15: =B15-C15-D15-E15-F15-I15+J15-G15-H15 -> 0 | L15: =B15/B55 -> 10000 | Q15: =K5+K7+K8+K10+K11+K12+K13+K28 -> 0
A16: Мадияр РОП | B16: 200000 | C16: 393331 | G16: 5000 | H16: 15000 | I16: =L16*D56 -> 0 | J16: =IFERROR(__xludf.DUMMYFUNCTION("IMPORTRANGE(""https://docs.google.com/spreadsheets/d/1JJd44_6b1hsmD6e8liei_zzkkh-GYab6gE4K23IJPVI/edit?gid=0#gid=0&range=J95"",""'Лист1'!K232"")"),213330.68549999935) -> 213330.69 | K16: =B16-C16-D16-E16-F16-I16+J16-G16-H16 -> -0.3145 | L16: =B16/B56 -> 8333.3333
A17: Динара колл центр | B17: 74000 | C17: 30000 | D17: 50000 | E17: 250000 | F17: 218037 | G17: 5000 | I17: =L17*D57 -> 0 | J17: =IFERROR(__xludf.DUMMYFUNCTION("IMPORTRANGE(""https://docs.google.com/spreadsheets/d/1JJd44_6b1hsmD6e8liei_zzkkh-GYab6gE4K23IJPVI/edit?gid=0#gid=0&range=J95"",""'Лист1'!X222"")"),479036.7224999995) -> 479036.72 | K17: =B17-C17-D17-E17-F17-I17+J17-G17-H17 -> -0.2775 | L17: =B17/B57 -> 3083.3333
A18: Мадина ОП | B18: 100000 | C18: 235487 | G18: 3000 | I18: =L18*D58 -> 0 | J18: =IFERROR(__xludf.DUMMYFUNCTION("IMPORTRANGE(""https://docs.google.com/spreadsheets/d/1JJd44_6b1hsmD6e8liei_zzkkh-GYab6gE4K23IJPVI/edit?gid=0#gid=0&range=J95"",""'Лист1'!AH222"")"),138487.18500000035) -> 138487.18 | K18: =B18-C18-D18-E18-F18-I18+J18-G18-H18 -> 0.185 | L18: =B18/B59 -> 4166.6667
A19: Нурым | B19: 250000 | C19: =241482+15498 -> 256980 | D19: 100000 | H19: 15000 | I19: =L19*D60 -> 0 | J19: =IFERROR(__xludf.DUMMYFUNCTION("IMPORTRANGE(""https://docs.google.com/spreadsheets/d/1JJd44_6b1hsmD6e8liei_zzkkh-GYab6gE4K23IJPVI/edit?gid=0#gid=0&range=J95"",""'Лист1'!I228"")-33000"),121979.65499999933) -> 121979.65 | K19: =B19-C19-D19-E19-F19-I19+J19-G19-H19 -> -0.345 | L19: =B19/B59 -> 10416.667
A20: СММ Диана | B20: 200000 | C20: 200000 | I20: =L20*D60 -> 0 | K20: =B20-C20-D20-E20-F20-I20+J20-G20-H20 -> 0 | L20: =B20/B60 -> 8333.3333
A21: Маргулан Видеограф | B21: 250000 | C21: 230000 | G21: 5000 | H21: 15000 | I21: =L21*D61 -> 0 | K21: =B21-C21-D21-E21-F21-I21+J21-G21-H21 -> 0 | L21: =B21/B61 -> 10416.667
A22: Амина Дизайнер | B22: 300000 | C22: 300000 | I22: =L22*D62 -> 0 | K22: =B22-C22-D22-E22-F22-I22+J22-G22-H22 -> 0 | L22: =B22/B62 -> 12500
A23: Алена | B23: 200000 | C23: 200000 | I23: =L23*D63 -> 0 | K23: =B23-C23-D23-E23-F23-I23+J23-G23-H23 -> 0 | L23: =B23/B63 -> 8333.3333 | Q23: =K15+K18+K21+250000+100000+K29+K31+20000 -> 370000.62
A24: Камила Офис менеджер | B24: 250000 | C24: 101167 | G24: 3000 | I24: =L24*D64 -> 145833.33 | K24: =B24-C24-D24-E24-F24-I24+J24-G24-H24 -> -0.33333333 | L24: =B24/B64 -> 10416.667
A25: Гульжахан Бухгалтер | B25: 200000 | C25: 200000 | I25: =L25*D65 -> 0 | K25: =B25-C25-D25-E25-F25-I25+J25-G25-H25 -> 0 | L25: =B25/B65 -> 10000
A26: Бахадыр Юрист | B26: 70000 | C26: 55000 | H26: 15000 | I26: =L26*D66 -> 0 | K26: =B26-C26-D26-E26-F26-I26+J26-G26-H26 -> 0 | L26: =B26/B66 -> 3500
A27: Эльвира (уборщица) | B27: 120000 | C27: 120000 | I27: =L27*D67 -> 0 | K27: =B27-C27-D27-E27-F27-I27+J27-G27-H27 -> 0 | L27: =B27/B67 -> 6000
A28: Жангелди с 22.01 | B28: 300000 | C28: 65000 | H28: 10000 | I28: =L28*D68 -> 225000 | K28: =B28-C28-D28-E28-F28-I28+J28-G28-H28 -> 0 | L28: =B28/B68 -> 12500
A29: Анель ОП + координатор 21.02 | B29: 300000 | C29: 72807 | G29: 3000 | I29: =L29*D69 -> 225000 | J29: =IFERROR(__xludf.DUMMYFUNCTION("IMPORTRANGE(""https://docs.google.com/spreadsheets/d/1JJd44_6b1hsmD6e8liei_zzkkh-GYab6gE4K23IJPVI/edit?gid=0#gid=0&range=J95"",""'Лист1'!AT222"")"),807.4350000000013) -> 807.435 | K29: =B29-C29-D29-E29-F29-I29+J29-G29-H29 -> 0.435 | L29: =B29/B69 -> 12500
A30: Алтынбек профоринтолог | B30: 100000 | C30: 27500 | I30: =L30*D70 -> 87500 | J30: 15000 | K30: =B30-C30-D30-E30-F30-I30+J30-G30-H30 -> 0 | L30: =B30/B70 -> 4166.6667
A31: Жанибек ОП | B31: 100000 | C31: 12500 | I31: =L31*D71 -> 87500 | K31: =B31-C31-D31-E31-F31-I31+J31-G31-H31 -> 0 | L31: =B31/B71 -> 4166.6667
A34: Общ | B34: =SUM(B2:B27) -> 6315000 | K34: =SUM(K2:K31) -> -0.65033333
N38: =K16-100000+K17+K22+K24+K27+100000+200000+15498 -> 215497.07
A40: ФИО | B40: рабочие дни за март | C40: отработано | D40: Дни отсутствия | E40: график работы
A41: Аружан | B41: 20 | C41: =B41-D41 -> 20 | D41: 0 | E41: 45327 | G41: 872722470819
A42: Нуртилеу | B42: 20 | C42: =B42-D42 -> 20 | D42: 0 | E42: 45327 | J42: =1132535-450000-5000-300000-120000-10000-101167-100000 -> 46368
A43: Салтанат | B43: 20 | C43: =B43-D43 -> 20 | D43: 0 | E43: 45327 | K43: =570831-393331-50000 -> 127500
A44: Алуа | B44: 20 | C44: =B44-D44 -> 20 | D44: 0 | E44: 45327
A45: Расиль Асхат | B45: 20 | C45: =B45-D45 -> 20 | D45: 0 | E45: 45327
A46: Алима | B46: 8 | C46: =B46-D46 -> 8 | D46: 0 | E46: 45297
A47: Асем психолог | B47: 20 | C47: =B47-D47 -> 20 | D47: 0 | E47: 45327
A48: Асель | B48: 20 | C48: =B48-D48 -> 20 | D48: 0 | E48: 45327
A49: Диас международн отд | B49: 20 | C49: =B49-D49 -> 20 | D49: 0 | E49: 45327
A50: Мерей | B50: 18 | C50: =B50-D50 -> 18 | D50: 0 | E50: 45297 | F50: с 11
A51: Miracle | B51: 11 | C51: =B51-D51 -> 11 | D51: 0 | E51: 45327 | F51: с14 | G51: вт чт суб
A52: Адип | B52: ? | C52: =B52-D52 -> #VALUE! | D52: 0 | E52: 45327
A53: Дамир | B53: ? | C53: =B53-D53 -> #VALUE! | D53: 0 | E53: 45327
A54: Шолпан | B54: 20 | C54: =B54-D54 -> 20 | D54: 0 | E54: 45327
A55: Бейбут | B55: 20 | C55: =B55-D55 -> 20 | D55: 0 | E55: 45327
A56: Мадияр РОП | B56: 24 | C56: =B56-D56 -> 24 | D56: 0 | E56: 45297
A57: Динара колл центр | B57: 24 | C57: =B57-D57 -> 24 | D57: 0 | E57: 45297
A58: Мадина ОП | B58: 24 | C58: =B58-D58 -> 24 | D58: 0 | E58: 45297
A59: Нурым | B59: 24 | C59: =B59-D59 -> 24 | D59: 0 | E59: 45297
A60: СММ Диана | B60: 24 | C60: =B60-D60 -> 24 | D60: 0 | E60: 45297
A61: Маргулан Видеограф | B61: 24 | C61: =B61-D61 -> 24 | D61: 0 | E61: 45297
A62: Амина Дизайнер | B62: 24 | C62: =B62-D62 -> 24 | D62: 0 | E62: 45297
A63: Алена | B63: 24 | C63: =B63-D63 -> 24 | D63: 0 | E63: 45297
A64: Камила Офис менеджер | B64: 24 | C64: =B64-D64 -> 10 | D64: 14 | E64: 45297 | F64: с 18.02
A65: Гульжахан Бухгалтер | B65: 20 | C65: =B65-D65 -> 20 | D65: 0 | E65: 45327
A66: Бахадыр Юрист | B66: 20 | C66: =B66-D66 -> 20 | D66: 0 | E66: 45327
A67: Эльвира (уборщица) | B67: 20 | C67: =B67-D67 -> 20 | D67: 0 | E67: 45327
A68: Жангельди | B68: 24 | C68: =B68-D68 -> 6 | D68: 18 | E68: 45327 | F68: 22
A69: Анель ОП | B69: 24 | C69: =B69-D69 -> 6 | D69: 18 | E69: 45327 | F69: 21
A70: Алтынбек ОП | B70: 24 | C70: =B70-D70 -> 3 | D70: 21 | E70: 45327 | F70: 25
A71: Жанибек ОП | B71: 24 | C71: =B71-D71 -> 3 | D71: 21 | E71: 45327 | F71: 25

Sheet Март
A1: Имя сотрудника | B1: зарплата за февраль | C1: аванс 1 | D1: аванс 2 | E1: аванс 3 | F1: аванс 4 | G1: На ДР | H1: Штрафы | I1: не выход на работу | J1: премия и % | K1: остаток зп на Сентябрь | L1: за 1 день
A2: Аружан | B2: 150000 | C2: 100000 | D2: 50000 | I2: =L2*D45 -> 0 | K2: =B2-C2-D2-E2-F2-I2+J2-G2-H2 -> 0 | L2: =B2/B45 -> 8333.3333
A3: Нуртилеу | B3: 150000 | C3: 150000 | I3: =L3*D46 -> 0 | K3: =B3-C3-D3-E3-F3-I3+J3-G3 -> 0 | L3: =B3/B46 -> 8333.3333
A4: Учебный отдел | P4: =194000+K21+K24+K16+K7 -> 194000.38
A5: Салтанат | B5: 1000000 | C5: 330000 | D5: 100000 | E5: 120000 | F5: =120500+98807+90000+140693 -> 450000 | I5: =L5*D48 -> 0 | K5: =B5-C5-D5-E5-F5-I5+J5-G5-H5 -> 0 | L5: =B5/B48 -> 55555.556
A6: Алуа (Онлайн) | B6: 94500 | C6: 94500 | I6: =L6*D49 -> 0 | K6: =B6-C6-D6-E6-F6-I6+J6-G6 -> 0 | L6: =B6/B49 -> 5250 | M6: онлайн
A7: Алима | B7: 150000 | C7: 90000 | I7: =L7*D50 -> 60000 | K7: =B7-C7-D7-E7-F7-I7+J7-G7 -> 0 | L7: =B7/B50 -> 30000 | M7: онлайн
A8: Асем Психолог | B8: 230000 | C8: 84000 | D8: 133222 | I8: =L8*D51 -> 12777.778 | K8: =B8-C8-D8-E8-F8-I8+J8-G8 -> 0.22222222 | L8: =B8/B51 -> 12777.778
A9: Асель | B9: 115000 | C9: 115000 | I9: =L9*D52 -> 0 | K9: =B9-C9-D9-E9-F9-I9+J9-G9 -> 0 | L9: =B9/B52 -> 6388.8889
A10: Диас международн отд (Онлайн) | B10: 450000 | C10: 250000 | D10: 200000 | I10: =L10*D53 -> 0 | K10: =B10-C10-D10-E10-F10-I10+J10-G10 -> 0 | L10: =B10/B53 -> 25000
A11: Жангелди | I11: =L11*D54 -> 0 | K11: =B11-C11-D11-E11-F11-I11+J11-G11 -> 0 | L11: =B11/B54 -> 0
A12: Мерей Сат | B12: 164000 | C12: 194000 | I12: =L12*D55 -> 0 | J12: 30000 | K12: =B12-C12-D12-E12-F12-I12+J12-G12 -> 0 | L12: =B12/B55 -> 9111.1111 | M12: по часам | N12: 4 часа в день | O12: по 4 к
A13: Miracle | B13: 300000 | C13: 6250 | D13: 143750 | I13: =L13*D56 -> 150000 | K13: =B13-C13-D13-E13-F13-I13+J13-G13 -> 0 | L13: =B13/B56 -> 25000 | M13: до 17 ого
A14: Адип SAT | B14: 222000 | C14: 222000 | I14: =L14*D57 -> 0 | K14: =B14-C14-D14-E14-F14-I14+J14-G14 -> 0 | L14: =B14/B57 -> 12333.333 | M14: по часам | N14: 4 часа в день | O14: по 4 к
A15: Дамир SAT | B15: 0 | I15: =L15*D58 -> 0 | K15: 0 | L15: =B15/B58 -> 0 | M15: по часам | N15: 4 часа в день | O15: по 4 к
A16: Шолпан | B16: 326000 | C16: 300000 | D16: 26000 | I16: =L16*D59 -> 0 | K16: =B16-C16-D16-E16-F16-I16+J16-G16-H16 -> 0 | L16: =B16/B59 -> 18111.111
A17: Ариана международ | B17: 100000 | C17: 100000 | K17: =B17-C17-D17-E17-F17-I17+J17-G17-H17 -> 0
A18: Отдел продаж
A19: Мадияр РОП | B19: 200000 | C19: 124000 | D19: 240506 | I19: =L19*D61 -> 0 | J19: =IFERROR(__xludf.DUMMYFUNCTION("IMPORTRANGE(""https://docs.google.com/spreadsheets/d/1JJd44_6b1hsmD6e8liei_zzkkh-GYab6gE4K23IJPVI/edit?gid=0#gid=0&range=J95"",""'Лист1'!K259"")"),164505.9419999999) -> 164505.94 | K19: =B19-C19-D19-E19-F19-I19+J19-G19-H19 -> -0.058 | L19: =B19/B61 -> 9523.8095
A20: Динара колл центр | B20: 100000 | C20: 100000 | D20: 70000 | E20: 87868 | I20: =L20*D62 -> 0 | J20: =IFERROR(__xludf.DUMMYFUNCTION("IMPORTRANGE(""https://docs.google.com/spreadsheets/d/1JJd44_6b1hsmD6e8liei_zzkkh-GYab6gE4K23IJPVI/edit?gid=0#gid=0&range=J95"",""'Лист1'!V247"")"),157868.3250000002) -> 157868.33 | K20: =B20-C20-D20-E20-F20-I20+J20-G20-H20 -> 0.325 | L20: =B20/B62 -> 4761.9048
A21: Мадина ОП | B21: 100000 | C21: 80952 | I21: =L21*D63 -> 19047.619 | J21: 0 | K21: =B21-C21-D21-E21-F21-I21+J21-G21-H21 -> 0.38095238 | L21: =B21/B63 -> 4761.9048
A22: Анель ОП | B22: 300000 | C22: 200000 | D22: 70000 | E22: 42615 | H22: 9000 | I22: =L22*D64 -> 0 | J22: =IFERROR(__xludf.DUMMYFUNCTION("IMPORTRANGE(""https://docs.google.com/spreadsheets/d/1JJd44_6b1hsmD6e8liei_zzkkh-GYab6gE4K23IJPVI/edit?gid=0#gid=0&range=J95"",""'Лист1'!AT249"")"),39045.510000000126) -> 39045.51 | K22: 0 | L22: =B22/B64 -> 14285.714
A24: Жанибек ОП | B24: 100000 | C24: 15000 | D24: 82000 | G24: 3000 | I24: =L24*D66 -> 0 | J24: =IFERROR(__xludf.DUMMYFUNCTION("IMPORTRANGE(""https://docs.google.com/spreadsheets/d/1JJd44_6b1hsmD6e8liei_zzkkh-GYab6gE4K23IJPVI/edit?gid=0#gid=0&range=J95"",""'Лист1'!BR249"")"),0.0) -> 0 | K24: =B24-C24-D24-E24-F24-I24+J24-G24-H24 -> 0 | L24: =B24/B66 -> 4761.9048
A25: Маркетинг
A26: Нурым | B26: 250000 | C26: 100000 | D26: 120372 | E26: 126090 | I26: =L26*D68 -> 0 | J26: =IFERROR(__xludf.DUMMYFUNCTION("IMPORTRANGE(""https://docs.google.com/spreadsheets/d/1JJd44_6b1hsmD6e8liei_zzkkh-GYab6gE4K23IJPVI/edit?gid=0#gid=0&range=J95"",""'Лист1'!I255"")"),96462.3049999997) -> 96462.305 | K26: =B26-C26-D26-E26-F26-I26+J26-G26-H26 -> 0.305 | L26: =B26/B68 -> 11904.762
A27: СММ Диана | B27: 0 | I27: =L27*D69 -> 0 | K27: =B27-C27-D27-E27-F27-I27+J27-G27-H27 -> 0 | L27: =B27/B69 -> 0
A28: Маргулан Видеограф | B28: 250000 | C28: 125000 | I28: =L28*D70 -> 125000 | K28: =B28-C28-D28-E28-F28-I28+J28-G28-H28 -> 0 | L28: =B28/B70 -> 13888.889
A29: Амина Дизайнер | B29: 200000 | C29: 100000 | D29: 100000 | I29: =L29*D71 -> 0 | K29: =B29-C29-D29-E29-F29-I29+J29-G29-H29 -> 0 | L29: =B29/B71 -> 11111.111
A30: Алена | B30: 200000 | C30: 200000 | I30: =L30*D72 -> 0 | K30: =B30-C30-D30-E30-F30-I30+J30-G30-H30 -> 0 | L30: =B30/B72 -> 11111.111
A31: БЭК Офис
A32: Камила Офис менеджер | B32: 250000 | C32: 100000 | D32: 100000 | E32: 50000 | I32: =L32*D74 -> 0 | K32: =B32-C32-D32-E32-F32-I32+J32-G32-H32 -> 0 | L32: =B32/B74 -> 11904.762 | R32: =100000+K16+K7 -> 100000
A33: Гульжахан Бухгалтер | B33: 150000 | I33: =L33*D75 -> 0 | K33: =B33-C33-D33-E33-F33-I33+J33-G33-H33 -> 150000 | L33: =B33/B75 -> 7142.8571
A34: Бахадыр Юрист | B34: 70000 | I34: =L34*D76 -> 0 | K34: =B34-C34-D34-E34-F34-I34+J34-G34-H34 -> 70000 | L34: =B34/B76 -> 3333.3333
A35: Эльвира (уборщица) | B35: 120000 | C35: 120000 | I35: =L35*D77 -> 0 | K35: =B35-C35-D35-E35-F35-I35+J35-G35-H35 -> 0 | L35: =B35/B77 -> 5714.2857
A38: Общ | B38: =SUM(B2:B35) -> 5741500 | K38: =SUM(K2:K36) -> 220001.18
I43: =C3+C11+C10+C12+C13+C14+C15+C19+C24+C26+C28+C34 -> 1186250
A44: ФИО | B44: рабочие дни за март | C44: отработано | D44: Дни отсутствия | E44: график работы
A45: Аружан | B45: 18 | C45: =B45-D45 -> 18 | D45: 0 | E45: 45327
A46: Нуртилеу | B46: 18 | C46: =B46-D46 -> 18 | D46: 0 | E46: 45327
A47: Учебный отдел
A48: Салтанат | B48: 18 | C48: =B48-D48 -> 18 | D48: 0 | E48: 45327
A49: Алуа (Онлайн) | B49: 18 | C49: =B49-D49 -> 18 | D49: 0 | E49: 45327
A50: Алима | B50: 5 | C50: =B50-D50 -> 3 | D50: 2 | E50: 45327 | K50: =170000+300000+100000+125000 -> 695000
A51: Асем Психолог | B51: 18 | C51: =B51-D51 -> 17 | D51: 1 | E51: 45297 | F51: 11
A52: Асель | B52: 18 | C52: =B52-D52 -> 18 | D52: 0 | E52: 45327
A53: Диас международн отд (Онлайн) | B53: 18 | C53: =B53-D53 -> 18 | D53: 0 | E53: 45327
A54: Жангелди | B54: 10 | C54: =B54-D54 -> 7 | D54: 3 | E54: 45327
A55: Мерей Сат | B55: 18 | C55: =B55-D55 -> 18 | D55: 0 | E55: 45297
A56: Miracle | B56: 12 | C56: =B56-D56 -> 6 | D56: 6 | E56: 45327
A57: Адип SAT | B57: 18 | C57: =B57-D57 -> 18 | D57: 0 | E57: 45327
A58: Дамир SAT | B58: 18 | C58: =B58-D58 -> 18 | D58: 0 | E58: 45327
A59: Шолпан | B59: 18 | C59: =B59-D59 -> 18 | D59: 0 | E59: 45327 | F59: до 17 300 после 400
A60: Отдел продаж
A61: Мадияр РОП | B61: 21 | C61: =B61-D61 -> 21 | D61: 0 | E61: 45297
A62: Динара колл центр | B62: 21 | C62: =B62-D62 -> 21 | D62: 0 | E62: 45297
A63: Мадина ОП | B63: 21 | C63: =B63-D63 -> 17 | D63: 4 | E63: 45297
A64: Анель ОП + координатор 21.02 | B64: 21 | C64: =B64-D64 -> 21 | D64: 0 | E64: 45297
A66: Жанибек ОП | B66: 21 | C66: =B66-D66 -> 21 | D66: 0 | E66: 45297
A67: Маркетинг
A68: Нурым | B68: 21 | C68: =B68-D68 -> 21 | D68: 0 | E68: 45297
A69: СММ Диана | B69: 18 | C69: =B69-D69 -> 18 | D69: 0 | E69: 45297
A70: Маргулан Видеограф | B70: 18 | C70: =B70-D70 -> 9 | D70: 9 | E70: 45327
A71: Амина Дизайнер | B71: 18 | C71: =B71-D71 -> 18 | D71: 0 | E71: 45327
A72: Алена | B72: 18 | C72: =B72-D72 -> 18 | D72: 0 | E72: 45327
A73: БЭК Офис
A74: Камила Офис менеджер | B74: 21 | C74: =B74-D74 -> 21 | D74: 0 | E74: 45297
A75: Гульжахан Бухгалтер | B75: 21 | C75: =B75-D75 -> 21 | D75: 0 | E75: 45327
A76: Бахадыр Юрист | B76: 21 | C76: =B76-D76 -> 21 | D76: 0 | E76: 45327
A77: Эльвира (уборщица) | B77: 21 | C77: =B77-D77 -> 21 | D77: 0 | E77: 45327

Sheet Апрель
A1: Имя сотрудника | B1: зарплата за февраль | C1: аванс 1 | D1: аванс 2 | E1: аванс 3 | F1: аванс 4 | G1: На ДР | H1: Штрафы | I1: не выход на работу | J1: премия и % | K1: остаток зп на Сентябрь | L1: за 1 день
A2: Аружан | B2: 220000 | C2: 200000 | D2: 20000 | I2: =L2*D42 -> 0 | K2: =B2-C2-D2-E2-F2-I2+J2-G2-H2 -> 0 | L2: =B2/B42 -> 10000
A3: Нуртилеу | B3: 185000 | C3: 110000 | D3: 75000 | I3: =L3*D43 -> 0 | K3: =B3-C3-D3-E3-F3-I3+J3-G3-H3 -> 0 | L3: =B3/B43 -> 8409.0909
A4: Учебный отдел | Q4: =94500+K8+K9+K11+K12 -> 94500.273
A5: Салтанат | B5: 1000000 | C5: 500000 | D5: 250000 | E5: 220000 | I5: =L5*D45 -> 0 | K5: =B5-C5-D5-E5-F5-I5+J5-G5-H5 -> 30000 | L5: =B5/B45 -> 45454.545
A6: Алуа (Онлайн) | B6: 69000 | C6: 69000 | I6: =L6*D46 -> 0 | K6: =B6-C6-D6-E6-F6-I6+J6-G6 -> 0 | L6: =B6/B46 -> 3136.3636 | M6: онлайн | Q6: 300000
A7: Алима | B7: 0 | I7: =L7*D47 -> 0 | K7: =B7-C7-D7-E7-F7-I7+J7-G7 -> 0 | L7: =B7/B47 -> 0 | M7: онлайн
A8: Асем Психолог | B8: 150000 | C8: 122727 | D8: 20000 | I8: =L8*D48 -> 27272.727 | J8: 20000 | K8: =B8-C8-D8-E8-F8-I8+J8-G8 -> 0.27272727 | L8: =B8/B48 -> 6818.1818 | Q8: 200000
A9: Асель | B9: 92750 | C9: 92750 | I9: =L9*D49 -> 0 | K9: =B9-C9-D9-E9-F9-I9+J9-G9 -> 0 | L9: =B9/B49 -> 4215.9091
A10: Диас международн отд (Онлайн) | B10: 350000 | C10: 350000 | I10: =L10*D50 -> 0 | K10: =B10-C10-D10-E10-F10-I10+J10-G10 -> 0 | L10: =B10/B50 -> 15909.091
A11: Мерей Сат | B11: 148000 | C11: 148000 | D11: 86000 | I11: =L11*D52 -> 0 | J11: 86000 | K11: =B11-C11-D11-E11-F11-I11+J11-G11 -> 0 | L11: =B11/B52 -> 6727.2727 | M11: по часам | N11: 4 часа в день | O11: по 4 к
A12: Адип SAT | B12: 192000 | C12: 192000 | I12: =L12*D54 -> 0 | K12: =B12-C12-D12-E12-F12-I12+J12-G12 -> 0 | L12: =B12/B54 -> 8727.2727 | M12: по часам | N12: 4 часа в день | O12: по 4 к
A13: Шолпан | B13: 405000 | C13: 62000 | D13: 250955 | H13: 70000 | I13: =L13*D56 -> 92045.455 | K13: =B13-C13-D13-E13-F13-I13+J13-G13 -> -0.45454545 | L13: =B13/B56 -> 18409.091
A14: Ариана междунардн | B14: 185000 | C14: 40000 | D14: 100000 | E14: 11500 | F14: 33500 | K14: =B14-C14-D14-E14-F14-I14+J14-G14 -> 0
A15: Отдел продаж
A16: Мадияр РОП | B16: 200000 | C16: 40000 | D16: 100000 | E16: 100000 | F16: 7866 | I16: =L16*D59 -> 30769.231 | J16: =IFERROR(__xludf.DUMMYFUNCTION("IMPORTRANGE(""https://docs.google.com/spreadsheets/d/1JJd44_6b1hsmD6e8liei_zzkkh-GYab6gE4K23IJPVI/edit?gid=0#gid=0&range=J95"",""'Лист1'!K286"")"),78634.8) -> 78634.8 | K16: =B16-C16-D16-E16-F16-I16+J16-G16-H16 -> -0.43076923 | L16: =B16/B59 -> 7692.3077
A17: Динара колл центр | B17: 250000 | C17: 70000 | D17: 80550 | E17: 159730 | I17: =L17*D60 -> 0 | J17: =37500+22780 -> 60280 | K17: =B17-C17-D17-E17-F17-I17+J17-G17-H17 -> 0 | L17: =B17/B60 -> 9615.3846
A18: Мадина ОП | B18: 0 | I18: =L18*D61 -> 0 | J18: 0 | K18: =B18-C18-D18-E18-F18-I18+J18-G18-H18 -> 0 | L18: =B18/B61 -> 0
A19: Анель ОП | B19: 250000 | C19: 100000 | D19: 90000 | E19: 50385 | I19: =L19*D62 -> 9615.3846 | J19: 0 | K19: =B19-C19-D19-E19-F19-I19+J19-G19-H19 -> -0.38461538 | L19: =B19/B62 -> 9615.3846
B20: 0 | J20: =IFERROR(__xludf.DUMMYFUNCTION("IMPORTRANGE(""https://docs.google.com/spreadsheets/d/1JJd44_6b1hsmD6e8liei_zzkkh-GYab6gE4K23IJPVI/edit?gid=0#gid=0&range=J95"",""'Лист1'!AT276"")"),86280.1875) -> 86280.188 | K20: 0
A21: Али ОП | B21: 100000 | C21: 20000 | D21: 87800 | I21: =L21*D64 -> 0 | J21: 0 | K21: 0 | L21: =B21/B64 -> 3846.1538
A22: Маркетинг
A23: Нурым | B23: 150000 | C23: 100000 | D23: 50000 | I23: =L23*D66 -> 0 | K23: =B23-C23-D23-E23-F23-I23+J23-G23-H23 -> 0 | L23: =B23/B66 -> 5769.2308
A24: СММ | B24: 200000 | C24: 200000 | I24: =L24*D67 -> 0 | K24: =B24-C24-D24-E24-F24-I24+J24-G24-H24 -> 0 | L24: =B24/B67 -> 9090.9091
A25: Маргулан Видеограф | B25: 250000 | C25: 100000 | D25: 150000 | I25: =L25*D68 -> 0 | K25: =B25-C25-D25-E25-F25-I25+J25-G25-H25 -> 0 | L25: =B25/B68 -> 11363.636
A26: Амина Дизайнер | B26: 200000 | C26: 200000 | I26: =L26*D69 -> 0 | K26: =B26-C26-D26-E26-F26-I26+J26-G26-H26 -> 0 | L26: =B26/B69 -> 9090.9091
A27: Алена | I27: =L27*D70 -> 0 | K27: 0 | L27: =B27/B70 -> 0
A28: БЭК Офис
A29: Камила Офис менеджер | B29: 250000 | C29: 67310 | D29: 10000 | E29: 172690 | I29: =L29*D72 -> 0 | K29: =B29-C29-D29-E29-F29-I29+J29-G29-H29 -> 0 | L29: =B29/B72 -> 9615.3846
A30: Гульжахан Бухгалтер | B30: 150000 | I30: =L30*D73 -> 0 | K30: =B30-C30-D30-E30-F30-I30+J30-G30-H30 -> 150000 | L30: =B30/B73 -> 5769.2308
A31: Бахадыр Юрист | B31: 0 | I31: =L31*D74 -> 0 | K31: =B31-C31-D31-E31-F31-I31+J31-G31-H31 -> 0 | L31: =B31/B74 -> 0
A32: Эльвира (уборщица) | B32: 120000 | C32: 106154 | I32: =L32*D75 -> 15000 | K32: 0 | L32: =B32/B75 -> 5000
A33: Жулдыз уборщица | B33: 10909 | C33: 10909 | K33: =B33-C33-D33-E33-F33-I33+J33-G33-H33 -> 0
A35: Общ | B35: =SUM(B2:B32) -> 5116750 | K35: =SUM(K2:K33) -> 179999
I40: =C3+#REF!+C10+C11+#REF!+C12+#REF!+C16+C21+C23+C25+C31 -> #REF!
A41: ФИО | B41: рабочие дни за март | C41: отработано | D41: Дни отсутствия | E41: график работы
A42: Аружан | B42: 22 | C42: =B42-D42 -> 22 | D42: 0 | E42: 45327
A43: Нуртилеу | B43: 22 | C43: =B43-D43 -> 22 | D43: 0 | E43: 45327
A44: Учебный отдел
A45: Салтанат | B45: 22 | C45: =B45-D45 -> 22 | D45: 0 | E45: 45327
A46: Алуа (Онлайн) | B46: 22 | C46: =B46-D46 -> 22 | D46: 0 | E46: 45327
A47: Алима | B47: 22 | C47: =B47-D47 -> 22 | D47: 0 | E47: 45327
A48: Асем Психолог | B48: 22 | C48: =B48-D48 -> 18 | D48: 4 | E48: 45297
A49: Асель | B49: 22 | C49: =B49-D49 -> 22 | D49: 0 | E49: 45327
A50: Диас международн отд (Онлайн) | B50: 22 | C50: =B50-D50 -> 22 | D50: 0 | E50: 45327
A51: Жангелди | B51: 10 | C51: =B51-D51 -> 10 | D51: 0 | E51: 45327
A52: Мерей Сат | B52: 22 | C52: =B52-D52 -> 22 | D52: 0 | E52: 45297
A53: Miracle | B53: 10 | C53: =B53-D53 -> 10 | D53: 0 | E53: 45327
A54: Адип SAT | B54: 22 | C54: =B54-D54 -> 22 | D54: 0 | E54: 45327
A55: Дамир SAT | B55: 22 | C55: =B55-D55 -> 22 | D55: 0 | E55: 45327
A56: Шолпан | B56: 22 | C56: =B56-D56 -> 17 | D56: 5 | E56: 45327
A57: Ариана междунардн
A58: Отдел продаж
A59: Мадияр РОП | B59: 26 | C59: =B59-D59 -> 22 | D59: 4 | E59: 45297
A60: Динара колл центр | B60: 26 | C60: =B60-D60 -> 26 | D60: 0 | E60: 45297
A61: Мадина ОП | B61: 26 | C61: =B61-D61 -> 26 | D61: 0 | E61: 45297
A62: Анель ОП + координатор 21.02 | B62: 26 | C62: =B62-D62 -> 25 | D62: 1 | E62: 45297
A64: Али ОП | B64: 26 | C64: =B64-D64 -> 26 | D64: 0 | E64: 45297
A65: Маркетинг
A66: Нурым | B66: 26 | C66: =B66-D66 -> 26 | D66: 0 | E66: 45297
A67: СММ Диана | B67: 22 | C67: =B67-D67 -> 22 | D67: 0 | E67: 45297
A68: Маргулан Видеограф | B68: 22 | C68: =B68-D68 -> 22 | D68: 0 | E68: 45327
A69: Амина Дизайнер | B69: 22 | C69: =B69-D69 -> 22 | D69: 0 | E69: 45327
A70: Алена | B70: 22 | C70: =B70-D70 -> 22 | D70: 0 | E70: 45327
A71: БЭК Офис
A72: Камила Офис менеджер | B72: 26 | C72: =B72-D72 -> 26 | D72: 0 | E72: 45297
A73: Гульжахан Бухгалтер | B73: 26 | C73: =B73-D73 -> 26 | D73: 0 | E73: 45327
A74: Бахадыр Юрист | B74: 26 | C74: =B74-D74 -> 26 | D74: 0 | E74: 45327
A75: Эльвира (уборщица) | B75: 24 | C75: =B75-D75 -> 21 | D75: 3 | E75: 45327

Sheet Май
A1: Имя сотрудника | B1: зарплата за февраль | C1: аванс 1 | D1: аванс 2 | E1: аванс 3 | F1: аванс 4 | G1: На ДР | H1: Штрафы | I1: не выход на работу | J1: премия и % | K1: остаток зп на Сентябрь | L1: за 1 день
A2: Аружан | B2: 0 | I2: =L2*D40 -> 0 | K2: =B2-C2-D2-E2-F2-I2+J2-G2-H2 -> 0 | L2: =B2/B40 -> 0
A3: Нуртилеу | B3: 0 | I3: =L3*D41 -> 0 | K3: =B3-C3-D3-E3-F3-I3+J3-G3 -> 0 | L3: =B3/B41 -> 0
A4: Учебный отдел
A5: Салтанат | B5: 1000000 | C5: 325000 | D5: 180000 | E5: 145000 | I5: =L5*D43 -> 0 | K5: =B5-C5-D5-E5-F5-I5+J5-G5-H5 -> 350000 | L5: =B5/B43 -> 55555.556
A6: Алуа (Онлайн) | B6: 42000 | C6: 42000 | I6: =L6*D44 -> 0 | K6: =B6-C6-D6-E6-F6-I6+J6-G6 -> 0 | L6: =B6/B44 -> 2333.3333 | M6: онлайн
A7: Асем Психолог | B7: 190000 | C7: 190000 | I7: =L7*D46 -> 0 | K7: =B7-C7-D7-E7-F7-I7+J7-G7 -> 0 | L7: =B7/B46 -> 10555.556
A8: Диас международн отд (Онлайн) | B8: 450000 | C8: 200000 | D8: 100000 | E8: 150000 | I8: =L8*D48 -> 0 | K8: =B8-C8-D8-E8-F8-I8+J8-G8 -> 0 | L8: =B8/B48 -> 25000
A9: Мерей Сат | B9: 278000 | C9: 278000 | I9: =L9*D50 -> 0 | K9: =B9-C9-D9-E9-F9-I9+J9-G9-H9 -> 0 | L9: =B9/B50 -> 15444.444 | M9: по часам | N9: 4 часа в день | O9: по 4 к
A10: Адип SAT | B10: 120000 | C10: 120000 | I10: 0 | K10: =B10-C10-D10-E10-F10-I10+J10-G10 -> 0 | L10: =B10/B52 -> 6666.6667 | M10: по часам | N10: 4 часа в день | O10: по 4 к
A11: Султан | B11: 160500 | C11: 15000 | D11: 64500 | E11: 81000 | I11: =L11*D54 -> 0 | K11: =B11-C11-D11-E11-F11-I11+J11-G11-H11 -> 0 | L11: =B11/B54 -> 8916.6667 | M11: по часам | N11: 4 часа в день | O11: по 4 к
A12: Ариана | B12: 185000 | C12: 61500 | D12: 40000 | E12: 30000 | F12: 53500 | K12: =B12-C12-D12-E12-F12-I12+J12-G12-H12 -> 0
A13: Отдел продаж
A14: Мадияр РОП | B14: 200000 | C14: 200000 | D14: 50000 | E14: 42041 | I14: =L14*D56 -> 8333.3333 | J14: =IFERROR(__xludf.DUMMYFUNCTION("IMPORTRANGE(""https://docs.google.com/spreadsheets/d/1JJd44_6b1hsmD6e8liei_zzkkh-GYab6gE4K23IJPVI/edit?gid=0#gid=0&range=J95"",""'Лист1'!K313"")"),100374.07500000001) -> 100374.07 | K14: =B14-C14-D14-E14-F14-I14+J14-G14-H14 -> -0.25833333 | L14: =B14/B56 -> 8333.3333
A15: Динара колл центр | B15: 250000 | C15: 250000 | D15: 484 | I15: =L15*D57 -> 10416.667 | J15: 10901 | K15: =B15-C15-D15-E15-F15-I15+J15-G15-H15 -> 0.33333333 | L15: =B15/B57 -> 10416.667
A16: Мерген РОП | B16: 0 | I16: =L16*D58 -> 0 | J16: 0 | K16: =B16-C16-D16-E16-F16-I16+J16-G16-H16 -> 0 | L16: =B16/B58 -> 0
A17: Анель ОП | B17: 100000 | C17: 60000 | D17: 100000 | E17: 13962 | I17: =L17*D59 -> 0 | J17: =IFERROR(__xludf.DUMMYFUNCTION("IMPORTRANGE(""https://docs.google.com/spreadsheets/d/1JJd44_6b1hsmD6e8liei_zzkkh-GYab6gE4K23IJPVI/edit?gid=0#gid=0&range=J95"",""'Лист1'!AT303"")"),73961.775) -> 73961.775 | K17: =B17-C17-D17-E17-F17-I17+J17-G17-H17 -> -0.225 | L17: =B17/B59 -> 4166.6667
B18: 0 | J18: 0 | K18: 0
A19: Али ОП | B19: 60000 | C19: 15000 | D19: 25000 | E19: 40000 | I19: =L19*D61 -> 0 | J19: 20000 | K19: =B19-C19-D19-E19-F19-I19+J19-G19-H19 -> 0 | L19: =B19/B61 -> 2500
A20: Маркетинг
A21: Нурым | B21: 150000 | I21: =L21*D63 -> 0 | K21: =B21-C21-D21-E21-F21-I21+J21-G21-H21 -> 150000 | L21: =B21/B63 -> 6250
A22: СММ | B22: 200000 | C22: 200000 | I22: =L22*D64 -> 0 | K22: =B22-C22-D22-E22-F22-I22+J22-G22-H22 -> 0 | L22: =B22/B64 -> 11111.111
A23: Маргулан Видеограф | B23: 250000 | C23: 250000 | I23: =L23*D65 -> 0 | K23: =B23-C23-D23-E23-F23-I23+J23-G23-H23 -> 0 | L23: =B23/B65 -> 13888.889
A24: Амина Дизайнер | B24: 200000 | C24: 200000 | I24: =L24*D66 -> 0 | K24: =B24-C24-D24-E24-F24-I24+J24-G24-H24 -> 0 | L24: =B24/B66 -> 11111.111
A25: Алена | B25: 0 | I25: =L25*D67 -> 0 | K25: 0 | L25: =B25/B67 -> 0
A26: БЭК Офис
A27: Камила Офис менеджер | B27: 200000 | C27: 30000 | D27: 5000 | E27: 140000 | F27: 25000 | I27: =L27*D69 -> 0 | K27: =B27-C27-D27-E27-F27-I27+J27-G27-H27 -> 0 | L27: =B27/B69 -> 8333.3333
A28: Гульжахан Бухгалтер | B28: 150000 | I28: =L28*D70 -> 0 | K28: =B28-C28-D28-E28-F28-I28+J28-G28-H28 -> 150000 | L28: =B28/B70 -> 6250
A29: Бахадыр Юрист | B29: 0 | I29: =L29*D71 -> 0 | K29: 0 | L29: =B29/B71 -> 0
A30: Жулдыз (уборщица) | B30: 80000 | C30: 40000 | I30: =L30*D72 -> 40000 | K30: =B30-C30-D30-E30-F30-I30+J30-G30-H30 -> 0 | L30: =B30/B72 -> 3333.3333
A31: Асем уборщица | B31: 80000 | C31: 33333 | I31: =L31*D73 -> 46666.667 | K31: =B31-C31-D31-E31-F31-I31+J31-G31-H31 -> 0.33333333 | L31: =B31/B73 -> 3333.3333
A33: Общ | B33: =SUM(B2:B30) -> 4265500 | K33: =SUM(K2:K31) -> 650000.18
I38: =C3+#REF!+C8+C9+#REF!+C10+#REF!+C14+C19+C21+C23+C29 -> #REF!
A39: ФИО | B39: рабочие дни за март | C39: отработано | D39: Дни отсутствия | E39: график работы
A40: Аружан | B40: 18 | C40: =B40-D40 -> 18 | D40: 0 | E40: 45327
A41: Нуртилеу | B41: 18 | C41: =B41-D41 -> 18 | D41: 0 | E41: 45327
A42: Учебный отдел
A43: Салтанат | B43: 18 | C43: =B43-D43 -> 18 | D43: 0 | E43: 45327
A44: Алуа (Онлайн) | B44: 18 | C44: =B44-D44 -> 18 | D44: 0 | E44: 45327
A45: Алима | B45: 18 | C45: =B45-D45 -> 18 | D45: 0 | E45: 45327
A46: Асем Психолог | B46: 18 | C46: =B46-D46 -> 18 | D46: 0 | E46: 45297
A47: Асель | B47: 18 | C47: =B47-D47 -> 18 | D47: 0 | E47: 45327
A48: Диас международн отд (Онлайн) | B48: 18 | C48: =B48-D48 -> 18 | D48: 0 | E48: 45327
A49: Жангелди | B49: 10 | C49: =B49-D49 -> 10 | D49: 0 | E49: 45327
A50: Мерей Сат | B50: 18 | C50: =B50-D50 -> 18 | D50: 0 | E50: 45297
A51: Miracle | B51: 10 | C51: =B51-D51 -> 10 | D51: 0 | E51: 45327
A52: Адип SAT | B52: 18 | C52: =B52-D52 -> 17 | D52: 1 | E52: 45327
A53: Дамир SAT | B53: 18 | C53: =B53-D53 -> 18 | D53: 0 | E53: 45327
A54: Шолпан | B54: 18 | C54: =B54-D54 -> 18 | D54: 0 | E54: 45327
A55: Отдел продаж
A56: Мадияр РОП | B56: 24 | C56: =B56-D56 -> 23 | D56: 1 | E56: 45297
A57: Динара колл центр | B57: 24 | C57: =B57-D57 -> 23 | D57: 1 | E57: 45297
A58: Мерген РОП | B58: 24 | C58: =B58-D58 -> 10 | D58: 14 | E58: 45297
A59: Анель ОП + координатор 21.02 | B59: 24 | C59: =B59-D59 -> 24 | D59: 0 | E59: 45297
A61: Али ОП | B61: 24 | C61: =B61-D61 -> 24 | D61: 0 | E61: 45297
A62: Маркетинг
A63: Нурым | B63: 24 | C63: =B63-D63 -> 24 | D63: 0 | E63: 45297
A64: СММ Диана | B64: 18 | C64: =B64-D64 -> 18 | D64: 0 | E64: 45297
A65: Маргулан Видеограф | B65: 18 | C65: =B65-D65 -> 18 | D65: 0 | E65: 45327
A66: Амина Дизайнер | B66: 18 | C66: =B66-D66 -> 18 | D66: 0 | E66: 45327
A67: Алена | B67: 18 | C67: =B67-D67 -> 18 | D67: 0 | E67: 45327
A68: БЭК Офис
A69: Камила Офис менеджер | B69: 24 | C69: =B69-D69 -> 24 | D69: 0 | E69: 45297
A70: Гульжахан Бухгалтер | B70: 24 | C70: =B70-D70 -> 24 | D70: 0 | E70: 45327
A71: Бахадыр Юрист | B71: 24 | C71: =B71-D71 -> 24 | D71: 0 | E71: 45327
A72: Жулдыз (уборщица) | B72: 24 | C72: =B72-D72 -> 12 | D72: 12 | E72: 45327
A73: Асем(уборщица) | B73: 24 | C73: =B73-D73 -> 10 | D73: 14 | E73: 45327

Sheet Июнь 2025
A1: Имя сотрудника | B1: зарплата за февраль | C1: аванс 1 | D1: аванс 2 | E1: аванс 3 | F1: аванс 4 | G1: На ДР | H1: Штрафы | I1: не выход на работу | J1: премия и % | K1: остаток зп на Сентябрь | L1: за 1 день
A2: Аружан | B2: 0 | I2: =L2*D36 -> 0 | K2: =B2-C2-D2-E2-F2-I2+J2-G2-H2 -> 0 | L2: =B2/B36 -> 0
A3: Нуртилеу | B3: 0 | I3: =L3*D37 -> 0 | K3: =B3-C3-D3-E3-F3-I3+J3-G3 -> 0 | L3: =B3/B37 -> 0
A4: Учебный отдел
A5: Салтанат | B5: 1000000 | I5: =L5*D39 -> 0 | K5: =B5-C5-D5-E5-F5-I5+J5-G5-H5 -> 1000000 | L5: =B5/B39 -> 47619.048
A6: Алуа (Онлайн) | B6: 79500 | C6: 79500 | I6: =L6*D40 -> 0 | K6: =B6-C6-D6-E6-F6-I6+J6-G6 -> 0 | L6: =B6/B40 -> 3785.7143 | M6: онлайн
A7: Султан | B7: 222000 | C7: 222000 | I7: =L7*D45 -> 0 | K7: =B7-C7-D7-E7-F7-I7+J7-G7-H7 -> 0 | L7: =B7/B45 -> 22200 | M7: по часам | N7: 4 часа в день | O7: по 4 к
A8: Диас международн отд (Онлайн) | B8: 450000 | C8: 150000 | D8: 250000 | E8: 50000 | I8: =L8*D44 -> 0 | K8: =B8-C8-D8-E8-F8-I8+J8-G8 -> 0 | L8: =B8/B44 -> 21428.571
A9: Мерей Сат | B9: 370000 | C9: 358000 | D9: 12000 | I9: =L9*D46 -> 0 | K9: =B9-C9-D9-E9-F9-I9+J9-G9-H9 -> 0 | L9: =B9/B46 -> 17619.048 | M9: по часам | N9: 4 часа в день | O9: по 4 к
A10: Динара колл центр | B10: 300000 | C10: 250000 | D10: 50000 | I10: =L10*D53 -> 0 | K10: =B10-C10-D10-E10-F10-I10+J10-G10-H10 -> 0 | L10: =B10/B53 -> 12000
A11: Даяна | B11: 75000 | C11: 75000
A12: Отдел продаж
A13: Мадияр РОП | B13: 200000 | C13: 137365 | I13: =L13*D52 -> 88000 | J13: =IFERROR(__xludf.DUMMYFUNCTION("IMPORTRANGE(""https://docs.google.com/spreadsheets/d/1JJd44_6b1hsmD6e8liei_zzkkh-GYab6gE4K23IJPVI/edit?gid=0#gid=0&range=J95"",""'Лист1'!J330"")"),25364.54250000006) -> 25364.542 | K13: =B13-C13-D13-E13-F13-I13+J13-G13-H13 -> -0.4575 | L13: =B13/B52 -> 8000
A14: Мерген РОП | B14: 300000 | C14: 204000 | I14: =L14*D54 -> 96000 | J14: 0 | K14: =B14-C14-D14-E14-F14-I14+J14-G14-H14 -> 0 | L14: =B14/B54 -> 12000
A15: Анель ОП | B15: 100000 | C15: 66038 | D15: 10000 | E15: 23962 | I15: =L15*D55 -> 0 | J15: 0 | K15: =B15-C15-D15-E15-F15-I15+J15-G15-H15 -> 0 | L15: =B15/B55 -> 4000
J16: =IFERROR(__xludf.DUMMYFUNCTION("IMPORTRANGE(""https://docs.google.com/spreadsheets/d/1JJd44_6b1hsmD6e8liei_zzkkh-GYab6gE4K23IJPVI/edit?gid=0#gid=0&range=J95"",""'Лист1'!J330"")"),25364.54250000006) -> 25364.542 | K16: 0
A17: Али ОП | B17: 100000 | C17: 56000 | I17: =L17*D57+27209 -> 47209 | J17: =IFERROR(__xludf.DUMMYFUNCTION("IMPORTRANGE(""https://docs.google.com/spreadsheets/d/1JJd44_6b1hsmD6e8liei_zzkkh-GYab6gE4K23IJPVI/edit?gid=0#gid=0&range=J95"",""'Лист1'!BF330"")"),3209.2200000000025) -> 3209.22 | K17: =B17-C17-D17-E17-F17-I17+J17-G17-H17 -> 0.22 | L17: =B17/B57 -> 4000
A18: Маркетинг
A19: Нурым | B19: 150000 | I19: =L19*D59 -> 0 | K19: =B19-C19-D19-E19-F19-I19+J19-G19-H19 -> 150000 | L19: =B19/B59 -> 6250
A20: СММ | B20: 200000 | C20: 100000 | D20: 100000 | I20: =L20*D60 -> 0 | K20: =B20-C20-D20-E20-F20-I20+J20-G20-H20 -> 0 | L20: =B20/B60 -> 9523.8095
A21: Маргулан Видеограф | B21: 0 | I21: =L21*D61 -> 0 | K21: =B21-C21-D21-E21-F21-I21+J21-G21-H21 -> 0 | L21: =B21/B61 -> 0
A22: Амина Дизайнер | B22: 200000 | C22: 100000 | D22: 100000 | I22: =L22*D62 -> 0 | K22: =B22-C22-D22-E22-F22-I22+J22-G22-H22 -> 0 | L22: =B22/B62 -> 9523.8095
A23: БЭК Офис
A24: Камила Офис менеджер | B24: 200000 | C24: 100000 | D24: 100000 | I24: =L24*D65 -> 0 | K24: =B24-C24-D24-E24-F24-I24+J24-G24-H24 -> 0 | L24: =B24/B65 -> 8000
A25: Гульжахан Бухгалтер | B25: 150000 | I25: =L25*D66 -> 0 | K25: =B25-C25-D25-E25-F25-I25+J25-G25-H25 -> 150000 | L25: =B25/B66 -> 6250
A27: Асем уборщица | B27: 80000 | C27: 80000 | I27: =L27*D69 -> 0 | K27: =B27-C27-D27-E27-F27-I27+J27-G27-H27 -> 0 | L27: =B27/B69 -> 3200
A29: Общ | B29: =SUM(B2:B26) -> 4096500 | C29: =B29+J13+J17 -> 4125073.8 | K29: =SUM(K2:K27) -> 1299999.8
I34: =C3+#REF!+C8+C9+#REF!+#REF!+#REF!+C13+C17+C19+C21+#REF! -> #REF!
A35: ФИО | B35: рабочие дни за март | C35: отработано | D35: Дни отсутствия | E35: график работы
A36: Аружан | B36: 18 | C36: =B36-D36 -> 18 | D36: 0 | E36: 45327
A37: Нуртилеу | B37: 18 | C37: =B37-D37 -> 18 | D37: 0 | E37: 45327
A38: Учебный отдел
A39: Салтанат | B39: 21 | C39: =B39-D39 -> 21 | D39: 0 | E39: 45327
A40: Алуа (Онлайн) | B40: 21 | C40: =B40-D40 -> 21 | D40: 0 | E40: 45327
A41: Алима | B41: 21 | C41: =B41-D41 -> 21 | D41: 0 | E41: 45327
A42: Асем Психолог | B42: 21 | C42: =B42-D42 -> 21 | D42: 0 | E42: 45297
A43: Асель | B43: 21 | C43: =B43-D43 -> 21 | D43: 0 | E43: 45327
A44: Диас международн отд (Онлайн) | B44: 21 | C44: =B44-D44 -> 21 | D44: 0 | E44: 45327
A45: Жангелди | B45: 10 | C45: =B45-D45 -> 10 | D45: 0 | E45: 45327
A46: Мерей Сат | B46: 21 | C46: =B46-D46 -> 21 | D46: 0 | E46: 45297
A47: Miracle | B47: 10 | C47: =B47-D47 -> 10 | D47: 0 | E47: 45327
A48: Адип SAT | B48: 18 | C48: =B48-D48 -> 18 | D48: 0 | E48: 45327
A49: Дамир SAT | B49: 18 | C49: =B49-D49 -> 18 | D49: 0 | E49: 45327
A50: Шолпан | B50: 18 | C50: =B50-D50 -> 18 | D50: 0 | E50: 45327
A51: Отдел продаж
A52: Мадияр РОП | B52: 25 | C52: =B52-D52 -> 14 | D52: 11 | E52: 45297
A53: Динара колл центр | B53: 25 | C53: =B53-D53 -> 25 | D53: 0 | E53: 45297
A54: Мерген РОП | B54: 25 | C54: =B54-D54 -> 17 | D54: 8 | E54: 45297
A55: Анель ОП + координатор 21.02 | B55: 25 | C55: =B55-D55 -> 25 | D55: 0 | E55: 45297
A57: Али ОП | B57: 25 | C57: =B57-D57 -> 20 | D57: 5 | E57: 45297
A58: Маркетинг
A59: Нурым | B59: 24 | C59: =B59-D59 -> 24 | D59: 0 | E59: 45297
A60: СММ Асем | B60: 21 | C60: =B60-D60 -> 21 | D60: 0 | E60: 45297
A61: Маргулан Видеограф | B61: 21 | C61: =B61-D61 -> 21 | D61: 0 | E61: 45327
A62: Амина Дизайнер | B62: 21 | C62: =B62-D62 -> 21 | D62: 0 | E62: 45327
A63: Алена | B63: 21 | C63: =B63-D63 -> 21 | D63: 0 | E63: 45327
A64: БЭК Офис
A65: Камила Офис менеджер | B65: 25 | C65: =B65-D65 -> 25 | D65: 0 | E65: 45297
A66: Гульжахан Бухгалтер | B66: 24 | C66: =B66-D66 -> 24 | D66: 0 | E66: 45327
A67: Бахадыр Юрист | B67: 24 | C67: =B67-D67 -> 24 | D67: 0 | E67: 45327
A68: Жулдыз (уборщица) | B68: 25 | C68: =B68-D68 -> 25 | D68: 0 | E68: 45327
A69: Асем(уборщица) | B69: 25 | C69: =B69-D69 -> 25 | D69: 0 | E69: 45327

Sheet Июль 2025
A1: Имя сотрудника | B1: зарплата за февраль | C1: аванс 1 | D1: аванс 2 | E1: аванс 3 | F1: аванс 4 | G1: На ДР | H1: Штрафы | I1: не выход на работу | J1: премия и % | K1: остаток зп на Сентябрь | L1: за 1 день
A2: Аружан | B2: 385000 | C2: 250000 | D2: 35000 | E2: 100000 | I2: =L2*D38 -> 0 | K2: =B2-C2-D2-E2-F2-I2+J2-G2-H2 -> 0 | L2: =B2/B38 -> 21388.889
A3: Нуртилеу | B3: 285000 | C3: 250000 | D3: 35000 | I3: =L3*D39 -> 0 | K3: =B3-C3-D3-E3-F3-I3+J3-G3 -> 0 | L3: =B3/B39 -> 15833.333
A4: Учебный отдел
A5: Салтанат | B5: 250000 | C5: 100000 | D5: 100000 | E5: 35000 | F5: 15000 | I5: =L5*D41 -> 0 | K5: =B5-C5-D5-E5-F5-I5+J5-G5-H5 -> 0 | L5: =B5/B41 -> 11904.762
A6: Алуа (Онлайн) | B6: 132000 | C6: 132000 | I6: =L6*D42 -> 0 | K6: =B6-C6-D6-E6-F6-I6+J6-G6 -> 0 | L6: =B6/B42 -> 6285.7143 | M6: онлайн
A7: Султан | B7: 219000 | C7: 219000 | I7: =L7*D47 -> 0 | K7: =B7-C7-D7-E7-F7-I7+J7-G7-H7 -> 0 | L7: =B7/B47 -> 21900 | M7: по часам | N7: 4 часа в день | O7: по 4 к
A8: Мади | B8: 99000 | C8: 99000 | I8: =L8*D45 -> 0 | K8: =B8-C8-D8-E8-F8-I8+J8-G8 -> 0 | L8: =B8/B45 -> 4714.2857
A9: Диас международн отд (Онлайн) | I9: =L9*D46 -> 0 | K9: 0 | L9: =B9/B46 -> 0
A10: Мерей Сат | B10: 416500 | C10: 416500 | I10: =L10*D48 -> 0 | K10: =B10-C10-D10-E10-F10-I10+J10-G10-H10 -> 0 | L10: =B10/B48 -> 19833.333 | M10: по часам | N10: 4 часа в день | O10: по 4 к
A11: Динара колл центр | B11: 300000 | C11: 250000 | D11: 38462 | I11: =L11*D55 -> 11538.462 | K11: =B11-C11-D11-E11-F11-I11+J11-G11-H11 -> -0.46153846 | L11: =B11/B55 -> 11538.462
A12: Даяна | B12: 75000 | C12: 75000 | I12: =L12*D50 -> 0 | K12: =B12-C12-D12-E12-F12-I12+J12-G12 -> 0 | L12: =B12/B50 -> 4166.6667 | M12: по часам | N12: 4 часа в день | O12: по 4 к
I13: =L13*D52 -> 0 | K13: =B13-C13-D13-E13-F13-I13+J13-G13-H13 -> 0 | L13: =B13/B52 -> 0 | M13: по часам | N13: 4 часа в день | O13: по 4 к
A14: Отдел продаж
A15: Мадияр РОП | B15: 100000 | C15: 150000 | D15: 50000 | E15: 34372 | J15: =IFERROR(__xludf.DUMMYFUNCTION("IMPORTRANGE(""https://docs.google.com/spreadsheets/d/1JJd44_6b1hsmD6e8liei_zzkkh-GYab6gE4K23IJPVI/edit?gid=0#gid=0&range=J95"",""'Лист1'!K367"")"),134372.47500000062) -> 134372.48 | K15: =B15-C15-D15-E15-F15-I15+J15-G15-H15 -> 0.475 | L15: =B15/B54 -> 3846.1538
A16: Мерген РОП | B16: 0 | I16: =L16*D56 -> 0 | J16: 0 | K16: =B16-C16-D16-E16-F16-I16+J16-G16-H16 -> 0 | L16: =B16/B56 -> 0
A17: Анель ОП | B17: 100000 | C17: 100000 | D17: 6038 | E17: 35000 | F17: =255000+18524 -> 273524 | I17: =L17*D57 -> 0 | J17: =IFERROR(__xludf.DUMMYFUNCTION("IMPORTRANGE(""https://docs.google.com/spreadsheets/d/1JJd44_6b1hsmD6e8liei_zzkkh-GYab6gE4K23IJPVI/edit?gid=0#gid=0&range=J95"",""'Лист1'!W357"")+18000"),314561.925) -> 314561.92 | K17: =B17-C17-D17-E17-F17-I17+J17-G17-H17 -> -0.075 | L17: =B17/B57 -> 3846.1538
J18: =IFERROR(__xludf.DUMMYFUNCTION("IMPORTRANGE(""https://docs.google.com/spreadsheets/d/1JJd44_6b1hsmD6e8liei_zzkkh-GYab6gE4K23IJPVI/edit?gid=0#gid=0&range=J95"",""'Лист1'!V358"")"),"") | K18: 0
A19: Али ОП | I19: =L19*D59 -> 0 | J19: =IFERROR(__xludf.DUMMYFUNCTION("IMPORTRANGE(""https://docs.google.com/spreadsheets/d/1JJd44_6b1hsmD6e8liei_zzkkh-GYab6gE4K23IJPVI/edit?gid=0#gid=0&range=J95"",""'Лист1'!BF331"")"),"") | K19: =B19-C19-D19-E19-F19-I19+J19-G19-H19 -> 0 | L19: =B19/B59 -> 0
A20: Маркетинг
A21: Нурым | B21: 0 | I21: =L21*D61 -> 0 | K21: =B21-C21-D21-E21-F21-I21+J21-G21-H21 -> 0 | L21: =B21/B61 -> 0
A22: СММ | I22: =L22*D62 -> 0 | K22: =B22-C22-D22-E22-F22-I22+J22-G22-H22 -> 0 | L22: =B22/B62 -> 0
A23: Маргулан Видеограф | I23: =L23*D63 -> 0 | K23: =B23-C23-D23-E23-F23-I23+J23-G23-H23 -> 0 | L23: =B23/B63 -> 0
A24: Амина Дизайнер | B24: 0 | I24: =L24*D64 -> 0 | K24: =B24-C24-D24-E24-F24-I24+J24-G24-H24 -> 0 | L24: =B24/B64 -> 0
A25: БЭК Офис
A26: Камила Офис менеджер | B26: 200000 | C26: 15000 | D26: 170000 | I26: =L26*D67 -> 15384.615 | K26: =B26-C26-D26-E26-F26-I26+J26-G26-H26 -> -384.61538 | L26: =B26/B67 -> 7692.3077
A27: Гульжахан Бухгалтер | B27: 150000 | I27: =L27*D68 -> 0 | K27: =B27-C27-D27-E27-F27-I27+J27-G27-H27 -> 150000 | L27: =B27/B68 -> 5769.2308
A29: Асем уборщица | B29: 80000 | C29: 73600 | I29: =L29*D71 -> 6400 | K29: =B29-C29-D29-E29-F29-I29+J29-G29-H29 -> 0 | L29: =B29/B71 -> 3200
A31: Общ | B31: =SUM(B2:B28) -> 2711500 | C31: =B31+J15+J17 -> 3160434.4 | K31: =SUM(K2:K29) -> 149615.32
I36: =C3+#REF!+C9+C10+#REF!+C12+#REF!+C15+C19+C21+C23+#REF! -> #REF!
A37: ФИО | B37: рабочие дни за март | C37: отработано | D37: Дни отсутствия | E37: график работы
A38: Аружан | B38: 18 | C38: =B38-D38 -> 18 | D38: 0 | E38: 45327
A39: Нуртилеу | B39: 18 | C39: =B39-D39 -> 18 | D39: 0 | E39: 45327
A40: Учебный отдел
A41: Салтанат | B41: 21 | C41: =B41-D41 -> 21 | D41: 0 | E41: 45327
A42: Алуа (Онлайн) | B42: 21 | C42: =B42-D42 -> 21 | D42: 0 | E42: 45327
A43: Алима | B43: 21 | C43: =B43-D43 -> 21 | D43: 0 | E43: 45327
A44: Асем Психолог | B44: 21 | C44: =B44-D44 -> 21 | D44: 0 | E44: 45297
A45: Асель | B45: 21 | C45: =B45-D45 -> 21 | D45: 0 | E45: 45327
A46: Диас международн отд (Онлайн) | B46: 26 | C46: =B46-D46 -> 12 | D46: 14 | E46: 45327
A47: Жангелди | B47: 10 | C47: =B47-D47 -> 10 | D47: 0 | E47: 45327
A48: Мерей Сат | B48: 21 | C48: =B48-D48 -> 21 | D48: 0 | E48: 45297
A49: Miracle | B49: 10 | C49: =B49-D49 -> 10 | D49: 0 | E49: 45327 | L49: =K6+K7+K10+K11+K12+K29+K5+K8 -> -0.46153846
A50: Адип SAT | B50: 18 | C50: =B50-D50 -> 18 | D50: 0 | E50: 45327 | G50: 260
A51: Дамир SAT | B51: 18 | C51: =B51-D51 -> 18 | D51: 0 | E51: 45327 | G51: 146
A52: Шолпан | B52: 18 | C52: =B52-D52 -> 18 | D52: 0 | E52: 45327
A53: Отдел продаж
A54: Мадияр РОП | B54: 26 | C54: =B54-D54 -> 26 | E54: 45297
A55: Динара колл центр | B55: 26 | C55: =B55-D55 -> 25 | D55: 1 | E55: 45297
A56: Мерген РОП | B56: 26 | C56: =B56-D56 -> 26 | D56: 0 | E56: 45297
A57: Анель ОП + координатор 21.02 | B57: 26 | C57: =B57-D57 -> 26 | D57: 0 | E57: 45297
A59: Али ОП | B59: 26 | C59: =B59-D59 -> 26 | D59: 0 | E59: 45297
A60: Маркетинг
A61: Нурым | B61: 26 | C61: =B61-D61 -> 26 | D61: 0 | E61: 45297
A62: СММ Асем | B62: 21 | C62: =B62-D62 -> 21 | D62: 0 | E62: 45297
A63: Маргулан Видеограф | B63: 21 | C63: =B63-D63 -> 21 | D63: 0 | E63: 45327
A64: Амина Дизайнер | B64: 21 | C64: =B64-D64 -> 21 | D64: 0 | E64: 45327
A65: Алена | B65: 21 | C65: =B65-D65 -> 21 | D65: 0 | E65: 45327
A66: БЭК Офис
A67: Камила Офис менеджер | B67: 26 | C67: =B67-D67 -> 24 | D67: 2 | E67: 45297
A68: Гульжахан Бухгалтер | B68: 26 | C68: =B68-D68 -> 26 | D68: 0 | E68: 45327
A69: Бахадыр Юрист | B69: 24 | C69: =B69-D69 -> 24 | D69: 0 | E69: 45327
A70: Жулдыз (уборщица) | B70: 25 | C70: =B70-D70 -> 25 | D70: 0 | E70: 45327
A71: Асем(уборщица) | B71: 25 | C71: =B71-D71 -> 23 | D71: 2 | E71: 45327

Sheet Август 2025
A1: Имя сотрудника | B1: зарплата за февраль | C1: аванс 1 | D1: аванс 2 | E1: аванс 3 | F1: аванс 4 | G1: На ДР | H1: Штрафы | I1: не выход на работу | J1: премия и % | K1: остаток зп на Сентябрь | L1: за 1 день
A2: Аружан | B2: 700000 | C2: 700000 | I2: =L2*D38 -> 0 | K2: =B2-C2-D2-E2-F2-I2+J2-G2-H2 -> 0 | L2: =B2/B38 -> 38888.889
A3: Нуртилеу | B3: 530000 | C3: 50000 | D3: 75000 | E3: 105000 | F3: 281500 | G3: 10000 | I3: =L3*D39 -> 0 | K3: =B3-C3-D3-E3-F3-I3+J3-G3 -> 8500 | L3: =B3/B39 -> 29444.444
A4: Учебный отдел
A5: Салтанат | B5: 250000 | C5: 185000 | D5: 59307 | E5: 5000 | I5: =L5*D41 -> 0 | K5: =B5-C5-D5-E5-F5-I5+J5-G5-H5 -> 693 | L5: =B5/B41 -> 11904.762
A6: Алуа (Онлайн) | B6: 141000 | C6: 141000 | I6: =L6*D42 -> 0 | K6: =B6-C6-D6-E6-F6-I6+J6-G6 -> 0 | L6: =B6/B42 -> 6714.2857 | M6: онлайн
A7: Султан | B7: 252000 | C7: 200000 | D7: 50000 | G7: 2000 | I7: =L7*D47 -> 0 | K7: =B7-C7-D7-E7-F7-I7+J7-G7-H7 -> 0 | L7: =B7/B47 -> 25200 | M7: по часам | N7: 4 часа в день | O7: по 4 к
A8: Мади | B8: 132000 | C8: 130000 | D8: 2000 | I8: =L8*D45 -> 0 | K8: =B8-C8-D8-E8-F8-I8+J8-G8 -> 0 | L8: =B8/B45 -> 6285.7143
A9: Мадина международн отд (Онлайн) | B9: 200000 | C9: 200000 | I9: =L9*D46 -> 0 | K9: =B9-C9-D9-E9-F9-I9+J9-G9 -> 0 | L9: =B9/B46 -> 7692.3077
A10: Мерей Сат | B10: 435000 | C10: 433000 | G10: 2000 | I10: =L10*D48 -> 0 | K10: =B10-C10-D10-E10-F10-I10+J10-G10-H10 -> 0 | L10: =B10/B48 -> 20714.286 | M10: по часам | N10: 4 часа в день | O10: по 4 к
A11: Динара Куратор | B11: 300000 | C11: 200000 | D11: 85462 | G11: 3000 | I11: =L11*D55 -> 11538.462 | K11: =B11-C11-D11-E11-F11-I11+J11-G11-H11 -> -0.46153846 | L11: =B11/B55 -> 11538.462
A12: Алтынбек Проф ориентолог | B12: 70000 | C12: 70000 | I12: =L12*D50 -> 0 | K12: =B12-C12-D12-E12-F12-I12+J12-G12 -> 0 | L12: =B12/B50 -> 3888.8889 | M12: по часам | N12: 4 часа в день | O12: по 4 к
A13: Ариана | B13: 150000 | C13: 150000 | I13: =L13*D52 -> 0 | K13: =B13-C13-D13-E13-F13-I13+J13-G13-H13 -> 0 | L13: =B13/B52 -> 8333.3333 | M13: по часам | N13: 4 часа в день | O13: по 4 к
A14: Отдел продаж
A15: Мадияр РОП | B15: 200000 | C15: 200000 | D15: 150000 | E15: 190128 | I15: =L15*D55 -> 7692.3077 | J15: =IFERROR(__xludf.DUMMYFUNCTION("IMPORTRANGE(""https://docs.google.com/spreadsheets/d/1JJd44_6b1hsmD6e8liei_zzkkh-GYab6gE4K23IJPVI/edit?gid=0#gid=0&range=J95"",""'Лист1'!K394"")"),197820.42299999978) -> 197820.42 | K15: =B15-C15-D15-E15-F15-I15+J15-G15-H15+50000+100000 -> 0.11530769 | L15: =B15/B54 -> 7692.3077
A16: Мерген РОП | I16: =L16*D56 -> 0 | J16: 0 | K16: =B16-C16-D16-E16-F16-I16+J16-G16-H16 -> 0 | L16: =B16/B56 -> 0
A17: Анель ОП | B17: 100000 | C17: 200000 | D17: 100000 | E17: 39911 | G17: 3000 | H17: 10000 | I17: =L17*D57 -> 7692.3077 | J17: =IFERROR(__xludf.DUMMYFUNCTION("IMPORTRANGE(""https://docs.google.com/spreadsheets/d/1JJd44_6b1hsmD6e8liei_zzkkh-GYab6gE4K23IJPVI/edit?gid=0#gid=0&range=J95"",""'Лист1'!W384"")"),280603.125) -> 280603.12 | K17: =B17-C17-D17-E17-F17-I17+J17-G17-H17-50000+30000 -> -0.18269231 | L17: =B17/B57 -> 3846.1538
K18: 0
A19: Али ОП | I19: =L19*D59 -> 0 | K19: 0 | L19: =B19/B59 -> 0
A20: Маркетинг
A21: Нурым | B21: 0 | I21: =L21*D61 -> 0 | K21: =B21-C21-D21-E21-F21-I21+J21-G21-H21 -> 0 | L21: =B21/B61 -> 0
A22: СММ | I22: =L22*D62 -> 0 | K22: =B22-C22-D22-E22-F22-I22+J22-G22-H22 -> 0 | L22: =B22/B62 -> 0
A23: Маргулан Видеограф | I23: =L23*D63 -> 0 | K23: =B23-C23-D23-E23-F23-I23+J23-G23-H23 -> 0 | L23: =B23/B63 -> 0
A24: Амина Дизайнер | B24: 0 | I24: =L24*D64 -> 0 | K24: =B24-C24-D24-E24-F24-I24+J24-G24-H24 -> 0 | L24: =B24/B64 -> 0
A25: БЭК Офис
A26: Камила Офис менеджер | B26: 200000 | C26: 20000 | D26: 20000 | E26: 90000 | F26: 34000 | G26: 3000 | I26: =L26*D67 -> 23076.923 | K26: =B26-C26-D26-E26-F26-I26+J26-G26-H26 -> 9923.0769 | L26: =B26/B67 -> 7692.3077
A27: Гульжахан Бухгалтер | B27: 150000 | I27: =L27*D68 -> 0 | K27: =B27-C27-D27-E27-F27-I27+J27-G27-H27 -> 150000 | L27: =B27/B68 -> 5769.2308
A29: Асем уборщица | B29: 80000 | C29: 80000 | I29: =L29*D71 -> 9600 | K29: =B29-C29-D29-E29-F29-I29+J29-G29-H29 -> -9600 | L29: =B29/B71 -> 3200
A31: Общ | B31: =SUM(B2:B28) -> 3810000 | C31: =B31+J15+J17 -> 4288423.5 | K31: =SUM(K2:K29) -> 159515.55
A37: ФИО | B37: рабочие дни за март | C37: отработано | D37: Дни отсутствия | E37: график работы | J37: долг по зп: | K37: ='Февраль'!K34+'Март'!K38+'Апрель'!K35+'Май'!K33+'Июнь 2025'!K29+'Июль 2025'!K31+K31 -> 2659130.3 | L37: =K37-'Февраль'!K4-'Март'!K5-'Апрель'!K5-'Май'!K5-'Июнь 2025'!K5-'Июль 2025'!K5-K5 -> 1278437.3
A38: Аружан | B38: 18 | C38: =B38-D38 -> 18 | D38: 0 | E38: 45327
A39: Нуртилеу | B39: 18 | C39: =B39-D39 -> 18 | D39: 0 | E39: 45327 | J39: долг по кредитам: | K39: =K40+K41+K42+K43 -> 9032189
A40: Учебный отдел | J40: жанерке | K40: 400000
A41: Салтанат | B41: 21 | C41: =B41-D41 -> 21 | D41: 0 | E41: 45327 | J41: Аружан | K41: =4632189-700000-300000 -> 3632189
A42: Алуа (Онлайн) | B42: 21 | C42: =B42-D42 -> 21 | D42: 0 | E42: 45327 | J42: Нуртилеу | K42: 2000000
A43: Алима | B43: 21 | C43: =B43-D43 -> 21 | D43: 0 | E43: 45327 | J43: Салтанат | K43: 3000000
A44: Асем Психолог | B44: 21 | C44: =B44-D44 -> 21 | D44: 0 | E44: 45297
A45: Асель | B45: 21 | C45: =B45-D45 -> 21 | D45: 0 | E45: 45327 | J45: налог | K45: 1500000
A46: Диас международн отд (Онлайн) | B46: 26 | C46: =B46-D46 -> 26 | E46: 45327
A47: Жангелди | B47: 10 | C47: =B47-D47 -> 10 | D47: 0 | E47: 45327
A48: Мерей Сат | B48: 21 | C48: =B48-D48 -> 21 | D48: 0 | E48: 45297
A49: Miracle | B49: 10 | C49: =B49-D49 -> 10 | D49: 0 | E49: 45327
A50: Адип SAT | B50: 18 | C50: =B50-D50 -> 18 | D50: 0 | E50: 45327
A51: Дамир SAT | B51: 18 | C51: =B51-D51 -> 18 | D51: 0 | E51: 45327
A52: Шолпан | B52: 18 | C52: =B52-D52 -> 18 | D52: 0 | E52: 45327
A53: Отдел продаж
A54: Мадияр РОП | B54: 26 | C54: =B54-D54 -> 23 | D54: 3 | E54: 45297
A55: Динара колл центр | B55: 26 | C55: =B55-D55 -> 25 | D55: 1 | E55: 45297
A56: Мерген РОП | B56: 26 | C56: =B56-D56 -> 26 | D56: 0 | E56: 45297
A57: Анель ОП + координатор 21.02 | B57: 26 | C57: =B57-D57 -> 24 | D57: 2 | E57: 45297
A59: Али ОП | B59: 26 | C59: =B59-D59 -> 26 | D59: 0 | E59: 45297
A60: Маркетинг
A61: Нурым | B61: 26 | C61: =B61-D61 -> 26 | D61: 0 | E61: 45297
A62: СММ Асем | B62: 21 | C62: =B62-D62 -> 21 | D62: 0 | E62: 45297
A63: Маргулан Видеограф | B63: 21 | C63: =B63-D63 -> 21 | D63: 0 | E63: 45327
A64: Амина Дизайнер | B64: 21 | C64: =B64-D64 -> 21 | D64: 0 | E64: 45327
A65: Алена | B65: 21 | C65: =B65-D65 -> 21 | D65: 0 | E65: 45327
A66: БЭК Офис
A67: Камила Офис менеджер | B67: 26 | C67: =B67-D67 -> 23 | D67: 3 | E67: 45297
A68: Гульжахан Бухгалтер | B68: 26 | C68: =B68-D68 -> 26 | E68: 45327
A69: Бахадыр Юрист | B69: 24 | C69: =B69-D69 -> 24 | E69: 45327
A70: Жулдыз (уборщица) | B70: 25 | C70: =B70-D70 -> 25 | E70: 45327
A71: Асем(уборщица) | B71: 25 | C71: =B71-D71 -> 22 | D71: 3 | E71: 45327

Sheet Сентябрь 2025
A1: Имя сотрудника | B1: зарплата за февраль | C1: аванс 1 | D1: аванс 2 | E1: аванс 3 | F1: аванс 4 | G1: На ДР | H1: Штрафы | I1: не выход на работу | J1: премия и % | K1: остаток зп на Сентябрь | L1: за 1 день
A2: Аружан | B2: 1000000 | C2: 300000 | D2: 700000 | I2: =L2*D38 -> 0 | K2: =B2-C2-D2-E2-F2-I2+J2-G2-H2 -> 0 | L2: =B2/B38 -> 55555.556
A3: Нуртилеу | B3: 1002678 | C3: 927678 | D3: 75000 | I3: =L3*D39 -> 0 | K3: =B3-C3-D3-E3-F3-I3+J3-G3 -> 0 | L3: =B3/B39 -> 55704.333
A4: Учебный отдел
A5: Салтанат | B5: 500000 | C5: 500000 | I5: =L5*D41 -> 0 | J5: 18720 | K5: =B5-C5-D5-E5-F5-I5+J5-G5-H5 -> 18720 | L5: =B5/B41 -> 23809.524
A6: Алуа (Онлайн) | B6: 94500 | C6: 94500 | I6: =L6*D42 -> 0 | K6: =B6-C6-D6-E6-F6-I6+J6-G6 -> 0 | L6: =B6/B42 -> 4500 | M6: онлайн
A7: Султан | B7: 222000 | C7: 222000 | I7: =L7*D47 -> 0 | K7: =B7-C7-D7-E7-F7-I7+J7-G7-H7 -> 0 | L7: =B7/B47 -> 22200 | M7: по часам | N7: 4 часа в день | O7: по 4 к
A8: Мади | B8: 129000 | C8: 129000 | I8: =L8*D45 -> 0 | K8: =B8-C8-D8-E8-F8-I8+J8-G8 -> 0 | L8: =B8/B45 -> 6142.8571
A9: Мадина международн отд (Онлайн) | B9: 300000 | C9: 300000 | I9: =L9*D46 -> 0 | K9: =B9-C9-D9-E9-F9-I9+J9-G9 -> 0 | L9: =B9/B46 -> 11538.462
A10: Мерей Сат | B10: 343000 | C10: 60500 | D10: 280500 | H10: 2000 | I10: =L10*D48 -> 0 | K10: =B10-C10-D10-E10-F10-I10+J10-G10-H10 -> 0 | L10: =B10/B48 -> 16333.333 | M10: по часам | N10: 4 часа в день | O10: по 4 к
A11: Динара колл центр | B11: 300000 | C11: 300000 | I11: =L11*D55 -> 0 | K11: =B11-C11-D11-E11-F11-I11+J11-G11-H11 -> 0 | L11: =B11/B55 -> 11538.462
A12: Алтынбек Проф ориентолог | B12: 130000 | C12: 130000 | I12: =L12*D50 -> 0 | K12: =B12-C12-D12-E12-F12-I12+J12-G12 -> 0 | L12: =B12/B50 -> 7222.2222 | M12: по часам | N12: 4 часа в день | O12: по 4 к
A13: Дильяра | B13: 37500 | C13: 37500 | I13: =L13*D52 -> 0 | K13: =B13-C13-D13-E13-F13-I13+J13-G13-H13 -> 0 | L13: =B13/B52 -> 2083.3333 | M13: по часам | N13: 4 часа в день | O13: по 4 к
A14: Отдел продаж
A15: Мадияр РОП | B15: 200000 | C15: 641878 | H15: 5000 | I15: =L15*D54 -> 7692.3077 | J15: =IFERROR(__xludf.DUMMYFUNCTION("IMPORTRANGE(""https://docs.google.com/spreadsheets/d/1JJd44_6b1hsmD6e8liei_zzkkh-GYab6gE4K23IJPVI/edit?gid=0#gid=0&range=J95"",""'Лист1'!K421"")"),374570.6085000004) -> 374570.61 | K15: =B15-C15-D15-E15-F15-I15+J15-G15-H15+80000 -> 0.30080769 | L15: =B15/B54 -> 7692.3077
A16: Дильназ | I16: =L16*D56 -> 0 | J16: 0 | K16: =B16-C16-D16-E16-F16-I16+J16-G16-H16 -> 0 | L16: =B16/B56 -> 0
A17: Анель ОП | B17: 100000 | C17: 192000 | D17: 100000 | E17: 170000 | F17: 70929 | H17: 23000 | I17: =L17*D57 -> 3846.1538 | J17: =IFERROR(__xludf.DUMMYFUNCTION("IMPORTRANGE(""https://docs.google.com/spreadsheets/d/1JJd44_6b1hsmD6e8liei_zzkkh-GYab6gE4K23IJPVI/edit?gid=0#gid=0&range=J95"",""'Лист1'!X411"")"),539775.1799999994) -> 539775.18 | K17: =B17-C17-D17-E17-F17-I17+J17-G17-H17-80000 -> 0.026153845 | L17: =B17/B57 -> 3846.1538
K18: 0
A19: Али ОП | I19: =L19*D59 -> 0 | K19: 0 | L19: =B19/B59 -> 0
A20: Маркетинг
A21: Нурым | B21: 0 | I21: =L21*D61 -> 0 | K21: =B21-C21-D21-E21-F21-I21+J21-G21-H21 -> 0 | L21: =B21/B61 -> 0
A22: СММ | I22: =L22*D62 -> 0 | K22: =B22-C22-D22-E22-F22-I22+J22-G22-H22 -> 0 | L22: =B22/B62 -> 0
A23: Жангелди | B23: 0 | I23: =L23*D63 -> 0 | K23: =B23-C23-D23-E23-F23-I23+J23-G23-H23 -> 0 | L23: =B23/B63 -> 0
A24: Амина Дизайнер | B24: 0 | I24: =L24*D64 -> 0 | K24: =B24-C24-D24-E24-F24-I24+J24-G24-H24 -> 0 | L24: =B24/B64 -> 0
A25: БЭК Офис
A26: Камила Офис менеджер | B26: 250000 | C26: 187000 | D26: 50000 | H26: 13000 | I26: =L26*D67 -> 0 | K26: =B26-C26-D26-E26-F26-I26+J26-G26-H26 -> 0 | L26: =B26/B67 -> 9615.3846
A27: Гульжахан Бухгалтер | B27: 150000 | C27: 150000 | I27: =L27*D68 -> 0 | K27: =B27-C27-D27-E27-F27-I27+J27-G27-H27 -> 0 | L27: =B27/B68 -> 5769.2308
A29: Асем уборщица | B29: 80000 | C29: 43077 | I29: =L29*D71 -> 36923.077 | K29: =B29-C29-D29-E29-F29-I29+J29-G29-H29 -> -0.076923077 | L29: =B29/B71 -> 3076.9231
A30: Сауле уборщиц | B30: 80000 | C30: 36923 | I30: =L30*D72 -> 43076.923 | K30: =B30-C30-D30-E30-F30-I30+J30-G30-H30 -> 0.076923077 | L30: =B30/B72 -> 3076.9231
A31: Общ | B31: =SUM(B2:B28) -> 4758678 | C31: =B31+J15+J17 -> 5673023.8 | K31: =SUM(K2:K29) -> 18720.25
A37: ФИО | B37: рабочие дни за март | C37: отработано | D37: Дни отсутствия | E37: график работы | J37: долг по зп: | K37: ='Февраль'!K34+'Март'!K38+'Апрель'!K35+'Май'!K33+'Июнь 2025'!K29+'Июль 2025'!K31+K31+'Август 2025'!K31 -> 2677850.6 | L37: =K37-'Февраль'!K4-'Март'!K5-'Апрель'!K5-'Май'!K5-'Июнь 2025'!K5-'Июль 2025'!K5-K5 -> 1279130.6
A38: Аружан | B38: 18 | C38: =B38-D38 -> 18 | D38: 0 | E38: 45327
A39: Нуртилеу | B39: 18 | C39: =B39-D39 -> 18 | D39: 0 | E39: 45327 | J39: долг по кредитам: | K39: =K40+K41+K42+K43 -> 9432189
A40: Учебный отдел | J40: жанерке | K40: 1500000
A41: Салтанат | B41: 21 | C41: =B41-D41 -> 21 | D41: 0 | E41: 45327 | J41: Аружан | K41: =4632189-700000-300000-700000 -> 2932189
A42: Алуа (Онлайн) | B42: 21 | C42: =B42-D42 -> 21 | D42: 0 | E42: 45327 | J42: Нуртилеу | K42: 2000000
A43: Алима | B43: 21 | C43: =B43-D43 -> 21 | D43: 0 | E43: 45327 | J43: Салтанат | K43: 3000000
A44: Асем Психолог | B44: 21 | C44: =B44-D44 -> 21 | D44: 0 | E44: 45297
A45: Асель | B45: 21 | C45: =B45-D45 -> 21 | D45: 0 | E45: 45327 | J45: налог | K45: 1500000
A46: Диас международн отд (Онлайн) | B46: 26 | C46: =B46-D46 -> 26 | E46: 45327
A47: Жангелди | B47: 10 | C47: =B47-D47 -> 10 | D47: 0 | E47: 45327
A48: Мерей Сат | B48: 21 | C48: =B48-D48 -> 21 | D48: 0 | E48: 45297
A49: Miracle | B49: 10 | C49: =B49-D49 -> 10 | D49: 0 | E49: 45327 | J49: возвратники | K49: =SUM(K50:K53) -> 0
A50: Адип SAT | B50: 18 | C50: =B50-D50 -> 18 | D50: 0 | E50: 45327 | J50: Айнур | K50: =600000-200000-400000 -> 0
A51: Дамир SAT | B51: 18 | C51: =B51-D51 -> 18 | D51: 0 | E51: 45327 | J51: Думан | K51: =645000-645000 -> 0
A52: Шолпан | B52: 18 | C52: =B52-D52 -> 18 | D52: 0 | E52: 45327 | J52: Алимаргулан | K52: =330000-330000 -> 0
A53: Отдел продаж | J53: Жушуан | K53: =750000-750000 -> 0
A54: Мадияр РОП | B54: 26 | C54: =B54-D54 -> 25 | D54: 1 | E54: 45297
A55: Динара колл центр | B55: 26 | C55: =B55-D55 -> 26 | E55: 45297
A56: Дильназ | B56: 26 | C56: =B56-D56 -> 21 | D56: 5 | E56: 45297
A57: Анель ОП + координатор 21.02 | B57: 26 | C57: =B57-D57 -> 25 | D57: 1 | E57: 45297
J58: Дильназ | K58: запас 500к за сат
A59: Али ОП | B59: 26 | C59: =B59-D59 -> 26 | D59: 0 | E59: 45297 | J59: Аян | K59: 400к
A60: Маркетинг | J60: Мира | K60: 450к
A61: Нурым | B61: 26 | C61: =B61-D61 -> 26 | D61: 0 | E61: 45297 | K61: =500-300 -> 200
A62: СММ Асем | B62: 21 | C62: =B62-D62 -> 21 | D62: 0 | E62: 45297 | J62: гелик | K62: 200 пред оплата
A63: Жангелди | B63: 25 | C63: =B63-D63 -> 6 | D63: 19 | E63: 45327
A64: Амина Дизайнер | B64: 21 | C64: =B64-D64 -> 21 | D64: 0 | E64: 45327
A65: Алена | B65: 21 | C65: =B65-D65 -> 21 | D65: 0 | E65: 45327
A66: БЭК Офис
A67: Камила Офис менеджер | B67: 26 | C67: =B67-D67 -> 26 | E67: 45297
A68: Гульжахан Бухгалтер | B68: 26 | C68: =B68-D68 -> 26 | E68: 45327
A69: Бахадыр Юрист | B69: 24 | C69: =B69-D69 -> 24 | E69: 45327
A70: Жулдыз (уборщица) | B70: 25 | C70: =B70-D70 -> 25 | E70: 45327
A71: Асем(уборщица) | B71: 26 | C71: =B71-D71 -> 14 | D71: 12 | E71: 45327
A72: Сауле уборщица | B72: 26 | C72: =B72-D72 -> 12 | D72: 14

Sheet Октябрь 2025
A1: Имя сотрудника | B1: зарплата за февраль | C1: аванс 1 | D1: аванс 2 | E1: аванс 3 | F1: аванс 4 | G1: На ДР | H1: Штрафы | I1: не выход на работу | J1: премия и % | K1: остаток зп на Сентябрь | L1: за 1 день
A2: Аружан | B2: 300000 | C2: 300000 | I2: =L2*D43 -> 0 | K2: =B2-C2-D2-E2-F2-I2+J2-G2-H2 -> 0 | L2: =B2/B43 -> 16666.667
A3: Нуртилеу | B3: 500000 | C3: 225000 | D3: 100000 | I3: =L3*D44 -> 0 | K3: =B3-C3-D3-E3-F3-I3+J3-G3 -> 175000 | L3: =B3/B44 -> 27777.778
A4: Учебный отдел
A5: Салтанат | B5: 500000 | C5: 50000 | E5: 102000 | G5: 5000 | I5: =L5*D46 -> 0 | K5: =B5-C5-D5-E5-F5-I5+J5-G5-H5 -> 343000 | L5: =B5/B46 -> 23809.524
A6: Алуа (Онлайн) | B6: =94500+100000 -> 194500 | C6: 194500 | I6: =L6*D47 -> 0 | K6: =B6-C6-D6-E6-F6-I6+J6-G6 -> 0 | L6: =B6/B47 -> 9261.9048 | M6: онлайн
A7: Султан | B7: =243000+75000+130000 -> 448000 | C7: 240000 | D7: 75000 | E7: 130000 | G7: 3000 | I7: =L7*D52 -> 0 | K7: =B7-C7-D7-E7-F7-I7+J7-G7-H7 -> 0 | L7: =B7/B52 -> 44800 | M7: по часам | N7: по 3 к | O7: 80 ч до 22окт
A8: Мади | B8: 82500 | C8: 82500 | I8: =L8*D50 -> 0 | K8: =B8-C8-D8-E8-F8-I8+J8-G8 -> 0 | L8: =B8/B50 -> 3928.5714
A9: Мадина международн отд (Онлайн) | B9: 200000 | C9: 200000 | I9: =L9*D51 -> 0 | K9: =B9-C9-D9-E9-F9-I9+J9-G9 -> 0 | L9: =B9/B51 -> 7692.3077
A10: Мерей Сат | B10: 104000 | G10: 3000 | H10: 101000 | I10: =L10*D53 -> 0 | K10: =B10-C10-D10-E10-F10-I10+J10-G10-H10 -> 0 | L10: =B10/B53 -> 4952.381 | M10: по часам | N10: по 5 к
A11: Динара колл центр | B11: 350000 | C11: 200000 | D11: 150000 | I11: =L11*D60 -> 0 | K11: =B11-C11-D11-E11-F11-I11+J11-G11-H11 -> 0 | L11: =B11/B60 -> 13461.538
A12: Диас международн | B12: 0 | I12: =L12*D55 -> 0 | K12: =B12-C12-D12-E12-F12-I12+J12-G12 -> 0 | L12: =B12/B55 -> 0
A13: Алтынбек Проф ориентолог | B13: 60000 | C13: 60000 | I13: =L13*D55 -> 0 | K13: =B13-C13-D13-E13-F13-I13+J13-G13 -> 0 | L13: =B13/B55 -> 3333.3333 | M13: консультация | N13: по 10 к
A14: Дильяра | B14: 289500 | C14: 286500 | G14: 3000 | I14: =L14*D57 -> 0 | K14: =B14-C14-D14-E14-F14-I14+J14-G14-H14 -> 0 | L14: =B14/B57 -> 16083.333
A15: Илона | B15: 112000 | C15: 112000 | I15: 0 | K15: =B15-C15-D15-E15-F15-I15+J15-G15-H15 -> 0 | L15: 0
A16: Сулейман | B16: 40000 | C16: 40000 | K16: =B16-C16-D16-E16-F16-I16+J16-G16-H16 -> 0 | L16: =B16/B59 -> 1538.4615
A17: Рустам | B17: 16000 | C17: 16000 | I17: =L17*D60 -> 0 | K17: =B17-C17-D17-E17-F17-I17+J17-G17-H17 -> 0 | L17: =B17/B60 -> 615.38462
A18: Абдулазиз | B18: 42000 | C18: 42000 | I18: =L18*D61 -> 0 | K18: =B18-C18-D18-E18-F18-I18+J18-G18-H18 -> 0 | L18: =B18/B61 -> 1615.3846
A19: Отдел продаж
A20: Мадияр РОП | B20: 200000 | C20: 500000 | D20: 50000 | H20: 30000 | I20: =L20*D59 -> 15384.615 | J20: =IFERROR(__xludf.DUMMYFUNCTION("IMPORTRANGE(""https://docs.google.com/spreadsheets/d/1JJd44_6b1hsmD6e8liei_zzkkh-GYab6gE4K23IJPVI/edit?gid=0#gid=0&range=J95"",""'Лист1'!K448"")"),459875.07000000065) -> 459875.07 | K20: =B20-C20-D20-E20-F20-I20+J20-G20-H20+100000 -> 164490.45 | L20: =B20/B59 -> 7692.3077
A21: Инжу | B21: 100000 | C21: 276000 | I21: =L21*D61 -> 0 | J21: 176000 | K21: =B21-C21-D21-E21-F21-I21+J21-G21-H21 -> 0 | L21: =B21/B61 -> 3846.1538
A22: Анель ОП | B22: 100000 | C22: 220000 | D22: 235000 | I22: =L22*D62 -> 3846.1538 | J22: =IFERROR(__xludf.DUMMYFUNCTION("IMPORTRANGE(""https://docs.google.com/spreadsheets/d/1JJd44_6b1hsmD6e8liei_zzkkh-GYab6gE4K23IJPVI/edit?gid=0#gid=0&range=J95"",""'Лист1'!W438"")"),314725.5) -> 314725.5 | K22: 0 | L22: =B22/B62 -> 3846.1538 | M22: -49121
A23: Дарина ОП | B23: 100000 | C23: 280000 | J23: 180000 | K23: =B23-C23-D23-E23-F23-I23+J23-G23-H23 -> 0
A24: Али ОП | I24: =L24*D64 -> 0 | K24: 0 | L24: =B24/B64 -> 0 | O24: =K18++K15+200000+K13+K34+K17 -> 200000
A25: Маркетинг
A26: Нурым | B26: 250000 | C26: 250000 | I26: =L26*D66 -> 0 | K26: =B26-C26-D26-E26-F26-I26+J26-G26-H26 -> 0 | L26: =B26/B66 -> 8620.6897 | M26: c 15
A27: Бота СММ | B27: 65000 | C27: 60000 | G27: 5000 | I27: 0 | K27: =B27-C27-D27-E27-F27-I27+J27-G27-H27 -> 0 | L27: =B27/B67 -> 2241.3793 | M27: c 6
A28: Жангелди | B28: 150000 | C28: 150000 | I28: =L28*D68 -> 0 | K28: =B28-C28-D28-E28-F28-I28+J28-G28-H28 -> 0 | L28: =B28/B68 -> 5172.4138 | M28: 23 ого октября
A29: Амина Дизайнер | B29: 130000 | C29: 130000 | I29: 0 | K29: =B29-C29-D29-E29-F29-I29+J29-G29-H29 -> 0 | L29: =B29/B69 -> 4482.7586 | M29: c 10
A30: БЭК Офис
A31: Камила Офис менеджер | B31: 250000 | C31: 100000 | D31: 100000 | E31: 50000 | I31: =L31*D72 -> 0 | K31: =B31-C31-D31-E31-F31-I31+J31-G31-H31 -> 0 | L31: =B31/B72 -> 9615.3846
A32: Гульжахан Бухгалтер | B32: 150000 | I32: =L32*D73 -> 0 | K32: =B32-C32-D32-E32-F32-I32+J32-G32-H32 -> 150000 | L32: =B32/B73 -> 5769.2308
A34: Асем уборщица | B34: 80000 | C34: 80000 | I34: =L34*D76 -> 0 | K34: =B34-C34-D34-E34-F34-I34+J34-G34-H34 -> 0 | L34: =B34/B76 -> 2962.963
A36: Общ | B36: =SUM(B2:B33) -> 4733500 | C36: =B36+J20+J22 -> 5508100.6 | K36: =SUM(K2:K34) -> 832490.45
N40: =K6+K7+K8+K9+K10+K11+K13+K14+K15+K15+K16+K17+K18+K21+K34 -> 0
L41: =K42-'Февраль'!K4-'Март'!K5-'Апрель'!K5-'Май'!K5-'Июнь 2025'!K5-'Июль 2025'!K5-K5 -> 1609105.3
A42: ФИО | B42: рабочие дни за март | C42: отработано | D42: Дни отсутствия | E42: график работы | J42: долг по зп: | K42: ='Февраль'!K34+'Март'!K38+'Апрель'!K35+'Май'!K33+'Июнь 2025'!K29+'Июль 2025'!K31+K36 -> 3332105.3
A43: Аружан | B43: 18 | C43: =B43-D43 -> 18 | D43: 0 | E43: 45327
A44: Нуртилеу | B44: 18 | C44: =B44-D44 -> 18 | D44: 0 | E44: 45327 | J44: долг по кредитам: | K44: =K45+K46+K47+K48 -> 8032189
A45: Учебный отдел | J45: жанерке | K45: 400000
A46: Салтанат | B46: 21 | C46: =B46-D46 -> 21 | D46: 0 | E46: 45327 | J46: Аружан | K46: =4632189-700000-300000-700000-300000 -> 2632189
A47: Алуа (Онлайн) | B47: 21 | C47: =B47-D47 -> 21 | D47: 0 | E47: 45327 | J47: Нуртилеу | K47: 2000000
A48: Султан | B48: 21 | C48: =B48-D48 -> 21 | D48: 0 | E48: 45327 | J48: Салтанат | K48: 3000000
A49: Мади | B49: 21 | C49: =B49-D49 -> 21 | D49: 0 | E49: 45297
A50: Мадина международн отд (Онлайн) | B50: 21 | C50: =B50-D50 -> 21 | D50: 0 | E50: 45327 | J50: налог | K50: 1500000
A51: Мерей Сат | B51: 26 | C51: =B51-D51 -> 26 | E51: 45327
A52: Динара колл центр | B52: 10 | C52: =B52-D52 -> 10 | D52: 0 | E52: 45327
A53: Диас международн | B53: 21 | C53: =B53-D53 -> 21 | D53: 0 | E53: 45297
A54: Алтынбек Проф ориентолог | B54: 10 | C54: =B54-D54 -> 10 | D54: 0 | E54: 45327 | J54: возвратники | K54: =SUM(K55:K58) -> 0
A55: Дильяра | B55: 18 | C55: =B55-D55 -> 18 | D55: 0 | E55: 45327 | J55: Айнур | K55: =600000-200000-400000 -> 0
A56: - | B56: 18 | C56: =B56-D56 -> 18 | D56: 0 | E56: 45327 | J56: Думан | K56: =645000-645000 -> 0
A57: - | B57: 18 | C57: =B57-D57 -> 18 | D57: 0 | E57: 45327 | J57: Алимаргулан | K57: =330000-330000 -> 0
A58: Отдел продаж | J58: Жушуан | K58: =750000-750000 -> 0
A59: Мадияр РОП | B59: 26 | C59: =B59-D59 -> 24 | D59: 2 | E59: 45297
A60: Динара колл центр | B60: 26 | C60: =B60-D60 -> 26 | D60: 0 | E60: 45297
A61: Инжу | B61: 26 | C61: =B61-D61 -> 26 | D61: 0 | E61: 45297 | J61: Асельхан | K61: =1260000-1260000 -> 0
A62: Анель ОП + координатор 21.02 | B62: 26 | C62: =B62-D62 -> 25 | D62: 1 | E62: 45297
A64: Али ОП | B64: 26 | C64: =B64-D64 -> 26 | D64: 0 | E64: 45297
A65: Маркетинг
A66: Нурым | B66: 29 | C66: =B66-D66 -> 29 | D66: 0 | E66: 45297
A67: СММ Бота | B67: 29 | C67: =B67-D67 -> 24 | D67: 5 | E67: 45297
A68: Жангелди | B68: 29 | C68: =B68-D68 -> 29 | D68: 0 | E68: 45327
A69: Амина Дизайнер | B69: 29 | C69: =B69-D69 -> 20 | D69: 9 | E69: 45327
A70: Алена | B70: 29 | C70: =B70-D70 -> 29 | D70: 0 | E70: 45327
A71: БЭК Офис
A72: Камила Офис менеджер | B72: 26 | C72: =B72-D72 -> 26 | E72: 45297
A73: Гульжахан Бухгалтер | B73: 26 | C73: =B73-D73 -> 26 | E73: 45327
A74: Бахадыр Юрист | B74: 24 | C74: =B74-D74 -> 24 | E74: 45327
A75: Жулдыз (уборщица) | B75: 25 | C75: =B75-D75 -> 25 | E75: 45327
A76: Асем(уборщица) | B76: 27 | C76: =B76-D76 -> 27 | E76: 45327

Sheet Ноябрь 2025
A1: Имя сотрудника | B1: зарплата за февраль | C1: аванс 1 | D1: аванс 2 | E1: аванс 3 | F1: аванс 4 | G1: На ДР | H1: Штрафы | I1: не выход на работу | J1: премия и % | K1: остаток зп на Сентябрь | L1: за 1 день
A2: Аружан | B2: 330000 | C2: 330000 | I2: =L2*D44 -> 0 | K2: =B2-C2-D2-E2-F2-I2+J2-G2-H2 -> 0 | L2: =B2/B44 -> 18333.333
A3: Нуртилеу | B3: 500000 | C3: 100000 | D3: 82000 | E3: 70000 | F3: 41738 | I3: =L3*D45 -> 0 | K3: =B3-C3-D3-E3-F3-I3+J3-G3 -> 206262 | L3: =B3/B45 -> 27777.778
A4: Учебный отдел
A5: Салтанат | B5: 500000 | C5: 61000 | D5: 318000 | E5: 107000 | I5: =L5*D47 -> 0 | K5: =B5-C5-D5-E5-F5-I5+J5-G5-H5 -> 14000 | L5: =B5/B47 -> 23809.524
A6: Алуа (Онлайн) | B6: 182000 | C6: 100000 | D6: 82000 | I6: =L6*D48 -> 0 | K6: =B6-C6-D6-E6-F6-I6+J6-G6 -> 0 | L6: =B6/B48 -> 8666.6667 | M6: онлайн
A7: Султан | B7: =68250+75000+12000 -> 155250 | C7: 12000 | D7: 50000 | E7: 40000 | F7: =41250+12000 -> 53250 | I7: =L7*D53 -> 0 | K7: =B7-C7-D7-E7-F7-I7+J7-G7-H7 -> 0 | L7: =B7/B53 -> 15525 | M7: по часам | N7: по 3 к | O7: 80 ч до 22окт
A8: Мади | B8: 0 | I8: =L8*D51 -> 0 | K8: =B8-C8-D8-E8-F8-I8+J8-G8 -> 0 | L8: =B8/B51 -> 0
A9: Мадина международн отд (Онлайн) | B9: 200000 | C9: 200000 | I9: =L9*D52 -> 0 | K9: =B9-C9-D9-E9-F9-I9+J9-G9 -> 0 | L9: =B9/B52 -> 7692.3077
A10: Ванесса | B10: 75000 | C10: 75000 | I10: =L10*D54 -> 0 | K10: =B10-C10-D10-E10-F10-I10+J10-G10-H10 -> 0 | L10: =B10/B54 -> 3571.4286 | M10: по часам | N10: по 5 к
A11: Динара колл центр | B11: 350000 | C11: 302885 | I11: =L11*D61 -> 47115.385 | K11: =B11-C11-D11-E11-F11-I11+J11-G11-H11 -> -0.38461538 | L11: =B11/B61 -> 13461.538
A12: Диас международн | B12: 200000 | C12: 80000 | I12: =L12*D56 -> 123076.92 | J12: 80000 | K12: 0 | L12: =B12/B56 -> 7692.3077
A13: Алтынбек Проф ориентолог | B13: 100000 | C13: 100000 | I13: 0 | K13: =B13-C13-D13-E13-F13-I13+J13-G13 -> 0 | L13: =B13/B56 -> 3846.1538 | M13: консультация | N13: по 10 к
A14: Дильяра | B14: 289500 | C14: 50000 | D14: 239500 | I14: =L14*D58 -> 0 | K14: =B14-C14-D14-E14-F14-I14+J14-G14-H14 -> 0 | L14: =B14/B58 -> 16083.333
A15: Илона | B15: 304000 | C15: 304000 | I15: 0 | K15: =B15-C15-D15-E15-F15-I15+J15-G15-H15 -> 0 | L15: 0
A16: Сулейман | B16: 80000 | C16: 80000 | I16: 0 | K16: =B16-C16-D16-E16-F16-I16+J16-G16-H16 -> 0 | L16: =B16/B60 -> 3076.9231
A17: Рустам | B17: 190000 | C17: 70000 | D17: 72500 | E17: 47500 | I17: 0 | K17: =B17-C17-D17-E17-F17-I17+J17-G17-H17 -> 0 | L17: =B17/B61 -> 7307.6923 | M17: 4кчас
A18: Абдулазиз | B18: 58000 | C18: 43500 | D18: 14500 | I18: =L18*D62 -> 0 | K18: =B18-C18-D18-E18-F18-I18+J18-G18-H18 -> 0 | L18: =B18/B62 -> 2230.7692 | M18: 4к час
A19: Ариана | B19: 199000 | C19: 90000 | D19: 109000 | K19: =B19-C19-D19-E19-F19-I19+J19-G19-H19 -> 0
A20: Отдел продаж
A21: Мадияр РОП | B21: 200000 | C21: 90000 | D21: 200000 | H21: 10000 | I21: =L21*D60 -> 38461.538 | J21: =IFERROR(__xludf.DUMMYFUNCTION("IMPORTRANGE(""https://docs.google.com/spreadsheets/d/1JJd44_6b1hsmD6e8liei_zzkkh-GYab6gE4K23IJPVI/edit?gid=0#gid=0&range=J95"",""'Лист1'!K475"")"),147709.30050000027) -> 147709.3 | K21: =B21-C21-D21-E21-F21-I21+J21-G21-H21 -> 9247.762 | L21: =B21/B60 -> 7692.3077
A22: Инжу КЦ | B22: 100000 | C22: 288000 | I22: =L22*D62 -> 0 | J22: 188000 | K22: =B22-C22-D22-E22-F22-I22+J22-G22-H22 -> 0 | L22: =B22/B62 -> 3846.1538
A23: Анель ОП | B23: 100000 | C23: 49121 | D23: 6000 | E23: 100000 | F23: =50000+21160 -> 71160 | H23: 10000 | I23: =L23*D63 -> 9615.3846 | J23: =IFERROR(__xludf.DUMMYFUNCTION("IMPORTRANGE(""https://docs.google.com/spreadsheets/d/1JJd44_6b1hsmD6e8liei_zzkkh-GYab6gE4K23IJPVI/edit?gid=0#gid=0&range=J95"",""'Лист1'!V465"")"),145896.22799999994) -> 145896.23 | K23: =B23-C23-D23-E23-F23-I23+J23-G23-H23 -> -0.15661538 | L23: =B23/B63 -> 3846.1538
A24: Дарина КЦ | B24: 100000 | C24: 70000 | D24: 100000 | E24: 90000 | J24: 160000 | K24: =B24-C24-D24-E24-F24-I24+J24-G24-H24 -> 0
I25: =L25*D65 -> 0 | K25: 0 | L25: =B25/B65 -> 0
A26: Маркетинг
A27: Нурым | B27: 0 | I27: =L27*D67 -> 0 | K27: =B27-C27-D27-E27-F27-I27+J27-G27-H27 -> 0 | L27: =B27/B67 -> 0 | M27: c 15
A28: Точка роста | B28: 500000 | C28: 500000 | I28: 0 | K28: =B28-C28-D28-E28-F28-I28+J28-G28-H28 -> 0 | L28: =B28/B68 -> 17241.379 | M28: c 6
A29: Жангелди | B29: 150000 | C29: 112500 | D29: 37500 | I29: =L29*D69 -> 0 | K29: =B29-C29-D29-E29-F29-I29+J29-G29-H29 -> 0 | L29: =B29/B69 -> 5172.4138 | M29: 23 ого октября
A30: Амина Дизайнер | B30: 0 | I30: =L30*D70 -> 0 | K30: =B30-C30-D30-E30-F30-I30+J30-G30-H30 -> 0 | L30: =B30/B70 -> 0 | M30: c 10
A31: БЭК Офис
A32: Камила Офис менеджер | B32: 250000 | C32: 50000 | D32: 20000 | E32: 50000 | H32: 20000 | I32: =L32*D73 -> 0 | K32: =B32-C32-D32-E32-F32-I32+J32-G32-H32 -> 110000 | L32: =B32/B73 -> 9615.3846
A33: Гульжахан Бухгалтер | B33: 150000 | I33: =L33*D74 -> 0 | K33: =B33-C33-D33-E33-F33-I33+J33-G33-H33 -> 150000 | L33: =B33/B74 -> 5769.2308
A35: Асем уборщица | B35: 80000 | C35: 71111 | I35: =L35*D77 -> 8888.8889 | K35: =B35-C35-D35-E35-F35-I35+J35-G35-H35 -> 0.11111111 | L35: =B35/B77 -> 2962.963
A37: Общ | B37: =SUM(B2:B34) -> 5262750 | C37: =B37+J21+J23 -> 5556355.5 | K37: =SUM(K2:K35) -> 489509.33
L42: =K43-'Февраль'!K4-'Март'!K5-'Апрель'!K5-'Май'!K5-'Июнь 2025'!K5-'Июль 2025'!K5-K5 -> 1595124.1
A43: ФИО | B43: рабочие дни за март | C43: отработано | D43: Дни отсутствия | E43: график работы | J43: долг по зп: | K43: ='Февраль'!K34+'Март'!K38+'Апрель'!K35+'Май'!K33+'Июнь 2025'!K29+'Июль 2025'!K31+K37 -> 2989124.1
A44: Аружан | B44: 18 | C44: =B44-D44 -> 18 | D44: 0 | E44: 45327
A45: Нуртилеу | B45: 18 | C45: =B45-D45 -> 18 | D45: 0 | E45: 45327 | J45: долг по кредитам: | K45: =K46+K47+K48+K49 -> 7702189
A46: Учебный отдел | J46: жанерке | K46: 400000
A47: Салтанат | B47: 21 | C47: =B47-D47 -> 21 | D47: 0 | E47: 45327 | J47: Аружан | K47: =4632189-700000-300000-700000-300000-270000-60000 -> 2302189
A48: Алуа (Онлайн) | B48: 21 | C48: =B48-D48 -> 21 | D48: 0 | E48: 45327 | J48: Нуртилеу | K48: 2000000
A49: Султан | B49: 21 | C49: =B49-D49 -> 21 | D49: 0 | E49: 45327 | J49: Салтанат | K49: 3000000
A50: Мади | B50: 21 | C50: =B50-D50 -> 21 | D50: 0 | E50: 45297
A51: Мадина международн отд (Онлайн) | B51: 21 | C51: =B51-D51 -> 21 | D51: 0 | E51: 45327 | J51: налог | K51: 1500000
A52: Мерей Сат | B52: 26 | C52: =B52-D52 -> 26 | E52: 45327
A53: Динара колл центр | B53: 10 | C53: =B53-D53 -> 10 | D53: 0 | E53: 45327
A54: Диас международн | B54: 21 | C54: =B54-D54 -> 21 | D54: 0 | E54: 45297
A55: Алтынбек Проф ориентолог | B55: 10 | C55: =B55-D55 -> 10 | D55: 0 | E55: 45327 | J55: возвратники | K55: =SUM(K56:K59) -> 0
A56: Дильяра | B56: 26 | C56: =B56-D56 -> 10 | D56: 16 | E56: 45327 | J56: Айнур | K56: =600000-200000-400000 -> 0
A57: - | B57: 18 | C57: =B57-D57 -> 18 | D57: 0 | E57: 45327 | J57: Думан | K57: =645000-645000 -> 0
A58: - | B58: 18 | C58: =B58-D58 -> 18 | D58: 0 | E58: 45327 | J58: Алимаргулан | K58: =330000-330000 -> 0
A59: Отдел продаж | J59: Жушуан | K59: =750000-750000 -> 0
A60: Мадияр РОП | B60: 26 | C60: =B60-D60 -> 21 | D60: 5 | E60: 45297
A61: Динара колл центр | B61: 26 | C61: =B61-D61 -> 22.5 | D61: 3.5 | E61: 45297
A62: Инжу | B62: 26 | C62: =B62-D62 -> 26 | D62: 0 | E62: 45297 | J62: Асельхан | K62: =1260000-1260000 -> 0
A63: Анель ОП + координатор 21.02 | B63: 26 | C63: =B63-D63 -> 23.5 | D63: 2.5 | E63: 45297
A65: Али ОП | B65: 26 | C65: =B65-D65 -> 26 | D65: 0 | E65: 45297
A66: Маркетинг
A67: Нурым | B67: 29 | C67: =B67-D67 -> 29 | D67: 0 | E67: 45297
A68: СММ Бота | B68: 29 | C68: =B68-D68 -> 24 | D68: 5 | E68: 45297
A69: Жангелди | B69: 29 | C69: =B69-D69 -> 29 | D69: 0 | E69: 45327
A70: Амина Дизайнер | B70: 29 | C70: =B70-D70 -> 20 | D70: 9 | E70: 45327
A71: Алена | B71: 29 | C71: =B71-D71 -> 29 | D71: 0 | E71: 45327
A72: БЭК Офис
A73: Камила Офис менеджер | B73: 26 | C73: =B73-D73 -> 26 | E73: 45297
A74: Гульжахан Бухгалтер | B74: 26 | C74: =B74-D74 -> 26 | E74: 45327
A75: Бахадыр Юрист | B75: 24 | C75: =B75-D75 -> 24 | E75: 45327
A76: Жулдыз (уборщица) | B76: 25 | C76: =B76-D76 -> 25 | E76: 45327
A77: Асем(уборщица) | B77: 27 | C77: =B77-D77 -> 24 | D77: 3 | E77: 45327

Sheet Декабрь 2025 
A1: Имя сотрудника | B1: зарплата за февраль | C1: аванс 1 | D1: аванс 2 | E1: аванс 3 | F1: аванс 4 | G1: На ДР | H1: Штрафы | I1: не выход на работу | J1: премия и % | K1: остаток зп на Сентябрь | L1: за 1 день
A2: Аружан | B2: 330000 | C2: 220000 | D2: 110000 | I2: =L2*D44 -> 0 | K2: =B2-C2-D2-E2-F2-I2+J2-G2-H2 -> 0 | L2: =B2/B44 -> 18333.333
A3: Нуртилеу | B3: 500000 | C3: 88000 | I3: =L3*D45 -> 0 | K3: =B3-C3-D3-E3-F3-I3+J3-G3 -> 412000 | L3: =B3/B45 -> 27777.778
A4: Учебный отдел
A5: Салтанат | B5: 500000 | I5: =L5*D47 -> 0 | K5: =B5-C5-D5-E5-F5-I5+J5-G5-H5 -> 500000 | L5: =B5/B47 -> 23809.524
A6: Алуа (Онлайн) | B6: 174000 | C6: 152250 | I6: =L6*D48 -> 0 | K6: =B6-C6-D6-E6-F6-I6+J6-G6 -> 21750 | L6: =B6/B48 -> 8285.7143 | M6: онлайн
A7: Султан | B7: =130000+59500+75000 -> 264500 | C7: 189500 | D7: 75000 | I7: =L7*D53 -> 0 | K7: =B7-C7-D7-E7-F7-I7+J7-G7-H7 -> 0 | L7: =B7/B53 -> 26450 | M7: по часам | N7: по 3 к | O7: 80 ч до 22окт
A8: Мади | B8: 0 | I8: =L8*D51 -> 0 | K8: =B8-C8-D8-E8-F8-I8+J8-G8 -> 0 | L8: =B8/B51 -> 0
A9: Мадина международн отд (Онлайн) | B9: 200000 | C9: 200000 | I9: =L9*D52 -> 0 | K9: =B9-C9-D9-E9-F9-I9+J9-G9 -> 0 | L9: =B9/B52 -> 7692.3077
A10: Ванесса | B10: 96000 | C10: 96000 | I10: =L10*D54 -> 0 | K10: =B10-C10-D10-E10-F10-I10+J10-G10-H10 -> 0 | L10: =B10/B54 -> 4571.4286 | M10: по часам | N10: по 5 к
A11: Динара колл центр | B11: 350000 | C11: 350000 | I11: =L11*D61 -> 0 | K11: =B11-C11-D11-E11-F11-I11+J11-G11-H11 -> 0 | L11: =B11/B61 -> 13461.538
A12: Диас международн | B12: 200000 | C12: 276923 | I12: =L12*D56 -> 0 | J12: 76923 | K12: =B12-C12-D12-E12-F12-I12+J12-G12 -> 0 | L12: =B12/B56 -> 11111.111
A13: Циньгун | B13: 70000 | C13: 70000 | I13: =L13*D56 -> 0 | K13: =B13-C13-D13-E13-F13-I13+J13-G13 -> 0 | L13: =B13/B56 -> 3888.8889
A14: Дильяра | B14: 204750 | C14: 204750 | I14: =L14*D58 -> 0 | K14: =B14-C14-D14-E14-F14-I14+J14-G14-H14 -> 0 | L14: =B14/B58 -> 11375
A15: Илона | B15: 172338 | C15: 172338 | I15: 0 | K15: =B15-C15-D15-E15-F15-I15+J15-G15-H15 -> 0 | L15: 0 | N15: оклад 222
A16: Сулейман | B16: 30000 | I16: 0 | K16: =B16-C16-D16-E16-F16-I16+J16-G16-H16 -> 30000 | L16: =B16/B60 -> 1153.8462
A17: Рустам | B17: 58000 | I17: 0 | K17: =B17-C17-D17-E17-F17-I17+J17-G17-H17 -> 58000 | L17: =B17/B61 -> 2230.7692
A18: Абдулазиз | B18: 18000 | C18: 18000 | I18: =L18*D62 -> 0 | K18: =B18-C18-D18-E18-F18-I18+J18-G18-H18 -> 0 | L18: =B18/B62 -> 692.30769
A19: Касымжомарт | B19: 114000 | C19: 114000 | K19: =B19-C19-D19-E19-F19-I19+J19-G19-H19 -> 0
A20: Отдел продаж
A21: Мадияр РОП | B21: 200000 | I21: =L21*D60 -> 69230.769 | J21: =IFERROR(__xludf.DUMMYFUNCTION("IMPORTRANGE(""https://docs.google.com/spreadsheets/d/1JJd44_6b1hsmD6e8liei_zzkkh-GYab6gE4K23IJPVI/edit?gid=0#gid=0&range=J95"",""'Лист1'!K502"")"),105518.99700000028) -> 105519 | K21: =B21-C21-D21-E21-F21-I21+J21-G21-H21 -> 236288.23 | L21: =B21/B60 -> 7692.3077
A22: Инжу КЦ | B22: 0 | I22: =L22*D62 -> 0 | J22: 0 | K22: =B22-C22-D22-E22-F22-I22+J22-G22-H22 -> 0 | L22: =B22/B62 -> 0
A23: Анель ОП | B23: 100000 | C23: 50000 | D23: 155000 | E23: 4108 | I23: =L23*D63 -> 23076.923 | J23: =IFERROR(__xludf.DUMMYFUNCTION("IMPORTRANGE(""https://docs.google.com/spreadsheets/d/1JJd44_6b1hsmD6e8liei_zzkkh-GYab6gE4K23IJPVI/edit?gid=0#gid=0&range=J95"",""'Лист1'!V492"")"),132185.06100000005) -> 132185.06 | K23: =B23-C23-D23-E23-F23-I23+J23-G23-H23 -> 0.13792308 | L23: =B23/B63 -> 3846.1538
A24: Дарина КЦ | B24: 100000 | C24: 80000 | D24: 50000 | E24: 122308 | I24: =L24*D64 -> 7692.3077 | J24: 160000 | K24: =B24-C24-D24-E24-F24-I24+J24-G24-H24 -> -0.30769231 | L24: =B24/B64 -> 3846.1538
I25: =L25*D65 -> 0 | K25: 0 | L25: =B25/B65 -> 0
A26: Маркетинг
A27: Нурым | B27: 0 | I27: =L27*D67 -> 0 | K27: =B27-C27-D27-E27-F27-I27+J27-G27-H27 -> 0 | L27: =B27/B67 -> 0 | M27: c 15
A28: Точка роста | B28: 400000 | C28: 50000 | I28: 0 | K28: =B28-C28-D28-E28-F28-I28+J28-G28-H28 -> 350000 | L28: =B28/B68 -> 13793.103 | M28: c 6
A29: Жангелди | B29: 0 | I29: =L29*D69 -> 0 | K29: =B29-C29-D29-E29-F29-I29+J29-G29-H29 -> 0 | L29: =B29/B69 -> 0 | M29: 23 ого октября
A30: Амина Дизайнер | B30: 0 | I30: =L30*D70 -> 0 | K30: =B30-C30-D30-E30-F30-I30+J30-G30-H30 -> 0 | L30: =B30/B70 -> 0 | M30: c 10
A31: БЭК Офис
A32: Камила Офис менеджер | B32: 250000 | I32: =L32*D73 -> 9615.3846 | K32: =B32-C32-D32-E32-F32-I32+J32-G32-H32 -> 240384.62 | L32: =B32/B73 -> 9615.3846
A33: Гульжахан Бухгалтер | B33: 150000 | I33: =L33*D74 -> 0 | K33: =B33-C33-D33-E33-F33-I33+J33-G33-H33 -> 150000 | L33: =B33/B74 -> 5769.2308
A35: Асем уборщица | B35: 80000 | C35: 77037 | I35: =L35*D77 -> 2962.963 | K35: =B35-C35-D35-E35-F35-I35+J35-G35-H35 -> 0.037037037 | L35: =B35/B77 -> 2962.963
A37: Общ | B37: =SUM(B2:B34) -> 4481588 | C37: =B37+J21+J23 -> 4719292.1 | K37: =SUM(K2:K35) -> 1998422.7
L42: =K43-'Февраль'!K4-'Март'!K5-'Апрель'!K5-'Май'!K5-'Июнь 2025'!K5-'Июль 2025'!K5-K5 -> 4118273.1
A43: ФИО | B43: рабочие дни за март | C43: отработано | D43: Дни отсутствия | E43: график работы | J43: долг по зп: | K43: ='Февраль'!K34+'Март'!K38+'Апрель'!K35+'Май'!K33+'Июнь 2025'!K29+'Июль 2025'!K31+'Август 2025'!K31+'Сентябрь 2025'!K31+'Октябрь 2025'!K36+'Ноябрь 2025'!K37+K37 -> 5998273.1
A44: Аружан | B44: 18 | C44: =B44-D44 -> 18 | D44: 0 | E44: 45327
A45: Нуртилеу | B45: 18 | C45: =B45-D45 -> 18 | D45: 0 | E45: 45327 | J45: долг по кредитам: | K45: =K46+K47+K48+K49 -> 7372189
A46: Учебный отдел | J46: жанерке | K46: 400000
A47: Салтанат | B47: 21 | C47: =B47-D47 -> 21 | D47: 0 | E47: 45327 | J47: Аружан | K47: =4632189-700000-300000-700000-300000-270000-60000-220000-110000 -> 1972189
A48: Алуа (Онлайн) | B48: 21 | C48: =B48-D48 -> 21 | D48: 0 | E48: 45327 | J48: Нуртилеу | K48: 2000000
A49: Султан | B49: 21 | C49: =B49-D49 -> 21 | D49: 0 | E49: 45327 | J49: Салтанат | K49: 3000000
A50: Мади | B50: 21 | C50: =B50-D50 -> 21 | D50: 0 | E50: 45297
A51: Мадина международн отд (Онлайн) | B51: 21 | C51: =B51-D51 -> 21 | D51: 0 | E51: 45327 | J51: налог | K51: 1500000
A52: Мерей Сат | B52: 26 | C52: =B52-D52 -> 26 | E52: 45327
A53: Динара колл центр | B53: 10 | C53: =B53-D53 -> 10 | D53: 0 | E53: 45327
A54: Диас международн | B54: 21 | C54: =B54-D54 -> 21 | D54: 0 | E54: 45297
A55: Алтынбек Проф ориентолог | B55: 10 | C55: =B55-D55 -> 10 | D55: 0 | E55: 45327 | J55: возвратники | K55: =SUM(K56:K59) -> 0
A56: Дильяра | B56: 18 | C56: =B56-D56 -> 18 | D56: 0 | E56: 45327 | J56: Айнур | K56: =600000-200000-400000 -> 0
A57: - | B57: 18 | C57: =B57-D57 -> 18 | D57: 0 | E57: 45327 | J57: Думан | K57: =645000-645000 -> 0
A58: - | B58: 18 | C58: =B58-D58 -> 18 | D58: 0 | E58: 45327 | J58: Алимаргулан | K58: =330000-330000 -> 0
A59: Отдел продаж | J59: Жушуан | K59: =750000-750000 -> 0
A60: Мадияр РОП | B60: 26 | C60: =B60-D60 -> 17 | D60: 9 | E60: 45297
A61: Динара колл центр | B61: 26 | C61: =B61-D61 -> 26 | D61: 0 | E61: 45297
A62: Инжу | B62: 26 | C62: =B62-D62 -> 26 | D62: 0 | E62: 45297 | J62: Асельхан | K62: =1260000-1260000 -> 0
A63: Анель ОП | B63: 26 | C63: =B63-D63 -> 20 | D63: 6 | E63: 45297
A64: Дарина | B64: 26 | C64: =B64-D64 -> 24 | D64: 2
A65: Али ОП | B65: 26 | C65: =B65-D65 -> 26 | D65: 0 | E65: 45297
A66: Маркетинг
A67: Нурым | B67: 29 | C67: =B67-D67 -> 29 | D67: 0 | E67: 45297
A68: СММ Бота | B68: 29 | C68: =B68-D68 -> 24 | D68: 5 | E68: 45297
A69: Жангелди | B69: 29 | C69: =B69-D69 -> 29 | D69: 0 | E69: 45327
A70: Амина Дизайнер | B70: 29 | C70: =B70-D70 -> 20 | D70: 9 | E70: 45327
A71: Алена | B71: 29 | C71: =B71-D71 -> 29 | D71: 0 | E71: 45327
A72: БЭК Офис
A73: Камила Офис менеджер | B73: 26 | C73: =B73-D73 -> 25 | D73: 1 | E73: 45297
A74: Гульжахан Бухгалтер | B74: 26 | C74: =B74-D74 -> 26 | E74: 45327
A75: Бахадыр Юрист | B75: 24 | C75: =B75-D75 -> 24 | E75: 45327
A76: Жулдыз (уборщица) | B76: 25 | C76: =B76-D76 -> 25 | E76: 45327
A77: Асем(уборщица) | B77: 27 | C77: =B77-D77 -> 26 | D77: 1 | E77: 45327

Sheet Январь 2026
A1: Имя сотрудника | B1: зарплата за февраль | C1: аванс 1 | D1: аванс 2 | E1: аванс 3 | F1: аванс 4 | G1: На ДР | H1: Штрафы | I1: не выход на работу | J1: премия и % | K1: остаток зп на Сентябрь | L1: за 1 день
A2: Аружан | B2: 330000 | C2: 220000 | D2: 110000 | I2: =L2*D44 -> 0 | K2: =B2-C2-D2-E2-F2-I2+J2-G2-H2 -> 0 | L2: =B2/B44 -> 18333.333
A3: Нуртилеу | B3: 500000 | C3: 150000 | I3: =L3*D45 -> 0 | K3: =B3-C3-D3-E3-F3-I3+J3-G3 -> 350000 | L3: =B3/B45 -> 27777.778
A4: Учебный отдел
A5: Салтанат | B5: 500000 | C5: 145000 | D5: 150000 | I5: =L5*D47 -> 0 | K5: =B5-C5-D5-E5-F5-I5+J5-G5-H5 -> 205000 | L5: =B5/B47 -> 23809.524
A6: Алуа (Онлайн) | B6: 146000 | C6: 42448 | I6: =L6*D48 -> 0 | K6: =B6-C6-D6-E6-F6-I6+J6-G6 -> 103552 | L6: =B6/B48 -> 6952.381 | M6: онлайн
A7: Султан | B7: =10500+87500 -> 98000 | C7: 98000 | I7: =L7*D53 -> 0 | K7: =B7-C7-D7-E7-F7-I7+J7-G7-H7 -> 0 | L7: =B7/B53 -> 9800 | M7: по часам | N7: по 3 к | O7: 80 ч до 22окт
A8: Мади | B8: 77000 | C8: 77000 | I8: =L8*D51 -> 0 | K8: =B8-C8-D8-E8-F8-I8+J8-G8 -> 0 | L8: =B8/B51 -> 3666.6667
A9: Мадина международн отд (Онлайн) | B9: 200000 | C9: 200000 | I9: =L9*D52 -> 0 | K9: =B9-C9-D9-E9-F9-I9+J9-G9 -> 0 | L9: =B9/B52 -> 7692.3077
A10: Ванесса | B10: =60000+31500 -> 91500 | C10: 91500 | I10: =L10*D54 -> 0 | K10: =B10-C10-D10-E10-F10-I10+J10-G10-H10 -> 0 | L10: =B10/B54 -> 4357.1429 | M10: по часам | N10: по 5 к
A11: Талшын куратор | B11: 250000 | C11: 31250 | I11: =L11*D61 -> 218750 | K11: =B11-C11-D11-E11-F11-I11+J11-G11-H11 -> 0 | L11: =B11/B61 -> 10416.667
A12: Диас международн | B12: 200000 | C12: 200000 | I12: =L12*D56 -> 0 | K12: =B12-C12-D12-E12-F12-I12+J12-G12 -> 0 | L12: =B12/B56 -> 11111.111
A13: Циньгун | B13: 14000 | C13: 14000 | I13: =L13*D56 -> 0 | K13: =B13-C13-D13-E13-F13-I13+J13-G13 -> 0 | L13: =B13/B56 -> 777.77778 | M13: консультация | N13: по 10 к
A14: Динара куратор | B14: 350000 | C14: 50000 | D14: 180000 | I14: =L14*D58 -> 19444.444 | K14: =B14-C14-D14-E14-F14-I14+J14-G14-H14 -> 100555.56 | L14: =B14/B58 -> 19444.444
A15: Илона | B15: 120240 | C15: 120240 | I15: 0 | K15: =B15-C15-D15-E15-F15-I15+J15-G15-H15 -> 0 | L15: 0 | M15: 120240 | N15: 160000 | O15: оклад 160
A16: Сулейман | B16: 0 | I16: 0 | K16: =B16-C16-D16-E16-F16-I16+J16-G16-H16 -> 0 | L16: =B16/B60 -> 0
A17: Рустам | B17: 68000 | C17: 68000 | I17: 0 | K17: =B17-C17-D17-E17-F17-I17+J17-G17-H17 -> 0 | L17: =B17/B61 -> 2833.3333
A18: Абдулазиз | B18: 0 | I18: =L18*D62 -> 0 | K18: =B18-C18-D18-E18-F18-I18+J18-G18-H18 -> 0 | L18: =B18/B62 -> 0
A19: Касымжомарт | B19: =150000+87500 -> 237500 | C19: 142500 | D19: 100000 | J19: 5000 | K19: =B19-C19-D19-E19-F19-I19+J19-G19-H19 -> 0
A20: Отдел продаж
A21: Мадияр РОП | B21: 200000 | I21: =L21*D60 -> 0 | J21: =IFERROR(__xludf.DUMMYFUNCTION("IMPORTRANGE(""https://docs.google.com/spreadsheets/d/1JJd44_6b1hsmD6e8liei_zzkkh-GYab6gE4K23IJPVI/edit?gid=0#gid=0&range=J95"",""'Лист1'!K529"")"),158938.81199999974) -> 158938.81 | K21: =B21-C21-D21-E21-F21-I21+J21-G21-H21 -> 358938.81 | L21: =B21/B60 -> 7692.3077
A22: Инжу КЦ | B22: 0 | I22: =L22*D62 -> 0 | J22: 0 | K22: =B22-C22-D22-E22-F22-I22+J22-G22-H22 -> 0 | L22: =B22/B62 -> 0
A23: Анель ОП | B23: 0 | I23: =L23*D63 -> 0 | J23: 0 | K23: 0 | L23: =B23/B63 -> 0
A24: Дарина КЦ | B24: 100000 | C24: 130000 | I24: =L24*D64 -> 0 | J24: 30000 | K24: =B24-C24-D24-E24-F24-I24+J24-G24-H24 -> 0
I25: =L25*D65 -> 0 | K25: 0 | L25: =B25/B65 -> 0
A26: Маркетинг
A27: Нурым | B27: 0 | I27: =L27*D67 -> 0 | K27: =B27-C27-D27-E27-F27-I27+J27-G27-H27 -> 0 | L27: =B27/B67 -> 0 | M27: c 15
A28: Точка роста | B28: 0 | I28: 0 | K28: =B28-C28-D28-E28-F28-I28+J28-G28-H28 -> 0 | L28: =B28/B68 -> 0 | M28: c 6
A29: Жангелди | B29: 0 | I29: =L29*D69 -> 0 | K29: =B29-C29-D29-E29-F29-I29+J29-G29-H29 -> 0 | L29: =B29/B69 -> 0 | M29: 23 ого октября
A30: Амина Дизайнер | B30: 0 | I30: =L30*D70 -> 0 | K30: =B30-C30-D30-E30-F30-I30+J30-G30-H30 -> 0 | L30: =B30/B70 -> 0 | M30: c 10
A31: БЭК Офис
A32: Камила Офис менеджер | B32: 250000 | I32: =L32*D73 -> 9615.3846 | K32: =B32-C32-D32-E32-F32-I32+J32-G32-H32 -> 240384.62 | L32: =B32/B73 -> 9615.3846
A33: Гульжахан Бухгалтер | B33: 150000 | I33: =L33*D74 -> 0 | K33: =B33-C33-D33-E33-F33-I33+J33-G33-H33 -> 150000 | L33: =B33/B74 -> 5769.2308
A35: Асем уборщица | B35: 80000 | C35: 20000 | I35: =L35*D77 -> 60000 | K35: =B35-C35-D35-E35-F35-I35+J35-G35-H35 -> 0 | L35: =B35/B77 -> 3333.3333
A36: Уборщица Раушан | B36: 80000 | C36: 50000 | D36: 3000 | I36: =L36*D78 -> 26666.667 | K36: =B36-C36-D36-E36-F36-I36+J36-G36-H36 -> 333.33333 | L36: =B36/B78 -> 3333.3333
A37: Общ | B37: =SUM(B2:B34) -> 3882240 | C37: =B37+J21+J23 -> 4041178.8 | K37: =SUM(K2:K35) -> 1508431
L42: =K43-'Февраль'!K4-'Март'!K5-'Апрель'!K5-'Май'!K5-'Июнь 2025'!K5-'Июль 2025'!K5-K5 -> 3923281.4
A43: ФИО | B43: рабочие дни за март | C43: отработано | D43: Дни отсутствия | E43: график работы | J43: долг по зп: | K43: ='Февраль'!K34+'Март'!K38+'Апрель'!K35+'Май'!K33+'Июнь 2025'!K29+'Июль 2025'!K31+'Август 2025'!K31+'Сентябрь 2025'!K31+'Октябрь 2025'!K36+'Ноябрь 2025'!K37+K37 -> 5508281.4
A44: Аружан | B44: 18 | C44: =B44-D44 -> 18 | D44: 0 | E44: 45327
A45: Нуртилеу | B45: 18 | C45: =B45-D45 -> 18 | D45: 0 | E45: 45327 | J45: долг по кредитам: | K45: =K46+K47+K48+K49 -> 7042189
A46: Учебный отдел | J46: жанерке | K46: 400000
A47: Салтанат | B47: 21 | C47: =B47-D47 -> 21 | D47: 0 | E47: 45327 | J47: Аружан | K47: =4632189-700000-300000-700000-300000-270000-60000-220000-110000-330000 -> 1642189
A48: Алуа (Онлайн) | B48: 21 | C48: =B48-D48 -> 21 | D48: 0 | E48: 45327 | J48: Нуртилеу | K48: 2000000
A49: Султан | B49: 21 | C49: =B49-D49 -> 21 | D49: 0 | E49: 45327 | J49: Салтанат | K49: 3000000
A50: Мади | B50: 21 | C50: =B50-D50 -> 21 | D50: 0 | E50: 45297
A51: Мадина международн отд (Онлайн) | B51: 21 | C51: =B51-D51 -> 21 | D51: 0 | E51: 45327 | J51: налог | K51: 1500000
A52: Мерей Сат | B52: 26 | C52: =B52-D52 -> 26 | E52: 45327
A53: Динара колл центр | B53: 10 | C53: =B53-D53 -> 10 | D53: 0 | E53: 45327
A54: Диас международн | B54: 21 | C54: =B54-D54 -> 21 | D54: 0 | E54: 45297
A55: Алтынбек Проф ориентолог | B55: 10 | C55: =B55-D55 -> 10 | D55: 0 | E55: 45327 | J55: возвратники | K55: =SUM(K56:K59) -> 1200000
A56: Дильяра | B56: 18 | C56: =B56-D56 -> 18 | D56: 0 | E56: 45327 | J56: Мама Ажар | K56: 100000
A57: - | B57: 18 | C57: =B57-D57 -> 18 | D57: 0 | E57: 45327 | J57: Лаура | K57: 1000000
A58: - | B58: 18 | C58: =B58-D58 -> 17 | D58: 1 | E58: 45327 | J58: Саян | K58: 100000
A59: Отдел продаж
A60: Мадияр РОП | B60: 26 | C60: =B60-D60 -> 26 | D60: 0 | E60: 45297
A61: Талшын куратор | B61: 24 | C61: =B61-D61 -> 3 | D61: 21 | E61: 45297
A62: Инжу | B62: 26 | C62: =B62-D62 -> 26 | D62: 0 | E62: 45297
A63: Анель ОП | B63: 26 | C63: =B63-D63 -> 20 | D63: 6 | E63: 45297
A64: Дарина | B64: 26 | C64: =B64-D64 -> 23 | D64: 3
A65: Али ОП | B65: 26 | C65: =B65-D65 -> 26 | D65: 0 | E65: 45297
A66: Маркетинг
A67: Нурым | B67: 29 | C67: =B67-D67 -> 29 | D67: 0 | E67: 45297
A68: СММ Бота | B68: 29 | C68: =B68-D68 -> 24 | D68: 5 | E68: 45297
A69: Жангелди | B69: 29 | C69: =B69-D69 -> 29 | D69: 0 | E69: 45327
A70: Амина Дизайнер | B70: 29 | C70: =B70-D70 -> 20 | D70: 9 | E70: 45327
A71: Алена | B71: 29 | C71: =B71-D71 -> 29 | D71: 0 | E71: 45327
A72: БЭК Офис
A73: Камила Офис менеджер | B73: 26 | C73: =B73-D73 -> 25 | D73: 1 | E73: 45297
A74: Гульжахан Бухгалтер | B74: 26 | C74: =B74-D74 -> 26 | E74: 45327
A75: Бахадыр Юрист | B75: 24 | C75: =B75-D75 -> 24 | E75: 45327
A76: Жулдыз (уборщица) | B76: 25 | C76: =B76-D76 -> 25 | E76: 45327
A77: Асем(уборщица) | B77: 24 | C77: =B77-D77 -> 6 | D77: 18 | E77: 45327
A78: Раушан(уборщица) | B78: 24 | C78: =B78-D78 -> 16 | D78: 8 | E78: 45327

Sheet Февраль 2026
A1: Имя сотрудника | B1: зарплата за февраль | C1: аванс 1 | D1: аванс 2 | E1: аванс 3 | F1: аванс 4 | G1: На ДР | H1: Штрафы | I1: не выход на работу | J1: премия и % | K1: остаток зп на Сентябрь | L1: за 1 день
A2: Аружан бывш учредитель | B2: 330000 | C2: 330000 | I2: =L2*D44 -> 0 | K2: =B2-C2-D2-E2-F2-I2+J2-G2-H2 -> 0 | L2: =B2/B44 -> 18333.333
A3: Нуртилеу директор владелец | B3: 500000 | C3: 200000 | D3: 25000 | I3: =L3*D45 -> 0 | K3: =B3-C3-D3-E3-F3-I3+J3-G3 -> 275000 | L3: =B3/B45 -> 27777.778
A4: Учебный отдел
A5: Салтанат академ дир | B5: 500000 | C5: 145000 | D5: 15000 | I5: =L5*D47 -> 0 | K5: =B5-C5-D5-E5-F5-I5+J5-G5-H5 -> 340000 | L5: =B5/B47 -> 23809.524
A6: Алуа (Онлайн) | B6: 166000 | I6: =L6*D48 -> 0 | K6: =B6-C6-D6-E6-F6-I6+J6-G6 -> 166000 | L6: =B6/B48 -> 7904.7619 | M6: онлайн
A7: Султан айлтс онлайн | B7: 63000 | I7: =L7*D53 -> 0 | K7: =B7-C7-D7-E7-F7-I7+J7-G7-H7 -> 63000 | L7: =B7/B53 -> 6300 | M7: по часам | N7: по 3 к | O7: 80 ч до 22окт
A8: Мади дженерал инглиш | B8: 114000 | I8: =L8*D51 -> 0 | K8: =B8-C8-D8-E8-F8-I8+J8-G8 -> 114000 | L8: =B8/B51 -> 5428.5714
A9: Мадина международн отд (Онлайн) | B9: 200000 | I9: =L9*D52 -> 0 | K9: =B9-C9-D9-E9-F9-I9+J9-G9 -> 200000 | L9: =B9/B52 -> 8333.3333
A10: Ванесса дженерал | B10: 105000 | I10: =L10*D54 -> 0 | K10: =B10-C10-D10-E10-F10-I10+J10-G10-H10 -> 105000 | L10: =B10/B54 -> 5000 | M10: по часам | N10: по 5 к
A11: Султан куратор | B11: 250000 | C11: 125000 | I11: =L11*D61 -> 125000 | K11: =B11-C11-D11-E11-F11-I11+J11-G11-H11 -> 0 | L11: =B11/B61 -> 10416.667
A12: Диас международн координатор | B12: 200000 | I12: =L12*D56 -> 0 | K12: =B12-C12-D12-E12-F12-I12+J12-G12 -> 200000 | L12: =B12/B56 -> 11111.111
B13: 0 | I13: =L13*D56 -> 0 | K13: =B13-C13-D13-E13-F13-I13+J13-G13 -> 0 | L13: =B13/B56 -> 0 | M13: консультация | N13: по 10 к
B14: 0 | I14: =L14*D58 -> 0 | K14: =B14-C14-D14-E14-F14-I14+J14-G14-H14 -> 0 | L14: =B14/B58 -> 0
A15: Илона айлтс | B15: 176000 | I15: 0 | K15: =B15-C15-D15-E15-F15-I15+J15-G15-H15 -> 176000 | L15: 0
B16: 0 | I16: 0 | K16: =B16-C16-D16-E16-F16-I16+J16-G16-H16 -> 0 | L16: =B16/B60 -> 0
A17: Рустам сат вербал | B17: 72000 | I17: 0 | K17: =B17-C17-D17-E17-F17-I17+J17-G17-H17 -> 72000 | L17: =B17/B61 -> 3000
A18: Аружан САТ уволилась с марта | B18: 66000 | C18: 57750 | I18: =L18*D62 -> 0 | K18: =B18-C18-D18-E18-F18-I18+J18-G18-H18 -> 8250 | L18: =B18/B62 -> 2750
A19: Касымжомарт Сат матем | B19: 203500 | K19: =B19-C19-D19-E19-F19-I19+J19-G19-H19 -> 203500
A20: Отдел продаж
A21: Мадияр РОП/Оп | B21: 200000 | I21: =L21*D60 -> 0 | J21: =IFERROR(__xludf.DUMMYFUNCTION("IMPORTRANGE(""https://docs.google.com/spreadsheets/d/1JJd44_6b1hsmD6e8liei_zzkkh-GYab6gE4K23IJPVI/edit?gid=0#gid=0&range=J95"",""'Лист1'!K556"")"),159009.1492499996) -> 159009.15 | K21: =B21-C21-D21-E21-F21-I21+J21-G21-H21 -> 359009.15 | L21: =B21/B60 -> 8333.3333
A22: Ерасыл Кц | B22: 0 | I22: =L22*D62 -> 0 | J22: 0 | K22: =B22-C22-D22-E22-F22-I22+J22-G22-H22 -> 0 | L22: =B22/B62 -> 0
B23: 0 | I23: =L23*D63 -> 0 | J23: 0 | K23: 0 | L23: =B23/B63 -> 0
A24: Дарина КЦ | B24: 100000 | C24: 35000 | I24: =L24*D64 -> 4166.6667 | J24: =42000+49200 -> 91200 | K24: =B24-C24-D24-E24-F24-I24+J24-G24-H24 -> 152033.33 | L24: =B24/B63 -> 4166.6667
I25: =L25*D65 -> 0 | K25: 0 | L25: =B25/B65 -> 0
A26: Маркетинг
B27: 0 | I27: =L27*D67 -> 0 | K27: =B27-C27-D27-E27-F27-I27+J27-G27-H27 -> 0 | L27: =B27/B67 -> 0 | M27: c 15
B28: 0 | I28: 0 | K28: =B28-C28-D28-E28-F28-I28+J28-G28-H28 -> 0 | L28: =B28/B68 -> 0 | M28: c 6
B29: 0 | I29: =L29*D69 -> 0 | K29: =B29-C29-D29-E29-F29-I29+J29-G29-H29 -> 0 | L29: =B29/B69 -> 0 | M29: 23 ого октября
B30: 0 | I30: =L30*D70 -> 0 | K30: =B30-C30-D30-E30-F30-I30+J30-G30-H30 -> 0 | L30: =B30/B70 -> 0 | M30: c 10
A31: БЭК Офис
A32: Камила Офис менеджер | B32: 250000 | C32: 150000 | I32: =L32*D73 -> 15625 | K32: =B32-C32-D32-E32-F32-I32+J32-G32-H32 -> 84375 | L32: =B32/B73 -> 10416.667
A33: Гульжахан Бухгалтер | B33: 150000 | I33: =L33*D74 -> 0 | K33: =B33-C33-D33-E33-F33-I33+J33-G33-H33 -> 150000 | L33: =B33/B74 -> 6250
A35: Асем уборщица | B35: 80000 | C35: 80000 | I35: =L35*D77 -> 0 | K35: =B35-C35-D35-E35-F35-I35+J35-G35-H35 -> 0 | L35: =B35/B77 -> 3333.3333
A37: Общ | B37: =SUM(B2:B34) -> 3645500 | C37: =B37+J21+J23 -> 3804509.1 | K37: =SUM(K2:K35) -> 2668167.5
L42: =K43-'Февраль'!K4-'Март'!K5-'Апрель'!K5-'Май'!K5-'Июнь 2025'!K5-'Июль 2025'!K5-K5 -> 4948017.9
A43: ФИО | B43: рабочие дни за март | C43: отработано | D43: Дни отсутствия | E43: график работы | J43: долг по остаткам зп: | K43: ='Февраль'!K34+'Март'!K38+'Апрель'!K35+'Май'!K33+'Июнь 2025'!K29+'Июль 2025'!K31+'Август 2025'!K31+'Сентябрь 2025'!K31+'Октябрь 2025'!K36+'Ноябрь 2025'!K37+K37 -> 6668017.9
A44: Аружан | B44: 18 | C44: =B44-D44 -> 18 | D44: 0 | E44: 45327
A45: Нуртилеу | B45: 18 | C45: =B45-D45 -> 18 | D45: 0 | E45: 45327 | J45: долг компании | K45: =K46+K47+K48+K49+K50 -> 11912189
A46: Учебный отдел | J46: жанерке долг | K46: 3400000
A47: Салтанат | B47: 21 | C47: =B47-D47 -> 21 | D47: 0 | E47: 45327 | J47: Аружан долг | K47: =4632189-700000-300000-700000-300000-270000-60000-220000-110000-330000-330000 -> 1312189
A48: Алуа (Онлайн) | B48: 21 | C48: =B48-D48 -> 21 | D48: 0 | E48: 45327 | J48: Нуртилеу кредит | K48: 2000000
A49: Султан | B49: 21 | C49: =B49-D49 -> 21 | D49: 0 | E49: 45327 | J49: Салтанат долг | K49: 3000000
A50: Мади | B50: 21 | C50: =B50-D50 -> 21 | D50: 0 | E50: 45297 | J50: долг Папа Мадияра | K50: 2200000
A51: Мадина международн отд (Онлайн) | B51: 21 | C51: =B51-D51 -> 21 | D51: 0 | E51: 45327
A52: Мерей Сат | B52: 24 | C52: =B52-D52 -> 24 | E52: 45327 | J52: налог | K52: 1500000
A53: Динара колл центр | B53: 10 | C53: =B53-D53 -> 10 | D53: 0 | E53: 45327
A54: Диас международн | B54: 21 | C54: =B54-D54 -> 21 | D54: 0 | E54: 45297
A55: Алтынбек Проф ориентолог | B55: 10 | C55: =B55-D55 -> 10 | D55: 0 | E55: 45327 | J55: возвратники | K55: =SUM(K56:K59) -> 800000
A56: Дильяра | B56: 18 | C56: =B56-D56 -> 18 | D56: 0 | E56: 45327
A57: - | B57: 18 | C57: =B57-D57 -> 18 | D57: 0 | E57: 45327 | J57: Лаура | K57: =1000000-100000-100000 -> 800000
A58: - | B58: 18 | C58: =B58-D58 -> 18 | D58: 0 | E58: 45327
A59: Отдел продаж
A60: Мадияр РОП | B60: 24 | C60: =B60-D60 -> 24 | D60: 0 | E60: 45297
A61: Султан Куратора | B61: 24 | C61: =B61-D61 -> 12 | D61: 12 | E61: 45297
A62: Инжу | B62: 24 | C62: =B62-D62 -> 24 | D62: 0 | E62: 45297
A63: Анель ОП | B63: 24 | C63: =B63-D63 -> 18 | D63: 6 | E63: 45297
A64: Дарина | B64: 24 | C64: =B64-D64 -> 23 | D64: 1
A65: Али ОП | B65: 24 | C65: =B65-D65 -> 24 | D65: 0 | E65: 45297
A66: Маркетинг
A67: Нурым | B67: 29 | C67: =B67-D67 -> 29 | D67: 0 | E67: 45297
A68: СММ Бота | B68: 29 | C68: =B68-D68 -> 24 | D68: 5 | E68: 45297
A69: Жангелди | B69: 29 | C69: =B69-D69 -> 29 | D69: 0 | E69: 45327
A70: Амина Дизайнер | B70: 29 | C70: =B70-D70 -> 20 | D70: 9 | E70: 45327
A71: Алена | B71: 29 | C71: =B71-D71 -> 29 | D71: 0 | E71: 45327
A72: БЭК Офис
A73: Камила Офис менеджер | B73: 24 | C73: =B73-D73 -> 22.5 | D73: 1.5 | E73: 45297
A74: Гульжахан Бухгалтер | B74: 24 | C74: =B74-D74 -> 24 | E74: 45327
A75: Бахадыр Юрист | B75: 24 | C75: =B75-D75 -> 24 | E75: 45327
A76: Жулдыз (уборщица) | B76: 24 | C76: =B76-D76 -> 24 | E76: 45327
A77: Асем(уборщица) | B77: 24 | C77: =B77-D77 -> 24 | D77: 0 | E77: 45327

Sheet Март 2026
A1: Имя сотрудника | B1: зарплата за февраль | C1: аванс 1 | D1: аванс 2 | E1: аванс 3 | F1: аванс 4 | G1: На ДР | H1: Штрафы | I1: не выход на работу | J1: премия и % | K1: остаток зп на Сентябрь | L1: за 1 день
A2: Аружан | B2: 330000 | I2: =L2*D44 -> 0 | K2: =B2-C2-D2-E2-F2-I2+J2-G2-H2 -> 330000 | L2: =B2/B44 -> 18333.333
A3: Нуртилеу | B3: 500000 | C3: =55000+83333 -> 138333 | I3: =L3*D45 -> 0 | K3: =B3-C3-D3-E3-F3-I3+J3-G3 -> 361667 | L3: =B3/B45 -> 27777.778
A4: Учебный отдел
A5: Салтанат | B5: 500000 | C5: 145000 | D5: 15000 | I5: =L5*D47 -> 0 | K5: =B5-C5-D5-E5-F5-I5+J5-G5-H5 -> 340000 | L5: =B5/B47 -> 23809.524
A6: Алуа (Онлайн) | B6: 152250 | I6: =L6*D48 -> 0 | K6: =B6-C6-D6-E6-F6-I6+J6-G6 -> 152250 | L6: =B6/B48 -> 7250 | M6: онлайн
A7: Султан | B7: =75000+59500 -> 134500 | I7: =L7*D53 -> 0 | K7: =B7-C7-D7-E7-F7-I7+J7-G7-H7 -> 134500 | L7: =B7/B53 -> 13450 | M7: по часам | N7: по 3 к | O7: 80 ч до 22окт
A8: Мади | B8: 80000 | I8: =L8*D51 -> 0 | K8: =B8-C8-D8-E8-F8-I8+J8-G8 -> 80000 | L8: =B8/B51 -> 3809.5238
A9: Мадина международн отд (Онлайн) | B9: 200000 | I9: =L9*D52 -> 0 | K9: =B9-C9-D9-E9-F9-I9+J9-G9 -> 200000 | L9: =B9/B52 -> 7692.3077
A10: Ванесса | B10: 96000 | I10: =L10*D54 -> 0 | K10: =B10-C10-D10-E10-F10-I10+J10-G10-H10 -> 96000 | L10: =B10/B54 -> 4571.4286 | M10: по часам | N10: по 5 к
A11: Султан куратор | B11: 250000 | I11: =L11*D61 -> 0 | K11: =B11-C11-D11-E11-F11-I11+J11-G11-H11 -> 250000 | L11: =B11/B61 -> 9615.3846
A12: Диас международн | B12: 200000 | I12: =L12*D56 -> 0 | K12: =B12-C12-D12-E12-F12-I12+J12-G12 -> 200000 | L12: =B12/B56 -> 11111.111
A13: Циньгун | B13: 0 | I13: =L13*D56 -> 0 | K13: =B13-C13-D13-E13-F13-I13+J13-G13 -> 0 | L13: =B13/B56 -> 0 | M13: консультация | N13: по 10 к
A14: Дильяра | B14: 0 | I14: =L14*D58 -> 0 | K14: =B14-C14-D14-E14-F14-I14+J14-G14-H14 -> 0 | L14: =B14/B58 -> 0
A15: Илона | B15: 222000 | I15: 0 | K15: =B15-C15-D15-E15-F15-I15+J15-G15-H15 -> 222000 | L15: 0
A16: Сулейман | B16: 0 | I16: 0 | K16: =B16-C16-D16-E16-F16-I16+J16-G16-H16 -> 0 | L16: =B16/B60 -> 0
A17: Рустам | B17: 70000 | I17: 0 | K17: =B17-C17-D17-E17-F17-I17+J17-G17-H17 -> 70000 | L17: =B17/B61 -> 2692.3077
A18: Абдулазиз | B18: 0 | I18: =L18*D62 -> 0 | K18: =B18-C18-D18-E18-F18-I18+J18-G18-H18 -> 0 | L18: =B18/B62 -> 0
A19: Касымжомарт | B19: 254000 | K19: =B19-C19-D19-E19-F19-I19+J19-G19-H19 -> 254000
A20: Отдел продаж
A21: Мадияр РОП | B21: 200000 | I21: =L21*D60 -> 0 | J21: =IFERROR(__xludf.DUMMYFUNCTION("IMPORTRANGE(""https://docs.google.com/spreadsheets/d/1JJd44_6b1hsmD6e8liei_zzkkh-GYab6gE4K23IJPVI/edit?gid=0#gid=0&range=J95"",""'Лист1'!K583"")"),44076.780000000166) -> 44076.78 | K21: =B21-C21-D21-E21-F21-I21+J21-G21-H21 -> 244076.78 | L21: =B21/B60 -> 7692.3077
A22: Инжу КЦ | B22: 0 | I22: =L22*D62 -> 0 | J22: 0 | K22: =B22-C22-D22-E22-F22-I22+J22-G22-H22 -> 0 | L22: =B22/B62 -> 0
A23: Анель ОП | B23: 0 | I23: =L23*D63 -> 0 | J23: 0 | K23: 0 | L23: =B23/B63 -> 0
A24: Дарина КЦ | B24: 100000 | I24: =L24*D64 -> 0 | J24: 160000 | K24: =B24-C24-D24-E24-F24-I24+J24-G24-H24 -> 260000
I25: =L25*D65 -> 0 | K25: 0 | L25: =B25/B65 -> 0
A26: Маркетинг
A27: Нурым | B27: 0 | I27: =L27*D67 -> 0 | K27: =B27-C27-D27-E27-F27-I27+J27-G27-H27 -> 0 | L27: =B27/B67 -> 0 | M27: c 15
A28: Точка роста | B28: 0 | I28: 0 | K28: =B28-C28-D28-E28-F28-I28+J28-G28-H28 -> 0 | L28: =B28/B68 -> 0 | M28: c 6
A29: Жангелди | B29: 0 | I29: =L29*D69 -> 0 | K29: =B29-C29-D29-E29-F29-I29+J29-G29-H29 -> 0 | L29: =B29/B69 -> 0 | M29: 23 ого октября
A30: Амина Дизайнер | B30: 0 | I30: =L30*D70 -> 0 | K30: =B30-C30-D30-E30-F30-I30+J30-G30-H30 -> 0 | L30: =B30/B70 -> 0 | M30: c 10
A31: БЭК Офис
A32: Камила Офис менеджер | B32: 250000 | C32: 150000 | I32: =L32*D73 -> 14423.077 | K32: =B32-C32-D32-E32-F32-I32+J32-G32-H32 -> 85576.923 | L32: =B32/B73 -> 9615.3846
A33: Гульжахан Бухгалтер | B33: 150000 | I33: =L33*D74 -> 0 | K33: =B33-C33-D33-E33-F33-I33+J33-G33-H33 -> 150000 | L33: =B33/B74 -> 5769.2308
A35: Асем уборщица | B35: 80000 | I35: =L35*D77 -> 0 | K35: =B35-C35-D35-E35-F35-I35+J35-G35-H35 -> 80000 | L35: =B35/B77 -> 3333.3333
A37: Общ | B37: =SUM(B2:B34) -> 3688750 | C37: =B37+J21+J23 -> 3732826.8 | K37: =SUM(K2:K35) -> 3510070.7
L42: =K43-'Февраль'!K4-'Март'!K5-'Апрель'!K5-'Май'!K5-'Июнь 2025'!K5-'Июль 2025'!K5-K5 -> 5789921.1
A43: ФИО | B43: рабочие дни за март | C43: отработано | D43: Дни отсутствия | E43: график работы | J43: долг по зп: | K43: ='Февраль'!K34+'Март'!K38+'Апрель'!K35+'Май'!K33+'Июнь 2025'!K29+'Июль 2025'!K31+'Август 2025'!K31+'Сентябрь 2025'!K31+'Октябрь 2025'!K36+'Ноябрь 2025'!K37+K37 -> 7509921.1
A44: Аружан | B44: 18 | C44: =B44-D44 -> 18 | D44: 0 | E44: 45327
A45: Нуртилеу | B45: 18 | C45: =B45-D45 -> 18 | D45: 0 | E45: 45327 | J45: долг по кредитам: | K45: =K46+K47+K48+K49+K50 -> 11912189
A46: Учебный отдел | J46: жанерке | K46: 3400000
A47: Салтанат | B47: 21 | C47: =B47-D47 -> 21 | D47: 0 | E47: 45327 | J47: Аружан | K47: =4632189-700000-300000-700000-300000-270000-60000-220000-110000-330000-330000 -> 1312189
A48: Алуа (Онлайн) | B48: 21 | C48: =B48-D48 -> 21 | D48: 0 | E48: 45327 | J48: Нуртилеу | K48: 2000000
A49: Султан | B49: 21 | C49: =B49-D49 -> 21 | D49: 0 | E49: 45327 | J49: Салтанат | K49: 3000000
A50: Мади | B50: 21 | C50: =B50-D50 -> 21 | D50: 0 | E50: 45297 | J50: Папа Мадияра | K50: 2200000
A51: Мадина международн отд (Онлайн) | B51: 21 | C51: =B51-D51 -> 21 | D51: 0 | E51: 45327
A52: Мерей Сат | B52: 26 | C52: =B52-D52 -> 26 | E52: 45327 | J52: налог | K52: 1500000
A53: Динара колл центр | B53: 10 | C53: =B53-D53 -> 10 | D53: 0 | E53: 45327
A54: Диас международн | B54: 21 | C54: =B54-D54 -> 21 | D54: 0 | E54: 45297
A55: Алтынбек Проф ориентолог | B55: 10 | C55: =B55-D55 -> 10 | D55: 0 | E55: 45327 | J55: возвратники | K55: =SUM(K56:K59) -> 800000
A56: Дильяра | B56: 18 | C56: =B56-D56 -> 18 | D56: 0 | E56: 45327
A57: - | B57: 18 | C57: =B57-D57 -> 18 | D57: 0 | E57: 45327 | J57: Лаура | K57: =1000000-100000-100000 -> 800000
A58: - | B58: 18 | C58: =B58-D58 -> 18 | D58: 0 | E58: 45327
A59: Отдел продаж
A60: Мадияр РОП | B60: 26 | C60: =B60-D60 -> 26 | D60: 0 | E60: 45297
A61: Динара колл центр | B61: 26 | C61: =B61-D61 -> 26 | D61: 0 | E61: 45297
A62: Инжу | B62: 26 | C62: =B62-D62 -> 26 | D62: 0 | E62: 45297
A63: Анель ОП | B63: 26 | C63: =B63-D63 -> 20 | D63: 6 | E63: 45297
A64: Дарина | B64: 26 | C64: =B64-D64 -> 23 | D64: 3
A65: Али ОП | B65: 26 | C65: =B65-D65 -> 26 | D65: 0 | E65: 45297
A66: Маркетинг
A67: Нурым | B67: 29 | C67: =B67-D67 -> 29 | D67: 0 | E67: 45297
A68: СММ Бота | B68: 29 | C68: =B68-D68 -> 24 | D68: 5 | E68: 45297
A69: Жангелди | B69: 29 | C69: =B69-D69 -> 29 | D69: 0 | E69: 45327
A70: Амина Дизайнер | B70: 29 | C70: =B70-D70 -> 20 | D70: 9 | E70: 45327
A71: Алена | B71: 29 | C71: =B71-D71 -> 29 | D71: 0 | E71: 45327
A72: БЭК Офис
A73: Камила Офис менеджер | B73: 26 | C73: =B73-D73 -> 24.5 | D73: 1.5 | E73: 45297
A74: Гульжахан Бухгалтер | B74: 26 | C74: =B74-D74 -> 26 | E74: 45327
A75: Бахадыр Юрист | B75: 24 | C75: =B75-D75 -> 24 | E75: 45327
A76: Жулдыз (уборщица) | B76: 25 | C76: =B76-D76 -> 25 | E76: 45327
A77: Асем(уборщица) | B77: 24 | C77: =B77-D77 -> 24 | D77: 0 | E77: 45327
